Workbook
Name CadastroEquipes: Equipes!$A$2:$A$1000

Sheet Atualização
A1: ATUALIZAÇÃO SEMANAL — FILA DE LIGAS
A2: Controle histórico: manter até 15 partidas por equipe em Dados · cálculos usam as 12 mais recentes · atualizações organizadas em blocos por liga
A4: FLUXO OPERACIONAL
A5: 1. Priorizar ligas com status REVISAR · 2. Buscar resultados concluídos nas fontes indicadas · 3. Padronizar nomes e horários · 4. Inserir somente chaves novas · 5. Durante cada atualização, manter os registros da liga juntos e inserir os jogos do mais antigo para o mais recente · 6. Manter até 15 jogos por equipe em Dados · 7. Recalcular as marcações da janela ativa de 12 · 8. Auditar duplicidades, placares e fórmulas.
A8: STATUS DA BASE
A9: =COUNTIF(H15:H111,"OK — 12+")&" ligas completas" -> 31 ligas completas | E9: =COUNTIF(H15:H111,"REVISAR")&" ligas para revisar" -> 8 ligas para revisar | I9: Último jogo na base
I10: =MAX(G15:G111) -> 46247
A13: FILA DETALHADA
A14: País | B14: Liga | C14: Perfil | D14: Partidas | E14: Equipes | F14: Mín. jogos/equipe | G14: Último jogo | H14: Status | I14: Fonte sugerida | J14: Ação
A15: ARG | B15: Liga Profesional | C15: Poucos Gols | D15: =COUNTIFS(tblDados[País],A15,tblDados[Liga],B15,tblDados[Janela_12_Liga],1) -> 4 | E15: {=IFERROR(ROWS(_xlfn.UNIQUE(_xlfn.VSTACK(_xlfn._xlws.FILTER(tblDados[Mandante],(tblDados[País]=A15)*(tblDados[Liga]=B15)*(tblDados[Janela_12_Liga]=1)),_xlfn._xlws.FILTER(tblDados[Visitante],(tblDados[País]=A15)*(tblDados[Liga]=B15)*(tblDados[Janela_12_Liga]=1))))),0)} -> 8 | F15: {=_xlfn.LET(_xlpm.p,A15,_xlpm.l,B15,_xlpm.t,_xlfn.UNIQUE(_xlfn.VSTACK(_xlfn._xlws.FILTER(tblDados[Mandante],(tblDados[País]=_xlpm.p)*(tblDados[Liga]=_xlpm.l)*(tblDados[Janela_12_Liga]=1)),_xlfn._xlws.FILTER(tblDados[Visitante],(tblDados[País]=_xlpm.p)*(tblDados[Liga]=_xlpm.l)*(tblDados[Janela_12_Liga]=1)))),IFERROR(MIN(_xlfn.MAP(_xlpm.t,_xlfn.LAMBDA(_xlpm.x,SUMPRODUCT((tblDados[Mandante]=_xlpm.x)*(tblDados[País]=_xlpm.p)*(tblDados[Liga]=_xlpm.l)*tblDados[Janela_12_Mandante])+SUMPRODUCT((tblDados[Visitante]=_xlpm.x)*(tblDados[País]=_xlpm.p)*(tblDados[Liga]=_xlpm.l)*tblDados[Janela_12_Visitante])))),0))} -> 1 | G15: =IFERROR(_xlfn.MAXIFS(tblDados[Data],tblDados[País],A15,tblDados[Liga],B15,tblDados[Janela_12_Liga],1),"") -> 46230 | H15: =IF(F15>=12,"OK — 12+","REVISAR") -> REVISAR | I15: WorldFootball · Futbol24 · Flashscore | J15: =IF(H15="OK — 12+","Manutenção semanal","Completar janela") -> Completar janela
A16: ARG | B16: Primera Nacional | C16: Poucos Gols | D16: =COUNTIFS(tblDados[País],A16,tblDados[Liga],B16,tblDados[Janela_12_Liga],1) -> 2 | E16: {=IFERROR(ROWS(_xlfn.UNIQUE(_xlfn.VSTACK(_xlfn._xlws.FILTER(tblDados[Mandante],(tblDados[País]=A16)*(tblDados[Liga]=B16)*(tblDados[Janela_12_Liga]=1)),_xlfn._xlws.FILTER(tblDados[Visitante],(tblDados[País]=A16)*(tblDados[Liga]=B16)*(tblDados[Janela_12_Liga]=1))))),0)} -> 4 | F16: {=_xlfn.LET(_xlpm.p,A16,_xlpm.l,B16,_xlpm.t,_xlfn.UNIQUE(_xlfn.VSTACK(_xlfn._xlws.FILTER(tblDados[Mandante],(tblDados[País]=_xlpm.p)*(tblDados[Liga]=_xlpm.l)*(tblDados[Janela_12_Liga]=1)),_xlfn._xlws.FILTER(tblDados[Visitante],(tblDados[País]=_xlpm.p)*(tblDados[Liga]=_xlpm.l)*(tblDados[Janela_12_Liga]=1)))),IFERROR(MIN(_xlfn.MAP(_xlpm.t,_xlfn.LAMBDA(_xlpm.x,SUMPRODUCT((tblDados[Mandante]=_xlpm.x)*(tblDados[País]=_xlpm.p)*(tblDados[Liga]=_xlpm.l)*tblDados[Janela_12_Mandante])+SUMPRODUCT((tblDados[Visitante]=_xlpm.x)*(tblDados[País]=_xlpm.p)*(tblDados[Liga]=_xlpm.l)*tblDados[Janela_12_Visitante])))),0))} -> 1 | G16: =IFERROR(_xlfn.MAXIFS(tblDados[Data],tblDados[País],A16,tblDados[Liga],B16,tblDados[Janela_12_Liga],1),"") -> 46230 | H16: =IF(F16>=12,"OK — 12+","REVISAR") -> REVISAR | I16: WorldFootball · Futbol24 · Flashscore | J16: =IF(H16="OK — 12+","Manutenção semanal","Completar janela") -> Completar janela
A17: BOL | B17: Div. Profesional | C17: Muitos Gols | D17: =COUNTIFS(tblDados[País],A17,tblDados[Liga],B17,tblDados[Janela_12_Liga],1) -> 97 | E17: {=IFERROR(ROWS(_xlfn.UNIQUE(_xlfn.VSTACK(_xlfn._xlws.FILTER(tblDados[Mandante],(tblDados[País]=A17)*(tblDados[Liga]=B17)*(tblDados[Janela_12_Liga]=1)),_xlfn._xlws.FILTER(tblDados[Visitante],(tblDados[País]=A17)*(tblDados[Liga]=B17)*(tblDados[Janela_12_Liga]=1))))),0)} -> 16 | F17: {=_xlfn.LET(_xlpm.p,A17,_xlpm.l,B17,_xlpm.t,_xlfn.UNIQUE(_xlfn.VSTACK(_xlfn._xlws.FILTER(tblDados[Mandante],(tblDados[País]=_xlpm.p)*(tblDados[Liga]=_xlpm.l)*(tblDados[Janela_12_Liga]=1)),_xlfn._xlws.FILTER(tblDados[Visitante],(tblDados[País]=_xlpm.p)*(tblDados[Liga]=_xlpm.l)*(tblDados[Janela_12_Liga]=1)))),IFERROR(MIN(_xlfn.MAP(_xlpm.t,_xlfn.LAMBDA(_xlpm.x,SUMPRODUCT((tblDados[Mandante]=_xlpm.x)*(tblDados[País]=_xlpm.p)*(tblDados[Liga]=_xlpm.l)*tblDados[Janela_12_Mandante])+SUMPRODUCT((tblDados[Visitante]=_xlpm.x)*(tblDados[País]=_xlpm.p)*(tblDados[Liga]=_xlpm.l)*tblDados[Janela_12_Visitante])))),0))} -> 12 | G17: =IFERROR(_xlfn.MAXIFS(tblDados[Data],tblDados[País],A17,tblDados[Liga],B17,tblDados[Janela_12_Liga],1),"") -> 46243 | H17: =IF(F17>=12,"OK — 12+","REVISAR") -> OK — 12+ | I17: WorldFootball · Futbol24 · Flashscore | J17: =IF(H17="OK — 12+","Manutenção semanal","Completar janela") -> Manutenção semanal
A18: BRA | B18: Série A | C18: Equilibrada | D18: =COUNTIFS(tblDados[País],A18,tblDados[Liga],B18,tblDados[Janela_12_Liga],1) -> 124 | E18: {=IFERROR(ROWS(_xlfn.UNIQUE(_xlfn.VSTACK(_xlfn._xlws.FILTER(tblDados[Mandante],(tblDados[País]=A18)*(tblDados[Liga]=B18)*(tblDados[Janela_12_Liga]=1)),_xlfn._xlws.FILTER(tblDados[Visitante],(tblDados[País]=A18)*(tblDados[Liga]=B18)*(tblDados[Janela_12_Liga]=1))))),0)} -> 20 | F18: {=_xlfn.LET(_xlpm.p,A18,_xlpm.l,B18,_xlpm.t,_xlfn.UNIQUE(_xlfn.VSTACK(_xlfn._xlws.FILTER(tblDados[Mandante],(tblDados[País]=_xlpm.p)*(tblDados[Liga]=_xlpm.l)*(tblDados[Janela_12_Liga]=1)),_xlfn._xlws.FILTER(tblDados[Visitante],(tblDados[País]=_xlpm.p)*(tblDados[Liga]=_xlpm.l)*(tblDados[Janela_12_Liga]=1)))),IFERROR(MIN(_xlfn.MAP(_xlpm.t,_xlfn.LAMBDA(_xlpm.x,SUMPRODUCT((tblDados[Mandante]=_xlpm.x)*(tblDados[País]=_xlpm.p)*(tblDados[Liga]=_xlpm.l)*tblDados[Janela_12_Mandante])+SUMPRODUCT((tblDados[Visitante]=_xlpm.x)*(tblDados[País]=_xlpm.p)*(tblDados[Liga]=_xlpm.l)*tblDados[Janela_12_Visitante])))),0))} -> 12 | G18: =IFERROR(_xlfn.MAXIFS(tblDados[Data],tblDados[País],A18,tblDados[Liga],B18,tblDados[Janela_12_Liga],1),"") -> 46233 | H18: =IF(F18>=12,"OK — 12+","REVISAR") -> OK — 12+ | I18: WorldFootball · Futbol24 · Flashscore | J18: =IF(H18="OK — 12+","Manutenção semanal","Completar janela") -> Manutenção semanal
A19: BRA | B19: Série B | C19: Poucos Gols | D19: =COUNTIFS(tblDados[País],A19,tblDados[Liga],B19,tblDados[Janela_12_Liga],1) -> 120 | E19: {=IFERROR(ROWS(_xlfn.UNIQUE(_xlfn.VSTACK(_xlfn._xlws.FILTER(tblDados[Mandante],(tblDados[País]=A19)*(tblDados[Liga]=B19)*(tblDados[Janela_12_Liga]=1)),_xlfn._xlws.FILTER(tblDados[Visitante],(tblDados[País]=A19)*(tblDados[Liga]=B19)*(tblDados[Janela_12_Liga]=1))))),0)} -> 20 | F19: {=_xlfn.LET(_xlpm.p,A19,_xlpm.l,B19,_xlpm.t,_xlfn.UNIQUE(_xlfn.VSTACK(_xlfn._xlws.FILTER(tblDados[Mandante],(tblDados[País]=_xlpm.p)*(tblDados[Liga]=_xlpm.l)*(tblDados[Janela_12_Liga]=1)),_xlfn._xlws.FILTER(tblDados[Visitante],(tblDados[País]=_xlpm.p)*(tblDados[Liga]=_xlpm.l)*(tblDados[Janela_12_Liga]=1)))),IFERROR(MIN(_xlfn.MAP(_xlpm.t,_xlfn.LAMBDA(_xlpm.x,SUMPRODUCT((tblDados[Mandante]=_xlpm.x)*(tblDados[País]=_xlpm.p)*(tblDados[Liga]=_xlpm.l)*tblDados[Janela_12_Mandante])+SUMPRODUCT((tblDados[Visitante]=_xlpm.x)*(tblDados[País]=_xlpm.p)*(tblDados[Liga]=_xlpm.l)*tblDados[Janela_12_Visitante])))),0))} -> 12 | G19: =IFERROR(_xlfn.MAXIFS(tblDados[Data],tblDados[País],A19,tblDados[Liga],B19,tblDados[Janela_12_Liga],1),"") -> 46245 | H19: =IF(F19>=12,"OK — 12+","REVISAR") -> OK — 12+ | I19: WorldFootball · Futbol24 · Flashscore | J19: =IF(H19="OK — 12+","Manutenção semanal","Completar janela") -> Manutenção semanal
A20: BRA | B20: Série C | C20: Poucos Gols | D20: =COUNTIFS(tblDados[País],A20,tblDados[Liga],B20,tblDados[Janela_12_Liga],1) -> 121 | E20: {=IFERROR(ROWS(_xlfn.UNIQUE(_xlfn.VSTACK(_xlfn._xlws.FILTER(tblDados[Mandante],(tblDados[País]=A20)*(tblDados[Liga]=B20)*(tblDados[Janela_12_Liga]=1)),_xlfn._xlws.FILTER(tblDados[Visitante],(tblDados[País]=A20)*(tblDados[Liga]=B20)*(tblDados[Janela_12_Liga]=1))))),0)} -> 20 | F20: {=_xlfn.LET(_xlpm.p,A20,_xlpm.l,B20,_xlpm.t,_xlfn.UNIQUE(_xlfn.VSTACK(_xlfn._xlws.FILTER(tblDados[Mandante],(tblDados[País]=_xlpm.p)*(tblDados[Liga]=_xlpm.l)*(tblDados[Janela_12_Liga]=1)),_xlfn._xlws.FILTER(tblDados[Visitante],(tblDados[País]=_xlpm.p)*(tblDados[Liga]=_xlpm.l)*(tblDados[Janela_12_Liga]=1)))),IFERROR(MIN(_xlfn.MAP(_xlpm.t,_xlfn.LAMBDA(_xlpm.x,SUMPRODUCT((tblDados[Mandante]=_xlpm.x)*(tblDados[País]=_xlpm.p)*(tblDados[Liga]=_xlpm.l)*tblDados[Janela_12_Mandante])+SUMPRODUCT((tblDados[Visitante]=_xlpm.x)*(tblDados[País]=_xlpm.p)*(tblDados[Liga]=_xlpm.l)*tblDados[Janela_12_Visitante])))),0))} -> 12 | G20: =IFERROR(_xlfn.MAXIFS(tblDados[Data],tblDados[País],A20,tblDados[Liga],B20,tblDados[Janela_12_Liga],1),"") -> 46244 | H20: =IF(F20>=12,"OK — 12+","REVISAR") -> OK — 12+ | I20: WorldFootball · Futbol24 · Flashscore | J20: =IF(H20="OK — 12+","Manutenção semanal","Completar janela") -> Manutenção semanal
A21: CAN | B21: Premier League | C21: Equilibrada | D21: =COUNTIFS(tblDados[País],A21,tblDados[Liga],B21,tblDados[Janela_12_Liga],1) -> 49 | E21: {=IFERROR(ROWS(_xlfn.UNIQUE(_xlfn.VSTACK(_xlfn._xlws.FILTER(tblDados[Mandante],(tblDados[País]=A21)*(tblDados[Liga]=B21)*(tblDados[Janela_12_Liga]=1)),_xlfn._xlws.FILTER(tblDados[Visitante],(tblDados[País]=A21)*(tblDados[Liga]=B21)*(tblDados[Janela_12_Liga]=1))))),0)} -> 8 | F21: {=_xlfn.LET(_xlpm.p,A21,_xlpm.l,B21,_xlpm.t,_xlfn.UNIQUE(_xlfn.VSTACK(_xlfn._xlws.FILTER(tblDados[Mandante],(tblDados[País]=_xlpm.p)*(tblDados[Liga]=_xlpm.l)*(tblDados[Janela_12_Liga]=1)),_xlfn._xlws.FILTER(tblDados[Visitante],(tblDados[País]=_xlpm.p)*(tblDados[Liga]=_xlpm.l)*(tblDados[Janela_12_Liga]=1)))),IFERROR(MIN(_xlfn.MAP(_xlpm.t,_xlfn.LAMBDA(_xlpm.x,SUMPRODUCT((tblDados[Mandante]=_xlpm.x)*(tblDados[País]=_xlpm.p)*(tblDados[Liga]=_xlpm.l)*tblDados[Janela_12_Mandante])+SUMPRODUCT((tblDados[Visitante]=_xlpm.x)*(tblDados[País]=_xlpm.p)*(tblDados[Liga]=_xlpm.l)*tblDados[Janela_12_Visitante])))),0))} -> 12 | G21: =IFERROR(_xlfn.MAXIFS(tblDados[Data],tblDados[País],A21,tblDados[Liga],B21,tblDados[Janela_12_Liga],1),"") -> 46242 | H21: =IF(F21>=12,"OK — 12+","REVISAR") -> OK — 12+ | I21: WorldFootball · Futbol24 · Flashscore | J21: =IF(H21="OK — 12+","Manutenção semanal","Completar janela") -> Manutenção semanal
A22: CHI | B22: Liga de Primera | C22: Equilibrada | D22: =COUNTIFS(tblDados[País],A22,tblDados[Liga],B22,tblDados[Janela_12_Liga],1) -> 98 | E22: {=IFERROR(ROWS(_xlfn.UNIQUE(_xlfn.VSTACK(_xlfn._xlws.FILTER(tblDados[Mandante],(tblDados[País]=A22)*(tblDados[Liga]=B22)*(tblDados[Janela_12_Liga]=1)),_xlfn._xlws.FILTER(tblDados[Visitante],(tblDados[País]=A22)*(tblDados[Liga]=B22)*(tblDados[Janela_12_Liga]=1))))),0)} -> 16 | F22: {=_xlfn.LET(_xlpm.p,A22,_xlpm.l,B22,_xlpm.t,_xlfn.UNIQUE(_xlfn.VSTACK(_xlfn._xlws.FILTER(tblDados[Mandante],(tblDados[País]=_xlpm.p)*(tblDados[Liga]=_xlpm.l)*(tblDados[Janela_12_Liga]=1)),_xlfn._xlws.FILTER(tblDados[Visitante],(tblDados[País]=_xlpm.p)*(tblDados[Liga]=_xlpm.l)*(tblDados[Janela_12_Liga]=1)))),IFERROR(MIN(_xlfn.MAP(_xlpm.t,_xlfn.LAMBDA(_xlpm.x,SUMPRODUCT((tblDados[Mandante]=_xlpm.x)*(tblDados[País]=_xlpm.p)*(tblDados[Liga]=_xlpm.l)*tblDados[Janela_12_Mandante])+SUMPRODUCT((tblDados[Visitante]=_xlpm.x)*(tblDados[País]=_xlpm.p)*(tblDados[Liga]=_xlpm.l)*tblDados[Janela_12_Visitante])))),0))} -> 12 | G22: =IFERROR(_xlfn.MAXIFS(tblDados[Data],tblDados[País],A22,tblDados[Liga],B22,tblDados[Janela_12_Liga],1),"") -> 46244 | H22: =IF(F22>=12,"OK — 12+","REVISAR") -> OK — 12+ | I22: WorldFootball · Futbol24 · Flashscore | J22: =IF(H22="OK — 12+","Manutenção semanal","Completar janela") -> Manutenção semanal
A23: ECU | B23: LigaPro Serie A | C23: Equilibrada | D23: =COUNTIFS(tblDados[País],A23,tblDados[Liga],B23,tblDados[Janela_12_Liga],1) -> 96 | E23: {=IFERROR(ROWS(_xlfn.UNIQUE(_xlfn.VSTACK(_xlfn._xlws.FILTER(tblDados[Mandante],(tblDados[País]=A23)*(tblDados[Liga]=B23)*(tblDados[Janela_12_Liga]=1)),_xlfn._xlws.FILTER(tblDados[Visitante],(tblDados[País]=A23)*(tblDados[Liga]=B23)*(tblDados[Janela_12_Liga]=1))))),0)} -> 16 | F23: {=_xlfn.LET(_xlpm.p,A23,_xlpm.l,B23,_xlpm.t,_xlfn.UNIQUE(_xlfn.VSTACK(_xlfn._xlws.FILTER(tblDados[Mandante],(tblDados[País]=_xlpm.p)*(tblDados[Liga]=_xlpm.l)*(tblDados[Janela_12_Liga]=1)),_xlfn._xlws.FILTER(tblDados[Visitante],(tblDados[País]=_xlpm.p)*(tblDados[Liga]=_xlpm.l)*(tblDados[Janela_12_Liga]=1)))),IFERROR(MIN(_xlfn.MAP(_xlpm.t,_xlfn.LAMBDA(_xlpm.x,SUMPRODUCT((tblDados[Mandante]=_xlpm.x)*(tblDados[País]=_xlpm.p)*(tblDados[Liga]=_xlpm.l)*tblDados[Janela_12_Mandante])+SUMPRODUCT((tblDados[Visitante]=_xlpm.x)*(tblDados[País]=_xlpm.p)*(tblDados[Liga]=_xlpm.l)*tblDados[Janela_12_Visitante])))),0))} -> 12 | G23: =IFERROR(_xlfn.MAXIFS(tblDados[Data],tblDados[País],A23,tblDados[Liga],B23,tblDados[Janela_12_Liga],1),"") -> 46244 | H23: =IF(F23>=12,"OK — 12+","REVISAR") -> OK — 12+ | I23: WorldFootball · Futbol24 · Flashscore | J23: =IF(H23="OK — 12+","Manutenção semanal","Completar janela") -> Manutenção semanal
A24: FIN | B24: Veikkausliiga | C24: Equilibrada | D24: =COUNTIFS(tblDados[País],A24,tblDados[Liga],B24,tblDados[Janela_12_Liga],1) -> 75 | E24: {=IFERROR(ROWS(_xlfn.UNIQUE(_xlfn.VSTACK(_xlfn._xlws.FILTER(tblDados[Mandante],(tblDados[País]=A24)*(tblDados[Liga]=B24)*(tblDados[Janela_12_Liga]=1)),_xlfn._xlws.FILTER(tblDados[Visitante],(tblDados[País]=A24)*(tblDados[Liga]=B24)*(tblDados[Janela_12_Liga]=1))))),0)} -> 12 | F24: {=_xlfn.LET(_xlpm.p,A24,_xlpm.l,B24,_xlpm.t,_xlfn.UNIQUE(_xlfn.VSTACK(_xlfn._xlws.FILTER(tblDados[Mandante],(tblDados[País]=_xlpm.p)*(tblDados[Liga]=_xlpm.l)*(tblDados[Janela_12_Liga]=1)),_xlfn._xlws.FILTER(tblDados[Visitante],(tblDados[País]=_xlpm.p)*(tblDados[Liga]=_xlpm.l)*(tblDados[Janela_12_Liga]=1)))),IFERROR(MIN(_xlfn.MAP(_xlpm.t,_xlfn.LAMBDA(_xlpm.x,SUMPRODUCT((tblDados[Mandante]=_xlpm.x)*(tblDados[País]=_xlpm.p)*(tblDados[Liga]=_xlpm.l)*tblDados[Janela_12_Mandante])+SUMPRODUCT((tblDados[Visitante]=_xlpm.x)*(tblDados[País]=_xlpm.p)*(tblDados[Liga]=_xlpm.l)*tblDados[Janela_12_Visitante])))),0))} -> 12 | G24: =IFERROR(_xlfn.MAXIFS(tblDados[Data],tblDados[País],A24,tblDados[Liga],B24,tblDados[Janela_12_Liga],1),"") -> 46243 | H24: =IF(F24>=12,"OK — 12+","REVISAR") -> OK — 12+ | I24: WorldFootball · Futbol24 · Flashscore | J24: =IF(H24="OK — 12+","Manutenção semanal","Completar janela") -> Manutenção semanal
A25: FIN | B25: Ykkösliiga | C25: Equilibrada | D25: =COUNTIFS(tblDados[País],A25,tblDados[Liga],B25,tblDados[Janela_12_Liga],1) -> 62 | E25: {=IFERROR(ROWS(_xlfn.UNIQUE(_xlfn.VSTACK(_xlfn._xlws.FILTER(tblDados[Mandante],(tblDados[País]=A25)*(tblDados[Liga]=B25)*(tblDados[Janela_12_Liga]=1)),_xlfn._xlws.FILTER(tblDados[Visitante],(tblDados[País]=A25)*(tblDados[Liga]=B25)*(tblDados[Janela_12_Liga]=1))))),0)} -> 10 | F25: {=_xlfn.LET(_xlpm.p,A25,_xlpm.l,B25,_xlpm.t,_xlfn.UNIQUE(_xlfn.VSTACK(_xlfn._xlws.FILTER(tblDados[Mandante],(tblDados[País]=_xlpm.p)*(tblDados[Liga]=_xlpm.l)*(tblDados[Janela_12_Liga]=1)),_xlfn._xlws.FILTER(tblDados[Visitante],(tblDados[País]=_xlpm.p)*(tblDados[Liga]=_xlpm.l)*(tblDados[Janela_12_Liga]=1)))),IFERROR(MIN(_xlfn.MAP(_xlpm.t,_xlfn.LAMBDA(_xlpm.x,SUMPRODUCT((tblDados[Mandante]=_xlpm.x)*(tblDados[País]=_xlpm.p)*(tblDados[Liga]=_xlpm.l)*tblDados[Janela_12_Mandante])+SUMPRODUCT((tblDados[Visitante]=_xlpm.x)*(tblDados[País]=_xlpm.p)*(tblDados[Liga]=_xlpm.l)*tblDados[Janela_12_Visitante])))),0))} -> 12 | G25: =IFERROR(_xlfn.MAXIFS(tblDados[Data],tblDados[País],A25,tblDados[Liga],B25,tblDados[Janela_12_Liga],1),"") -> 46243 | H25: =IF(F25>=12,"OK — 12+","REVISAR") -> OK — 12+ | I25: WorldFootball · Futbol24 · Flashscore | J25: =IF(H25="OK — 12+","Manutenção semanal","Completar janela") -> Manutenção semanal
A26: FIN | B26: Ykkönen | C26: Muitos Gols | D26: =COUNTIFS(tblDados[País],A26,tblDados[Liga],B26,tblDados[Janela_12_Liga],1) -> 73 | E26: {=IFERROR(ROWS(_xlfn.UNIQUE(_xlfn.VSTACK(_xlfn._xlws.FILTER(tblDados[Mandante],(tblDados[País]=A26)*(tblDados[Liga]=B26)*(tblDados[Janela_12_Liga]=1)),_xlfn._xlws.FILTER(tblDados[Visitante],(tblDados[País]=A26)*(tblDados[Liga]=B26)*(tblDados[Janela_12_Liga]=1))))),0)} -> 12 | F26: {=_xlfn.LET(_xlpm.p,A26,_xlpm.l,B26,_xlpm.t,_xlfn.UNIQUE(_xlfn.VSTACK(_xlfn._xlws.FILTER(tblDados[Mandante],(tblDados[País]=_xlpm.p)*(tblDados[Liga]=_xlpm.l)*(tblDados[Janela_12_Liga]=1)),_xlfn._xlws.FILTER(tblDados[Visitante],(tblDados[País]=_xlpm.p)*(tblDados[Liga]=_xlpm.l)*(tblDados[Janela_12_Liga]=1)))),IFERROR(MIN(_xlfn.MAP(_xlpm.t,_xlfn.LAMBDA(_xlpm.x,SUMPRODUCT((tblDados[Mandante]=_xlpm.x)*(tblDados[País]=_xlpm.p)*(tblDados[Liga]=_xlpm.l)*tblDados[Janela_12_Mandante])+SUMPRODUCT((tblDados[Visitante]=_xlpm.x)*(tblDados[País]=_xlpm.p)*(tblDados[Liga]=_xlpm.l)*tblDados[Janela_12_Visitante])))),0))} -> 12 | G26: =IFERROR(_xlfn.MAXIFS(tblDados[Data],tblDados[País],A26,tblDados[Liga],B26,tblDados[Janela_12_Liga],1),"") -> 46245 | H26: =IF(F26>=12,"OK — 12+","REVISAR") -> OK — 12+ | I26: WorldFootball · Futbol24 · Flashscore | J26: =IF(H26="OK — 12+","Manutenção semanal","Completar janela") -> Manutenção semanal
... A52: AUS | B52: NPL Western Australia | C52: Muitos Gols | D52: =COUNTIFS(tblDados[País],A52,tblDados[Liga],B52,tblDados[Janela_12_Liga],1) -> 72 | E52: {=IFERROR(ROWS(_xlfn.UNIQUE(_xlfn.VSTACK(_xlfn._xlws.FILTER(tblDados[Mandante],(tblDados[País]=A52)*(tblDados[Liga]=B52)*(tblDados[Janela_12_Liga]=1)),_xlfn._xlws.FILTER(tblDados[Visitante],(tblDados[País]=A52)*(tblDados[Liga]=B52)*(tblDados[Janela_12_Liga]=1))))),0)} -> 12 | F52: {=_xlfn.LET(_xlpm.p,A52,_xlpm.l,B52,_xlpm.t,_xlfn.UNIQUE(_xlfn.VSTACK(_xlfn._xlws.FILTER(tblDados[Mandante],(tblDados[País]=_xlpm.p)*(tblDados[Liga]=_xlpm.l)*(tblDados[Janela_12_Liga]=1)),_xlfn._xlws.FILTER(tblDados[Visitante],(tblDados[País]=_xlpm.p)*(tblDados[Liga]=_xlpm.l)*(tblDados[Janela_12_Liga]=1)))),IFERROR(MIN(_xlfn.MAP(_xlpm.t,_xlfn.LAMBDA(_xlpm.x,SUMPRODUCT((tblDados[Mandante]=_xlpm.x)*(tblDados[País]=_xlpm.p)*(tblDados[Liga]=_xlpm.l)*tblDados[Janela_12_Mandante])+SUMPRODUCT((tblDados[Visitante]=_xlpm.x)*(tblDados[País]=_xlpm.p)*(tblDados[Liga]=_xlpm.l)*tblDados[Janela_12_Visitante])))),0))} -> 12 | G52: =IFERROR(_xlfn.MAXIFS(tblDados[Data],tblDados[País],A52,tblDados[Liga],B52,tblDados[Janela_12_Liga],1),"") -> 46241 | H52: =IF(F52>=12,"OK — 12+","REVISAR") -> OK — 12+ | I52: WorldFootball · Futbol24 · Flashscore | J52: =IF(H52="OK — 12+","Manutenção semanal","Completar janela") -> Manutenção semanal
A53: KOR | B53: K League 1 | C53: Poucos Gols | D53: =COUNTIFS(tblDados[País],A53,tblDados[Liga],B53,tblDados[Janela_12_Liga],1) -> 57 | E53: {=IFERROR(ROWS(_xlfn.UNIQUE(_xlfn.VSTACK(_xlfn._xlws.FILTER(tblDados[Mandante],(tblDados[País]=A53)*(tblDados[Liga]=B53)*(tblDados[Janela_12_Liga]=1)),_xlfn._xlws.FILTER(tblDados[Visitante],(tblDados[País]=A53)*(tblDados[Liga]=B53)*(tblDados[Janela_12_Liga]=1))))),0)} -> 12 | F53: {=_xlfn.LET(_xlpm.p,A53,_xlpm.l,B53,_xlpm.t,_xlfn.UNIQUE(_xlfn.VSTACK(_xlfn._xlws.FILTER(tblDados[Mandante],(tblDados[País]=_xlpm.p)*(tblDados[Liga]=_xlpm.l)*(tblDados[Janela_12_Liga]=1)),_xlfn._xlws.FILTER(tblDados[Visitante],(tblDados[País]=_xlpm.p)*(tblDados[Liga]=_xlpm.l)*(tblDados[Janela_12_Liga]=1)))),IFERROR(MIN(_xlfn.MAP(_xlpm.t,_xlfn.LAMBDA(_xlpm.x,SUMPRODUCT((tblDados[Mandante]=_xlpm.x)*(tblDados[País]=_xlpm.p)*(tblDados[Liga]=_xlpm.l)*tblDados[Janela_12_Mandante])+SUMPRODUCT((tblDados[Visitante]=_xlpm.x)*(tblDados[País]=_xlpm.p)*(tblDados[Liga]=_xlpm.l)*tblDados[Janela_12_Visitante])))),0))} -> 6 | G53: =IFERROR(_xlfn.MAXIFS(tblDados[Data],tblDados[País],A53,tblDados[Liga],B53,tblDados[Janela_12_Liga],1),"") -> 46242 | H53: PARCIAL — 6 equipes | I53: WorldFootball · AiScore · Sofascore | J53: Completar liga posteriormente
A54: PRÓXIMAS PARTIDAS — K LEAGUE 1 (GMT−3)
A55: Data | B55: Hora GMT−3 | C55: Mandante | D55: Visitante | E55: Liga | F55: Fuso original | G55: Hora KST | H55: Status | I55: Fonte | J55: Ação
A56: 16/08/2026 | B56: 0.3125 | C56: Ulsan HD FC | D56: Gangwon FC | E56: K League 1 | F56: KST (UTC+9) | G56: 0.8125 | H56: Agendada | I56: Dailysports · WorldFootball | J56: Analisar
A57: 16/08/2026 | B57: 0.3125 | C57: Incheon United | D57: Gimcheon Sangmu | E57: K League 1 | F57: KST (UTC+9) | G57: 0.8125 | H57: Agendada | I57: Dailysports · WorldFootball | J57: Analisar
A58: 16/08/2026 | B58: 0.3125 | C58: Bucheon FC 1995 | D58: Jeonbuk FC | E58: K League 1 | F58: KST (UTC+9) | G58: 0.8125 | H58: Agendada | I58: Dailysports · WorldFootball | J58: Analisar
A59: KOR | B59: K League 2 | C59: Equilibrada | D59: =COUNTIFS(tblDados[País],A59,tblDados[Liga],B59,tblDados[Janela_12_Liga],1) -> 78 | E59: {=IFERROR(ROWS(_xlfn.UNIQUE(_xlfn.VSTACK(_xlfn._xlws.FILTER(tblDados[Mandante],(tblDados[País]=A59)*(tblDados[Liga]=B59)*(tblDados[Janela_12_Liga]=1)),_xlfn._xlws.FILTER(tblDados[Visitante],(tblDados[País]=A59)*(tblDados[Liga]=B59)*(tblDados[Janela_12_Liga]=1))))),0)} -> 17 | F59: {=_xlfn.LET(_xlpm.p,A59,_xlpm.l,B59,_xlpm.t,_xlfn.UNIQUE(_xlfn.VSTACK(_xlfn._xlws.FILTER(tblDados[Mandante],(tblDados[País]=_xlpm.p)*(tblDados[Liga]=_xlpm.l)*(tblDados[Janela_12_Liga]=1)),_xlfn._xlws.FILTER(tblDados[Visitante],(tblDados[País]=_xlpm.p)*(tblDados[Liga]=_xlpm.l)*(tblDados[Janela_12_Liga]=1)))),IFERROR(MIN(_xlfn.MAP(_xlpm.t,_xlfn.LAMBDA(_xlpm.x,SUMPRODUCT((tblDados[Mandante]=_xlpm.x)*(tblDados[País]=_xlpm.p)*(tblDados[Liga]=_xlpm.l)*tblDados[Janela_12_Mandante])+SUMPRODUCT((tblDados[Visitante]=_xlpm.x)*(tblDados[País]=_xlpm.p)*(tblDados[Liga]=_xlpm.l)*tblDados[Janela_12_Visitante])))),0))} -> 6 | G59: =IFERROR(_xlfn.MAXIFS(tblDados[Data],tblDados[País],A59,tblDados[Liga],B59,tblDados[Janela_12_Liga],1),"") -> 46242 | H59: PARCIAL — 8 equipes | I59: WorldFootball · XScores · AiScore · Sofascore | J59: Completar liga posteriormente
A60: PRÓXIMAS PARTIDAS — K LEAGUE 2 (GMT−3)
A61: Data | B61: Hora GMT−3 | C61: Mandante | D61: Visitante | E61: Liga | F61: Fuso original | G61: Hora KST | H61: Status | I61: Fonte | J61: Ação
A62: 16/08/2026 | B62: 0.3125 | C62: Seoul E-Land FC | D62: Ansan Greeners | E62: K League 2 | F62: KST (UTC+9) | G62: 0.8125 | H62: Agendada | I62: Flashscore · Sofascore | J62: Analisar
A63: 16/08/2026 | B63: 0.3125 | C63: Daegu FC | D63: Chungnam Asan FC | E63: K League 2 | F63: KST (UTC+9) | G63: 0.8125 | H63: Agendada | I63: Flashscore · Sofascore | J63: Analisar
A64: 16/08/2026 | B64: 0.3125 | C64: Gimpo FC | D64: Cheonan City FC | E64: K League 2 | F64: KST (UTC+9) | G64: 0.8125 | H64: Agendada | I64: Flashscore · Sofascore | J64: Analisar
A65: 16/08/2026 | B65: 0.3125 | C65: Paju Frontier | D65: Seongnam FC | E65: K League 2 | F65: KST (UTC+9) | G65: 0.8125 | H65: Agendada | I65: Flashscore · Sofascore | J65: Analisar
A66: As fontes usadas são páginas públicas com estruturas diferentes e sujeitas a alterações ou bloqueios. Por isso, um Office Script agendado não consegue reproduzir sozinho a pesquisa e a validação. A alternativa segura é usar esta fila como controle e executar semanalmente uma atualização assistida: pesquisar cada liga, importar resultados concluídos, validar horários e recalcular as janelas.
D69: =COUNTIFS(tblDados[País],A69,tblDados[Liga],B69,tblDados[Janela_12_Liga],1) -> 0 | E69: {=IFERROR(ROWS(_xlfn.UNIQUE(_xlfn.VSTACK(_xlfn._xlws.FILTER(tblDados[Mandante],(tblDados[País]=A69)*(tblDados[Liga]=B69)*(tblDados[Janela_12_Liga]=1)),_xlfn._xlws.FILTER(tblDados[Visitante],(tblDados[País]=A69)*(tblDados[Liga]=B69)*(tblDados[Janela_12_Liga]=1))))),0)} -> 0 | F69: {=_xlfn.LET(_xlpm.p,A69,_xlpm.l,B69,_xlpm.t,_xlfn.UNIQUE(_xlfn.VSTACK(_xlfn._xlws.FILTER(tblDados[Mandante],(tblDados[País]=_xlpm.p)*(tblDados[Liga]=_xlpm.l)*(tblDados[Janela_12_Liga]=1)),_xlfn._xlws.FILTER(tblDados[Visitante],(tblDados[País]=_xlpm.p)*(tblDados[Liga]=_xlpm.l)*(tblDados[Janela_12_Liga]=1)))),IFERROR(MIN(_xlfn.MAP(_xlpm.t,_xlfn.LAMBDA(_xlpm.x,SUMPRODUCT((tblDados[Mandante]=_xlpm.x)*(tblDados[País]=_xlpm.p)*(tblDados[Liga]=_xlpm.l)*tblDados[Janela_12_Mandante])+SUMPRODUCT((tblDados[Visitante]=_xlpm.x)*(tblDados[País]=_xlpm.p)*(tblDados[Liga]=_xlpm.l)*tblDados[Janela_12_Visitante])))),0))} -> 0 | G69: =IFERROR(_xlfn.MAXIFS(tblDados[Data],tblDados[País],A69,tblDados[Liga],B69,tblDados[Janela_12_Liga],1),"") -> 0 | H69: =IF(F69>=12,"OK — 12+","REVISAR") -> REVISAR | I69: WorldFootball · Futbol24 · Flashscore | J69: =IF(H69="OK — 12+","Manutenção semanal","Completar janela") -> Completar janela
A70: COMANDO SEMANAL RECOMENDADO
A71: “Atualize as ligas marcadas como REVISAR e faça manutenção das ligas completas, buscando resultados concluídos desde a última data, mantendo somente a união das últimas 12 partidas por equipe e auditando duplicidades.”

Sheet Memória
A1: MEMÓRIA OPERACIONAL — PROCEDIMENTO DA ABA BACKTEST
A2: Manual permanente para transcrição, liquidação, comparação de linhas e controle visual dos registros. Última atualização: 09/08/2026.
A4: REGRA-MESTRA
A5: Antes de alterar o Backtest, ler esta aba. Cada bilhete finalizado deve ser registrado uma única vez na tblCalibracao. Conferir Bilhetes, odds informadas, observação em Y e linha usada em H. Não inventar odds, linhas ou resultados.
A7: FLUXO OBRIGATÓRIO — PASSO A PASSO
A8: 1 | B8: Identificar o bilhete | C8: Localizar em Bilhetes: data, confronto, liga, placar, linha apostada, odd, stake, resultado e P/L.
A9: 2 | B9: Evitar duplicidade | C9: Normalizar “×” e “x” e confirmar que o confronto ainda não existe na coluna B da tblCalibracao.
A10: 3 | B10: Preencher dados-base | C10: Preencher A:E, G:H e L. A=Data; B=Confronto; C=Liga; D=Placar; E=Odd; G=Gols; H=Usada; L=Fonte odds.
A11: 4 | B11: Calcular P/L usado | C11: F deve ser fórmula viva de liquidação asiática com stake unitária de R$ 0,50. Exceção: cashout usa o lucro líquido real informado.
A12: 5 | B12: Encontrar melhor aproveitamento | C12: Comparar somente as linhas e odds realmente informadas no bilhete. Preencher I=Melhor G, J=Odd M.G. e K=P/L M.G. com a alternativa de maior P/L positivo.
A13: 6 | B13: Sem alternativa positiva | C13: Se nenhuma linha cotada produzir lucro positivo, deixar I:K vazias. Não preencher uma linha hipotética.
A14: 7 | B14: Calcular delta | C14: M = diferença não negativa entre Melhor G e Usada. Se I estiver vazia, M deve ficar vazia.
A15: 8 | B15: Classificar faixas | C15: N:X devem conter fórmulas para O0,50 a O3,00, usando G, ½G, P, ½R ou R.
A16: 9 | B16: Marcar linha usada | C16: Ler H e a observação Y. Marcar somente a célula correspondente em N:X com borda azul-escura espessa e negrito. Remover qualquer outra marcação incorreta na mesma linha.
A17: 10 | B17: Escrever análise | C17: Y deve explicar resultado, linha/odd usada, placar, P/L, melhor alternativa cotada, diferença financeira e aprendizado operacional. Usar o padrão de Y35.
A18: 11 | B18: Cashout | C18: Registrar P/L líquido real; explicar retorno bruto e stake; manter em H a linha original; marcar em N:X o desfecho que teria ocorrido pelo placar final.
A19: 12 | B19: Verificar | C19: Confirmar fórmulas, formatos, ausência de erros, nenhuma duplicidade e todos os campos obrigatórios preenchidos.
A21: MAPA DAS COLUNAS DA tblCalibracao
A22: Coluna | B22: Campo | C22: Tipo | D22: Regra de preenchimento
A23: A | B23: Data | C23: Entrada | D23: Data da partida, formato dd/mm/aa.
A24: B | B24: Confronto | C24: Entrada | D24: Mandante x Visitante; manter nome reconhecível e sem numeração.
A25: C | B25: Liga | C25: Entrada | D25: País - Liga.
A26: D | B26: Placar | C26: Entrada | D26: Mandante x Visitante.
A27: E | B27: Odd | C27: Entrada | D27: Odd da linha usada, preferencialmente 0,000.
A28: F | B28: P/L (R$) | C28: Fórmula / exceção | D28: Liquidação asiática com stake R$ 0,50; cashout recebe lucro líquido real.
A29: G | B29: Gols | C29: Entrada | D29: Soma dos gols do placar.
A30: H | B30: Usada | C30: Entrada | D30: Linha Over realmente apostada. Controla a marcação visual em N:X.
A31: I | B31: Melhor G | C31: Análise | D31: Linha cotada que produziria maior P/L positivo.
A32: J | B32: Odd M.G. | C32: Entrada histórica | D32: Odd informada da Melhor G. Nunca inventar.
A33: K | B33: P/L M.G. | C33: Fórmula | D33: Liquidação da melhor linha com stake R$ 0,50.
... A37: Y | B37: Análise da Entrada | C37: Texto analítico | D37: Narrativa completa seguindo o padrão da linha 35.
A39: LIQUIDAÇÃO DAS LINHAS ASIÁTICAS OVER
A40: Tipo de linha | B40: Exemplo | C40: Liquidação | D40: Regra
A41: Inteira | B41: Over 2,00 | C41: Green / Push / Red | D41: Total > linha = Green; total = linha = Push; total < linha = Red.
A42: Meia | B42: Over 2,50 | C42: Green / Red | D42: Total > linha = Green; caso contrário = Red.
A43: Quarto .25 | B43: Over 2,25 | C43: Green / ½ Red / Red | D43: 3+ = Green; exatamente 2 = ½ Red; 0–1 = Red.
A44: Quarto .75 | B44: Over 2,75 | C44: Green / ½ Green / Red | D44: 4+ = Green; exatamente 3 = ½ Green; 0–2 = Red.
A46: FÓRMULAS-BASE
A47: Campo | B47: Fórmula / lógica
A48: F — P/L usado | B48: FÓRMULA: =IF(OR([@Odd]="",[@Usada]=""),"",LET(t,[@Gols],l,[@Usada],o,[@Odd],n,INT(l),f,ROUND(MOD(l,1),2),IF(f=0,IF(t>l,0.5*(o-1),IF(t=l,0,-0.5)),IF(f=0.5,IF(t>l,0.5*(o-1),-0.5),IF(f=0.25,IF(t>=n+1,0.5*(o-1),IF(t=n,-0.25,-0.5)),IF(f=0.75,IF(t>=n+2,0.5*(o-1),IF(t=n+1,0.25*(o-1),-0.5)),""))))))
A49: K — P/L melhor linha | B49: Mesma lógica de F, substituindo Usada por Melhor G e Odd por Odd M.G.
A50: M — Delta | B50: FÓRMULA: =IF(OR([@Usada]="",[@[Melhor G]]=""),"",MAX(0,[@[Melhor G]]-[@Usada]))
A51: N:X — classificação | B51: Aplicar a regra asiática correspondente ao cabeçalho e aos gols em G; resultado permitido: G, ½G, P, ½R ou R.
A53: PADRÃO OBRIGATÓRIO DA OBSERVAÇÃO EM Y
A54: Estrutura: “[Resultado] no Over [linha] @ [odd]: o placar [placar] ([gols] gols) [liquidação] e gerou/perdeu R$ [valor]. Entre as linhas cotadas, Over [melhor] @ [odd] teria produzido R$ [valor], R$ [diferença] acima/abaixo do realizado. Conclusão sobre proteção, agressividade ou eficiência potencial.”
A55: Referência: Backtest!Y35. Se nenhuma linha cotada produzir lucro, declarar que o problema foi a seleção da partida, não apenas a linha. Para cashout, informar retorno bruto, stake, lucro líquido e desfecho teórico pelo placar final.
A57: MARCAÇÃO VISUAL DA LINHA USADA
A58: Valor em H | B58: Coluna marcada | C58: Mercado | D58: Estilo
A59: 0.5 | B59: N | C59: O0,50 | D59: Borda #17365D espessa nos 4 lados + negrito
A60: 0.75 | B60: O | C60: O0,75 | D60: Mesmo estilo
A61: 1 | B61: P | C61: O1,00 | D61: Mesmo estilo
A62: 1.25 | B62: Q | C62: O1,25 | D62: Mesmo estilo
A63: 1.5 | B63: R | C63: O1,50 | D63: Mesmo estilo
A64: 1.75 | B64: S | C64: O1,75 | D64: Mesmo estilo
A65: 2 | B65: T | C65: O2,00 | D65: Mesmo estilo
A66: 2.25 | B66: U | C66: O2,25 | D66: Mesmo estilo
A67: 2.5 | B67: V | C67: O2,50 | D67: Mesmo estilo
A68: 2.75 | B68: W | C68: O2,75 | D68: Mesmo estilo
A69: 3 | B69: X | C69: O3,00 | D69: Mesmo estilo
A71: CHECKLIST FINAL
A72: □ | B72: Confronto não duplicado
A73: □ | B73: A:E, G:H e L preenchidos
A74: □ | B74: F, K, M e N:X com fórmulas quando aplicável
A75: □ | B75: I:K baseados somente em odds informadas
A76: □ | B76: Y analítica no padrão da linha 35
A77: □ | B77: Somente a linha usada marcada em N:X
A78: □ | B78: Cashout preserva P/L real
A79: □ | B79: Sem #REF!, #DIV/0!, #NOME?, #VALOR! ou #SPILL!
A81: PROCEDIMENTO DA ABA DADOS — COLETA E INPUT
A82: Objetivo: obter cobertura integral de uma liga, trabalhando clube por clube e registrando as 12 partidas mais recentes de 2026, com deduplicação e horários convertidos para GMT−3.
A84: Etapa | B84: Ação | C84: Regra obrigatória | D84: Resultado esperado
A85: 1 | B85: Definir a liga | C85: Informar país e competição no padrão “PAÍS - Liga”. | D85: Escopo único de coleta.
A86: 2 | B86: Solicitar o primeiro clube | C86: Trabalhar um clube por vez até cobrir todos os participantes da liga. | D86: Lista sequencial de clubes.
A87: 3 | B87: Coletar o histórico | C87: Buscar as 12 partidas mais recentes do clube disputadas em 2026. | D87: Até 12 jogos válidos por clube.
A88: 4 | B88: Cobertura integral | C88: Repetir o processo para todos os clubes da liga, sem selecionar somente equipes de interesse. | D88: Liga integralmente coberta.
A89: 5 | B89: Padronizar horário | C89: Converter cada horário para GMT−3 antes do input. | D89: Coluna Hora comparável e consistente.
A90: 6 | B90: Padronizar nomes | C90: Usar o nome cadastrado em CadastroEquipes; corrigir variações antes de consolidar. | D90: Sem alertas indevidos em U:V.
A91: 7 | B91: Montar o registro | C91: Preencher ID, Data, Hora, País, Liga, Partida, Mandante, gols e Visitante em A:L. | D91: Linha-base completa na tblDados.
A92: 8 | B92: Deduplicar | C92: Usar Chave_Partida e Primeira_Ocorrencia; manter somente a primeira ocorrência estatística. | D92: Partidas repetidas não contam duas vezes.
A93: 9 | B93: Dados de aposta | C93: Preencher M:R apenas quando a partida tiver aposta vinculada. | D93: Histórico esportivo separado do histórico de apostas.
A94: 10 | B94: Validar o lote | C94: Confirmar ano 2026, máximo de 12 partidas por clube, liga correta, GMT−3, placares e nomes. | D94: Lote pronto para alimentar Equipes e o simulador.
A95: 11 | B95: Avançar ao próximo clube | C95: Após validar o clube atual, solicitar o próximo até concluir a liga. | D95: Processo rastreável e sem lacunas.
A97: FRASE-PADRÃO DE INÍCIO
A98: “Vamos para a [LIGA], mantendo o padrão: cobertura integral, 12 partidas mais recentes de 2026, deduplicação e horários em GMT−3. Envie o primeiro clube.”
A100: CHECKLIST DO LOTE DE DADOS
A101: □ | B101: Liga e país corretos
A102: □ | B102: Até 12 partidas mais recentes de 2026 por clube
A103: □ | B103: Horários em GMT−3
A104: □ | B104: Nomes reconhecidos em CadastroEquipes
A105: □ | B105: Deduplicação validada por Chave_Partida / Primeira_Ocorrencia
A107: DIRETRIZ DE PRIORIZAÇÃO — ETAPA ATUAL DO PROJETO
A108: Nesta etapa do projeto, EV não é o critério prioritário. A decisão deve priorizar a consistência dos acertos e a preservação da taxa de acerto; somente depois deve buscar melhorar o ganho entre as linhas compatíveis com acertos consistentes. Não rejeitar automaticamente uma entrada apenas por EV negativo.
A110: PADRÃO VISUAL OBRIGATÓRIO DOS BILHETES
A111: Todo novo bilhete deve replicar integralmente a aparência do último bloco aprovado na aba Bilhetes. São obrigatórios: mesmas células mescladas, preenchimentos, cores de fonte, negrito, tamanhos, bordas, alinhamentos, quebra de texto, formatos numéricos, larguras de coluna, alturas de linha e espaçamento. Copiar apenas formatos não basta quando as novas linhas possuem formatação residual: reaplicar o bloco completo e comparar célula a célula com o modelo. Preservar os dados e usar fórmulas de status, total, liquidação e P/L adequadas à linha asiática escolhida. Antes de concluir, confirmar que não existem diferenças visuais nem erros de fórmula.
A113: ORDEM OBRIGATÓRIA DA COLETA MLS
A114: Na aba Dados, organizar somente os novos registros estatísticos com ID EST- em três blocos sequenciais: primeiro MLS-East, depois MLS-West e, por último, MLS-Cross. Jogos entre conferências devem ser classificados exclusivamente como MLS-Cross. Registros históricos ou de apostas com IDs originais (por exemplo, 00082-USA) nunca devem ser deslocados de suas posições existentes. Não misturar partidas Cross nas médias internas de East ou West.
A116: DIRETRIZ PROVISÓRIA — λ, RISCO DE 0×0 E AVANÇO DE LINHA
A117: Regra experimental baseada em 30 bilhetes contabilizados, dos quais 29 possuem λ registrado. Prioridade: proteção, seguida de lucro. Reavaliar quando a amostra aumentar.
A119: Faixa / filtro | B119: Regra | C119: Condição adicional | D119: Aplicação
A120: λ < 2,50 | B120: Não avançar linha | C120: Usar máxima proteção disponível | D120: Manter linha técnica/conservadora
...

Sheet Dados
A1: ID_Bilhete | B1: Data | C1: Hora | D1: País | E1: Liga | F1: Partida | G1: Mandante | H1: GM_M | I1: GS_M | J1: Visitante | K1: GM_V | L1: GS_V | M1: Mercado | N1: Linha_Selecao | O1: Odd | P1: Stake | Q1: Resultado_Aposta | R1: Lucro_Prejuizo | S1: Chave_Partida | T1: Primeira_Ocorrencia | U1: Alerta / Sugestão Mandante | V1: Alerta / Sugestão Visitante | W1: Janela_12_Mandante | X1: Janela_12_Visitante | Y1: Janela_12_Liga
A2: 00003-NOR | B2: 46230 | C2: 0.58333333 | D2: NOR | E2: Eliteserien | F2: Rosenborg BK 4 vs 0 Fredrikstad FK | G2: Rosenborg BK | H2: 4 | I2: 0 | J2: Fredrikstad FK | K2: 0 | L2: 4 | M2: Gols +/- | N2: Mais de 2.0 | O2: 1 | P2: 0.5 | Q2: Cashout | R2: 0.13 | S2: 2026-07-27|Rosenborg BK|Fredrikstad FK | T2: 1 | W2: 1 | X2: 1 | Y2: 1
A3: 00005-NOR | B3: 46230 | C3: 0.58333333 | D3: NOR | E3: OBOS-ligaen | F3: Stabæk Fotball 6 vs 0 IL Hødd | G3: Stabæk Fotball | H3: 6 | I3: 0 | J3: IL Hødd | K3: 0 | L3: 6 | M3: Gols +/- | N3: Mais de 3.0 | O3: 1 | P3: 0.5 | Q3: Cashout | R3: 0.19 | S3: 2026-07-27|Stabæk Fotball|IL Hødd | T3: 1 | W3: 1 | X3: 1 | Y3: 1
A4: 00006-SWE | B4: 46230 | C4: 0.58680556 | D4: SWE | E4: Superettan | F4: Östers IF 3 vs 0 Varbergs BoIS FC | G4: Östers IF | H4: 3 | I4: 0 | J4: Varbergs BoIS FC | K4: 0 | L4: 3 | M4: Gols +/- | N4: Mais de 2.0 | O4: 1 | P4: 0.5 | Q4: Cashout | R4: 0.06 | S4: 2026-07-27|Östers IF|Varbergs BoIS FC | T4: 1 | W4: 1 | X4: 1 | Y4: 1
A5: 00008-SWE | B5: 46230 | C5: 0.58333333 | D5: SWE | E5: Allsvenskan | F5: BK Häcken 0 vs 0 AIK | G5: BK Häcken | H5: 0 | I5: 0 | J5: AIK | K5: 0 | L5: 0 | M5: Gols +/- | N5: Mais de 2.0 | O5: 1.17 | P5: 0.5 | Q5: Red | R5: -0.5 | S5: 2026-07-27|BK Häcken|AIK | T5: 1 | W5: 1 | X5: 1 | Y5: 1
A6: 00010-ISL | B6: 46230 | C6: 0.67708333 | D6: ISL | E6: Besta-deild karla (PL) | F6: Breidablik 1 vs 0 IBV Vestmannaeyjar | G6: Breidablik | H6: 1 | I6: 0 | J6: IBV Vestmannaeyjar | K6: 0 | L6: 1 | M6: Gols +/- | N6: Mais de 2.0 | O6: 1.175 | P6: 0.5 | Q6: Red | R6: -0.5 | S6: 2026-07-27|Breidablik|IBV Vestmannaeyjar | T6: 1 | W6: 1 | X6: 1 | Y6: 1
A7: 00012-ISL | B7: 46230 | C7: 0.67708333 | D7: ISL | E7: Besta-deild karla (PL) | F7: KA Akureyri 0 vs 0 Thor Akureyri (Þór Akureyri) | G7: KA Akureyri | H7: 0 | I7: 0 | J7: Thor Akureyri (Þór Akureyri) | K7: 0 | L7: 0 | M7: Gols +/- | N7: Mais de 2.0 | O7: 1.14 | P7: 0.5 | Q7: Red | R7: -0.5 | S7: 2026-07-27|KA Akureyri|Thor Akureyri (Þór Akureyri) | T7: 1 | W7: 1 | X7: 1 | Y7: 1
A8: 00013-BRA | B8: 46230 | C8: 0.83333333 | D8: BRA | E8: Série B | F8: CRB 2 vs 0 Vila Nova | G8: CRB | H8: 2 | I8: 0 | J8: Vila Nova | K8: 0 | L8: 2 | M8: Gols +/- | N8: Mais de 1.0, 1.5 | O8: 1.225 | P8: 0.5 | Q8: Green | R8: 0.12 | S8: 2026-07-27|CRB|Vila Nova | T8: 1 | W8: 1 | X8: 1 | Y8: 1
A9: 00014-BRA | B9: 46230 | C9: 0.83333333 | D9: BRA | E9: Série B | F9: Atlético-GO 3 vs 1 Operário-PR | G9: Atlético-GO | H9: 3 | I9: 1 | J9: Operário-PR | K9: 1 | L9: 3 | M9: Gols +/- | N9: Mais de 1.0 | O9: 1.125 | P9: 0.5 | Q9: Green | R9: 0.07 | S9: 2026-07-27|Atlético-GO|Operário-PR | T9: 1 | W9: 1 | X9: 1 | Y9: 1
A10: 00015-BRA | B10: 46230 | C10: 0.83333333 | D10: BRA | E10: Série B | F10: Sport Recife 1 vs 1 Cuiabá | G10: Sport Recife | H10: 1 | I10: 1 | J10: Cuiabá | K10: 1 | L10: 1 | M10: Gols +/- | N10: Mais de 1.0 | O10: 1.17 | P10: 0.5 | Q10: Red | R10: 0.09 | S10: 2026-07-27|Sport Recife|Cuiabá | T10: 1 | W10: 1 | X10: 1 | Y10: 1
A11: 00017-ISL | B11: 46231 | C11: 0.67708333 | D11: ISL | E11: Lengjudeildin (1ªD) | F11: Aegir 0 vs 1 Njardvik | G11: Aegir | H11: 0 | I11: 1 | J11: Njardvik | K11: 1 | L11: 0 | M11: Gols +/- | N11: Mais de 2.0, 2.5 | O11: 1.17 | P11: 0.5 | Q11: Red | R11: -0.5 | S11: 2026-07-28|Aegir|Njardvik | T11: 1 | W11: 1 | X11: 1 | Y11: 1
A12: 00019-BRA | B12: 46231 | C12: 0.83333333 | D12: BRA | E12: Série B | F12: Ponte Preta 1 vs 1 Athletic Club-MG | G12: Ponte Preta | H12: 1 | I12: 1 | J12: Athletic Club-MG | K12: 1 | L12: 1 | M12: Gols +/- | N12: Mais de 0.5 | O12: 1.105 | P12: 0.5 | Q12: Green | R12: 0.06 | S12: 2026-07-28|Ponte Preta|Athletic Club-MG | T12: 1 | W12: 1 | X12: 1 | Y12: 1
A13: 00020-BRA | B13: 46231 | C13: 0.79166667 | D13: BRA | E13: Série B | F13: Juventude 1 vs 0 Avaí | G13: Juventude | H13: 1 | I13: 0 | J13: Avaí | K13: 0 | L13: 1 | M13: Gols +/- | N13: Mais de 1.0 | O13: 1.12 | P13: 0.5 | Q13: Devolvida | R13: 0 | S13: 2026-07-28|Juventude|Avaí | T13: 1 | W13: 1 | X13: 1 | Y13: 1
... A70: 00099-NOR | B70: 46236 | C70: 0.5 | D70: NOR | E70: OBOS-ligaen | F70: Egersunds IK 2 vs 0 Sandnes Ulf | G70: Egersunds IK | H70: 2 | I70: 0 | J70: Sandnes Ulf | K70: 0 | L70: 2 | M70: Gols +/- | N70: Mais de 2.0 | O70: 1.22 | P70: 0.5 | Q70: Devolvida | R70: 0 | S70: 2026-08-02|Egersunds IK|Sandnes Ulf | T70: 1 | W70: 1 | X70: 1 | Y70: 1
A71: EST-00001 | B71: 46164 | C71: 0.52083333 | D71: FIN | E71: Kakkonen A | F71: Atlantis FC 8 vs 0 PuiU | G71: Atlantis FC | H71: 8 | I71: 0 | J71: PuiU | K71: 0 | L71: 8 | S71: 2026-05-22|Atlantis FC|PuiU | T71: 1 | W71: 1 | X71: 1 | Y71: 1
A72: EST-00002 | B72: 46173 | C72: 0.375 | D72: FIN | E72: Kakkonen A | F72: Reipas (Lahden Reipas) 1 vs 0 Atlantis FC | G72: Reipas (Lahden Reipas) | H72: 1 | I72: 0 | J72: Atlantis FC | K72: 0 | L72: 1 | S72: 2026-05-31|Reipas (Lahden Reipas)|Atlantis FC | T72: 1 | W72: 1 | X72: 1 | Y72: 1
A73: EST-00003 | B73: 46179 | C73: 0.33333333 | D73: FIN | E73: Kakkonen A | F73: Atlantis FC 3 vs 2 HIFK | G73: Atlantis FC | H73: 3 | I73: 2 | J73: HIFK | K73: 2 | L73: 3 | S73: 2026-06-06|Atlantis FC|HIFK | T73: 1 | W73: 1 | X73: 1 | Y73: 1
A74: EST-00004 | B74: 46184 | C74: 0.5 | D74: FIN | E74: Kakkonen A | F74: PPJ 3 vs 3 Atlantis FC | G74: PPJ | H74: 3 | I74: 3 | J74: Atlantis FC | K74: 3 | L74: 3 | S74: 2026-06-11|PPJ|Atlantis FC | T74: 1 | W74: 1 | X74: 1 | Y74: 1
A75: EST-00005 | B75: 46200 | C75: 0.45833333 | D75: FIN | E75: Kakkonen A | F75: MyPa 1 vs 2 Atlantis FC | G75: MyPa | H75: 1 | I75: 2 | J75: Atlantis FC | K75: 2 | L75: 1 | S75: 2026-06-27|MyPa|Atlantis FC | T75: 1 | W75: 1 | X75: 1 | Y75: 1
A76: EST-00006 | B76: 46207 | C76: 0.41666667 | D76: FIN | E76: Kakkonen A | F76: Atlantis FC 5 vs 1 PEPO | G76: Atlantis FC | H76: 5 | I76: 1 | J76: PEPO | K76: 1 | L76: 5 | S76: 2026-07-04|Atlantis FC|PEPO | T76: 1 | W76: 1 | X76: 1 | Y76: 1
A77: EST-00007 | B77: 46213 | C77: 0.52083333 | D77: FIN | E77: Kakkonen A | F77: Atlantis FC 3 vs 5 Kiffen | G77: Atlantis FC | H77: 3 | I77: 5 | J77: Kiffen | K77: 5 | L77: 3 | S77: 2026-07-10|Atlantis FC|Kiffen | T77: 1 | W77: 1 | X77: 1 | Y77: 1
A78: EST-00008 | B78: 46221 | C78: 0.375 | D78: FIN | E78: Kakkonen A | F78: Union Plaani 3 vs 6 Atlantis FC | G78: Union Plaani | H78: 3 | I78: 6 | J78: Atlantis FC | K78: 6 | L78: 3 | S78: 2026-07-18|Union Plaani|Atlantis FC | T78: 1 | W78: 1 | X78: 1 | Y78: 1
A79: EST-00009 | B79: 46228 | C79: 0.41666667 | D79: FIN | E79: Kakkonen A | F79: Atlantis FC 5 vs 3 HPS | G79: Atlantis FC | H79: 5 | I79: 3 | J79: HPS | K79: 3 | L79: 5 | S79: 2026-07-25|Atlantis FC|HPS | T79: 1 | W79: 1 | X79: 1 | Y79: 1
A80: EST-00011 | B80: 46171 | C80: 0.52083333 | D80: FIN | E80: Ykkösliiga | F80: KTP 1 vs 0 SJK Akatemia | G80: KTP | H80: 1 | I80: 0 | J80: SJK Akatemia | K80: 0 | L80: 1 | S80: 2026-05-29|KTP|SJK Akatemia | T80: 1 | W80: 1 | X80: 1 | Y80: 1
A81: EST-00012 | B81: 46182 | C81: 0.52083333 | D81: FIN | E81: Ykkösliiga | F81: SJK Akatemia 0 vs 0 Jippo | G81: SJK Akatemia | H81: 0 | I81: 0 | J81: Jippo | K81: 0 | L81: 0 | S81: 2026-06-09|SJK Akatemia|Jippo | T81: 1 | W81: 1 | X81: 1 | Y81: 1
A82: EST-00013 | B82: 46188 | C82: 0.52083333 | D82: FIN | E82: Ykkösliiga | F82: SJK Akatemia 0 vs 2 Haka | G82: SJK Akatemia | H82: 0 | I82: 2 | J82: Haka | K82: 2 | L82: 0 | S82: 2026-06-15|SJK Akatemia|Haka | T82: 1 | W82: 1 | X82: 1 | Y82: 1
... A276: EST-00241 | B276: 46229 | C276: 0.52083333 | D276: FIN | E276: Ykkönen | F276: KuPS Akatemia 2 vs 2 VJS | G276: KuPS Akatemia | H276: 2 | I276: 2 | J276: VJS | K276: 2 | L276: 2 | S276: 2026-07-26|KuPS Akatemia|VJS | T276: 1 | W276: 1 | X276: 1 | Y276: 1
A277: 00100-FIN | B277: 46241 | C277: 0.52083333 | D277: FIN | E277: Ykkönen | F277: KuPS Akatemia 0 vs 1 Inter Turku 2 | G277: KuPS Akatemia | H277: 0 | I277: 1 | J277: Inter Turku 2 | K277: 1 | L277: 0 | M277: Gols +/- | N277: Mais de 2.5 | O277: 1.225 | P277: 0.5 | Q277: Red | R277: -0.5 | S277: 2026-08-07|KuPS Akatemia|Inter Turku 2 | T277: 1 | W277: 1 | X277: 1 | Y277: 1
A278: 00101-FIN | B278: 46241 | C278: 0.52083333 | D278: FIN | E278: Kakkonen C | F278: Jaro 2 1 vs 3 JBK | G278: Jaro 2 | H278: 1 | I278: 3 | J278: JBK | K278: 3 | L278: 1 | M278: Gols +/- | N278: Mais de 2.0, 2.5 | O278: 1.2 | P278: 0.5 | Q278: Green | R278: 0.1 | S278: 2026-08-07|Jaro 2|JBK | T278: 1 | W278: 1 | X278: 1 | Y278: 1
A279: 00102-CHN | B279: 46241 | C279: 0.35763889 | D279: CHN | E279: Super League | F279: Beijing Guoan 4 vs 0 Shenzhen Xinpengcheng | G279: Beijing Guoan | H279: 4 | I279: 0 | J279: Shenzhen Xinpengcheng | K279: 0 | L279: 4 | M279: Gols +/- | N279: Mais de 2.0 | O279: 1.14 | P279: 0.5 | Q279: Green | R279: 0.07 | S279: 2026-08-07|Beijing Guoan|Shenzhen Xinpengcheng | T279: 1 | W279: 1 | X279: 1 | Y279: 1
A280: 00103-AUS | B280: 46241 | C280: 0.22916667 | D280: AUS | E280: NPL Queensland | F280: Lions FC 4 vs 2 Brisbane Roar NPL | G280: Lions FC | H280: 4 | I280: 2 | J280: Brisbane Roar NPL | K280: 2 | L280: 4 | M280: Gols +/- | N280: Mais de 2.5 | O280: 1.26 | P280: 0.5 | Q280: Green | R280: 0.13 | S280: 2026-08-07|Lions FC|Brisbane Roar NPL | T280: 1 | W280: 1 | X280: 1 | Y280: 1
A281: 00104-BOL | B281: 46239 | C281: 0.875 | D281: BOL | E281: Div. Profesional | F281: Bolívar 2 vs 1 Oriente Petrolero | G281: Bolívar | H281: 2 | I281: 1 | J281: Oriente Petrolero | K281: 1 | L281: 2 | M281: Gols +/- | N281: Mais de 2.0, 2.5 | O281: 1.17 | P281: 0.5 | Q281: Green | R281: 0.08 | S281: 2026-08-05|Bolívar|Oriente Petrolero | T281: 1 | W281: 1 | X281: 1 | Y281: 1
A282: 00105-BOL | B282: 46239 | C282: 0.79166667 | D282: BOL | E282: Div. Profesional | F282: Nacional Potosí 2 vs 3 The Strongest | G282: Nacional Potosí | H282: 2 | I282: 3 | J282: The Strongest | K282: 3 | L282: 2 | M282: Gols +/- | N282: Mais de 2.0 | O282: 1.225 | P282: 0.5 | Q282: Green | R282: 0.11 | S282: 2026-08-05|Nacional Potosí|The Strongest | T282: 1 | W282: 1 | X282: 1 | Y282: 1
A283: 00106-ISL | B283: 46239 | C283: 0.625 | D283: ISL | E283: Besta-deild karla (PL) | F283: Keflavík 3 vs 0 KA Akureyri | G283: Keflavík | H283: 3 | I283: 0 | J283: KA Akureyri | K283: 0 | L283: 3 | M283: Gols +/- | N283: Mais de 2.0, 2.5 | O283: 1.24 | P283: 0.5 | Q283: Green | R283: 0.12 | S283: 2026-08-05|Keflavík|KA Akureyri | T283: 1 | W283: 1 | X283: 1 | Y283: 1
A284: 00107-FIN | B284: 46239 | C284: 0.54166667 | D284: FIN | E284: Ykkönen | F284: VJS 0 vs 0 Keski-Uusimaa | G284: VJS | H284: 0 | I284: 0 | J284: Keski-Uusimaa | K284: 0 | L284: 0 | M284: Gols +/- | N284: Mais de 2.0 | O284: 1.125 | P284: 0.5 | Q284: Red | R284: -0.5 | S284: 2026-08-05|VJS|Keski-Uusimaa | T284: 1 | W284: 1 | X284: 1 | Y284: 1
A285: 00108-FIN | B285: 46239 | C285: 0.52083333 | D285: FIN | E285: Ykkönen | F285: SalPa 2 vs 1 JJK Jyvaskyla | G285: SalPa | H285: 2 | I285: 1 | J285: JJK Jyvaskyla | K285: 1 | L285: 2 | M285: Gols +/- | N285: Mais de 2.0 | O285: 1.13 | P285: 0.5 | Q285: Green | R285: 0.06 | S285: 2026-08-05|SalPa|JJK Jyvaskyla | T285: 1 | W285: 1 | X285: 1 | Y285: 1
A286: 00109-FIN | B286: 46239 | C286: 0.52083333 | D286: FIN | E286: Ykkönen | F286: RoPS (Rovaniemi) 2 vs 2 Jazz Pori | G286: RoPS (Rovaniemi) | H286: 2 | I286: 2 | J286: Jazz Pori | K286: 2 | L286: 2 | M286: Gols +/- | N286: Mais de 2.0, 2.5 | O286: 1.225 | P286: 0.5 | Q286: Green | R286: 0.11 | S286: 2026-08-05|RoPS (Rovaniemi)|Jazz Pori | T286: 1 | W286: 1 | X286: 1 | Y286: 1
A287: 00110-FIN | B287: 46239 | C287: 0.5 | D287: FIN | E287: Ykkönen | F287: OLS Oulu 4 vs 2 TPV | G287: OLS Oulu | H287: 4 | I287: 2 | J287: TPV | K287: 2 | L287: 4 | M287: Gols +/- | N287: Mais de 1.5, 2.0 | O287: 1.12 | P287: 0.5 | Q287: Green | R287: 0.06 | S287: 2026-08-05|OLS Oulu|TPV | T287: 1 | W287: 1 | X287: 1 | Y287: 1
A288: 00111-BOL | B288: 46238 | C288: 0.875 | D288: BOL | E288: Div. Profesional | F288: Guabirá 3 vs 0 Real Tomayapo | G288: Guabirá | H288: 3 | I288: 0 | J288: Real Tomayapo | K288: 0 | L288: 3 | M288: Gols +/- | N288: Mais de 1.5 | O288: 1.115 | P288: 0.5 | Q288: Green | R288: 0.06 | S288: 2026-08-04|Guabirá|Real Tomayapo | T288: 1 | W288: 1 | X288: 1 | Y288: 1
... A305: 00130-SWE | B305: 46237 | C305: 0.58333333 | D305: SWE | E305: Allsvenskan | F305: Halmstads BK 0 vs 2 IK Sirius | G305: Halmstads BK | H305: 0 | I305: 2 | J305: IK Sirius | K305: 2 | L305: 0 | M305: Gols +/- | N305: Mais de 1.5 | O305: 1.13 | P305: 0.5 | Q305: Green | R305: 0.07 | S305: 2026-08-03|Halmstads BK|IK Sirius | T305: 1 | W305: 1 | X305: 1 | Y305: 1
A306: EST-00245 | B306: 46130 | C306: 0.45833333 | D306: FIN | E306: Kakkonen B | F306: P-Iirot Rauma 4 vs 0 MuSa | G306: P-Iirot Rauma | H306: 4 | I306: 0 | J306: MuSa | K306: 0 | L306: 4 | S306: 2026-04-18|P-Iirot Rauma|MuSa | T306: 1 | W306: 0 | X306: 0 | Y306: 0
A307: EST-00246 | B307: 46136 | C307: 0.52083333 | D307: FIN | E307: Kakkonen B | F307: MuSa 0 vs 6 Honka | G307: MuSa | H307: 0 | I307: 6 | J307: Honka | K307: 6 | L307: 0 | S307: 2026-04-24|MuSa|Honka | T307: 1 | W307: 0 | X307: 1 | Y307: 1
A308: EST-00247 | B308: 46144 | C308: 0.41666667 | D308: FIN | E308: Kakkonen B | F308: GrIFK 1 vs 1 MuSa | G308: GrIFK | H308: 1 | I308: 1 | J308: MuSa | K308: 1 | L308: 1 | S308: 2026-05-02|GrIFK|MuSa | T308: 1 | W308: 0 | X308: 0 | Y308: 0
A309: EST-00248 | B309: 46151 | C309: 0.41666667 | D309: FIN | E309: Kakkonen B | F309: MuSa 0 vs 2 HJS | G309: MuSa | H309: 0 | I309: 2 | J309: HJS | K309: 2 | L309: 0 | S309: 2026-05-09|MuSa|HJS | T309: 1 | W309: 0 | X309: 1 | Y309: 1
A310: EST-00249 | B310: 46158 | C310: 0.41666667 | D310: FIN | E310: Kakkonen B | F310: EPS 6 vs 1 MuSa | G310: EPS | H310: 6 | I310: 1 | J310: MuSa | K310: 1 | L310: 6 | S310: 2026-05-16|EPS|MuSa | T310: 1 | W310: 1 | X310: 1 | Y310: 1
A311: EST-00251 | B311: 46171 | C311: 0.52083333 | D311: FIN | E311: Kakkonen B | F311: AIFK 4 vs 2 MuSa | G311: AIFK | H311: 4 | I311: 2 | J311: MuSa | K311: 2 | L311: 4 | S311: 2026-05-29|AIFK|MuSa | T311: 1 | W311: 1 | X311: 1 | Y311: 1
A312: EST-00252 | B312: 46178 | C312: 0.52083333 | D312: FIN | E312: Kakkonen B | F312: MuSa 0 vs 0 NJS | G312: MuSa | H312: 0 | I312: 0 | J312: NJS | K312: 0 | L312: 0 | S312: 2026-06-05|MuSa|NJS | T312: 1 | W312: 1 | X312: 1 | Y312: 1
A313: EST-00253 | B313: 46185 | C313: 0.52083333 | D313: FIN | E313: Kakkonen B | F313: EBK 0 vs 2 MuSa | G313: EBK | H313: 0 | I313: 2 | J313: MuSa | K313: 2 | L313: 0 | S313: 2026-06-12|EBK|MuSa | T313: 1 | W313: 1 | X313: 1 | Y313: 1
A314: EST-00254 | B314: 46200 | C314: 0.45833333 | D314: FIN | E314: Kakkonen B | F314: MuSa 2 vs 2 P-Iirot Rauma | G314: MuSa | H314: 2 | I314: 2 | J314: P-Iirot Rauma | K314: 2 | L314: 2 | S314: 2026-06-27|MuSa|P-Iirot Rauma | T314: 1 | W314: 1 | X314: 1 | Y314: 1
A315: EST-00256 | B315: 46212 | C315: 0.52083333 | D315: FIN | E315: Kakkonen B | F315: MuSa 3 vs 1 GrIFK | G315: MuSa | H315: 3 | I315: 1 | J315: GrIFK | K315: 1 | L315: 3 | S315: 2026-07-09|MuSa|GrIFK | T315: 1 | W315: 1 | X315: 1 | Y315: 1
A316: EST-00257 | B316: 46221 | C316: 0.41666667 | D316: FIN | E316: Kakkonen B | F316: HJS 2 vs 1 MuSa | G316: HJS | H316: 2 | I316: 1 | J316: MuSa | K316: 1 | L316: 2 | S316: 2026-07-18|HJS|MuSa | T316: 1 | W316: 1 | X316: 1 | Y316: 1
A317: EST-00258 | B317: 46228 | C317: 0.41666667 | D317: FIN | E317: Kakkonen B | F317: MuSa 0 vs 2 EPS | G317: MuSa | H317: 0 | I317: 2 | J317: EPS | K317: 2 | L317: 0 | S317: 2026-07-25|MuSa|EPS | T317: 1 | W317: 1 | X317: 1 | Y317: 1
... A2818: EST-02962 | B2818: 46172 | C2818: 0.70833333 | D2818: BRA | E2818: Série C | F2818: Itabaiana 0 vs 1 Volta Redonda | G2818: Itabaiana | H2818: 0 | I2818: 1 | J2818: Volta Redonda | K2818: 1 | L2818: 0 | S2818: 2026-05-30|Itabaiana|Volta Redonda | T2818: 1 | W2818: 1 | X2818: 1 | Y2818: 1
A2819: EST-02964 | B2819: 46224 | C2819: 0.27083333 | D2819: AUS | E2819: Australia Cup | F2819: Lions FC 1 vs 1 Perth Glory (AET) | G2819: Lions FC | H2819: 1 | I2819: 1 | J2819: Perth Glory | K2819: 1 | L2819: 1 | M2819: Histórico / atualização web | S2819: 2026-07-21|Lions FC|Perth Glory | T2819: 1 | W2819: 0 | X2819: 0 | Y2819: 0
A2820: EST-02966 | B2820: 46186 | C2820: 0.083333333 | D2820: AUS | E2820: FFA Cup Qualifiers | F2820: Sunshine Coast Wanderers 0 vs 3 Lions FC | G2820: Sunshine Coast Wanderers | H2820: 0 | I2820: 3 | J2820: Lions FC | K2820: 3 | L2820: 0 | M2820: Histórico / atualização web | S2820: 2026-06-13|Sunshine Coast Wanderers|Lions FC | T2820: 1 | W2820: 0 | X2820: 0 | Y2820: 0
A2821: EST-02989 | B2821: 46242 | C2821: 0.91666667 | D2821: AUS | E2821: NPL New South Wales | F2821: Wollongong Wolves 1 vs 2 Sydney United | G2821: Wollongong Wolves | H2821: 1 | I2821: 2 | J2821: Sydney United | K2821: 2 | L2821: 1 | S2821: 2026-08-08|Wollongong Wolves|Sydney United | T2821: 1 | W2821: 1 | X2821: 1 | Y2821: 1
A2822: EST-02965 | B2822: 46215 | C2822: 0.16666667 | D2822: AUS | E2822: NPL Queensland | F2822: Lions FC 1 vs 0 Eastern Suburbs | G2822: Lions FC | H2822: 1 | I2822: 0 | J2822: Eastern Suburbs | K2822: 0 | L2822: 1 | M2822: Histórico / atualização web | S2822: 2026-07-12|Lions FC|Eastern Suburbs | T2822: 1 | W2822: 1 | X2822: 1 | Y2822: 1
A2823: EST-02963 | B2823: 46242 | C2823: 0.20833333 | D2823: AUS | E2823: NPL Queensland | F2823: Brisbane Olympic FC 1 vs 2 Moreton City Excelsior | G2823: Brisbane Olympic FC | H2823: 1 | I2823: 2 | J2823: Moreton City Excelsior | K2823: 2 | L2823: 1 | M2823: Histórico / atualização web | S2823: 2026-08-08|Brisbane Olympic FC|Moreton City Excelsior | T2823: 1 | W2823: 1 | X2823: 1 | Y2823: 1
A2824: EST-02990 | B2824: 46242 | C2824: 0.41666667 | D2824: AUS | E2824: NPL Queensland | F2824: Brisbane City 2 vs 0 Gold Coast Utd | G2824: Brisbane City | H2824: 2 | I2824: 0 | J2824: Gold Coast Utd | K2824: 0 | L2824: 2 | S2824: 2026-08-08|Brisbane City|Gold Coast Utd | T2824: 1 | W2824: 1 | X2824: 1 | Y2824: 1
A2825: EST-02991 | B2825: 46242 | C2825: 0.41666667 | D2825: AUS | E2825: NPL Queensland | F2825: Eastern Suburbs 0 vs 0 Wynnum Wolves | G2825: Eastern Suburbs | H2825: 0 | I2825: 0 | J2825: Wynnum Wolves | K2825: 0 | L2825: 0 | S2825: 2026-08-08|Eastern Suburbs|Wynnum Wolves | T2825: 1 | W2825: 1 | X2825: 1 | Y2825: 1
A2826: EST-02992 | B2826: 46242 | C2826: 0.41666667 | D2826: AUS | E2826: NPL Queensland | F2826: Gold Coast Knights 2 vs 2 Peninsula Power | G2826: Gold Coast Knights | H2826: 2 | I2826: 2 | J2826: Peninsula Power | K2826: 2 | L2826: 2 | S2826: 2026-08-08|Gold Coast Knights|Peninsula Power | T2826: 1 | W2826: 1 | X2826: 1 | Y2826: 1
A2827: EST-02993 | B2827: 46242 | C2827: 0.41666667 | D2827: AUS | E2827: NPL Queensland | F2827: Magic United 2 vs 1 Rochedale Rovers | G2827: Magic United | H2827: 2 | I2827: 1 | J2827: Rochedale Rovers | K2827: 1 | L2827: 2 | S2827: 2026-08-08|Magic United|Rochedale Rovers | T2827: 1 | W2827: 1 | X2827: 1 | Y2827: 1
A2828: EST-02994 | B2828: 46241 | C2828: 0.125 | D2828: AUS | E2828: NPL South Australia | F2828: Adelaide City 1 vs 0 Playford Patriots | G2828: Adelaide City | H2828: 1 | I2828: 0 | J2828: Playford Patriots | K2828: 0 | L2828: 1 | S2828: 2026-08-07|Adelaide City|Playford Patriots | T2828: 1 | W2828: 1 | X2828: 1 | Y2828: 1
A2829: EST-02995 | B2829: 46241 | C2829: 0.125 | D2829: AUS | E2829: NPL South Australia | F2829: Campbelltown City 2 vs 0 FK Beograd | G2829: Campbelltown City | H2829: 2 | I2829: 0 | J2829: FK Beograd | K2829: 0 | L2829: 2 | S2829: 2026-08-07|Campbelltown City|FK Beograd | T2829: 1 | W2829: 1 | X2829: 1 | Y2829: 1
A2830: EST-02997 | B2830: 46241 | C2830: 0.91666667 | D2830: AUS | E2830: NPL South Australia | F2830: Croydon 1 vs 1 Sturt Lions | G2830: Croydon | H2830: 1 | I2830: 1 | J2830: Sturt Lions | K2830: 1 | L2830: 1 | S2830: 2026-08-07|Croydon|Sturt Lions | T2830: 1 | W2830: 1 | X2830: 1 | Y2830: 1
A2831: EST-02996 | B2831: 46241 | C2831: 0.9375 | D2831: AUS | E2831: NPL South Australia | F2831: Adelaide United U23 5 vs 2 Para | G2831: Adelaide United U23 | H2831: 5 | I2831: 2 | J2831: Para | K2831: 2 | L2831: 5 | S2831: 2026-08-07|Adelaide United U23|Para | T2831: 1 | W2831: 1 | X2831: 1 | Y2831: 1
A2832: EST-02998 | B2832: 46245 | C2832: 0.14583333 | D2832: AUS | E2832: NPL South Australia | F2832: Sturt Lions 0 vs 0 Adelaide Comets | G2832: Sturt Lions | H2832: 0 | I2832: 0 | J2832: Adelaide Comets | K2832: 0 | L2832: 0 | S2832: 2026-08-11|Sturt Lions|Adelaide Comets | T2832: 1 | W2832: 1 | X2832: 1 | Y2832: 1
A2833: EST-03022 | B2833: 46150 | C2833: 0 | D2833: AUS | E2833: NPL Western Australia | F2833: Perth Azzurri 1 vs 1 Fremantle City | G2833: Perth Azzurri | H2833: 1 | I2833: 1 | J2833: Fremantle City | K2833: 1 | L2833: 1 | S2833: 2026-05-08|Perth Azzurri|Fremantle City | T2833: 1 | W2833: 1 | X2833: 1 | Y2833: 1
A2834: EST-03023 | B2834: 46151 | C2834: 0 | D2834: AUS | E2834: NPL Western Australia | F2834: Perth Glory U23 3 vs 1 Western Knights | G2834: Perth Glory U23 | H2834: 3 | I2834: 1 | J2834: Western Knights | K2834: 1 | L2834: 3 | S2834: 2026-05-09|Perth Glory U23|Western Knights | T2834: 1 | W2834: 1 | X2834: 1 | Y2834: 1
A2835: EST-03024 | B2835: 46151 | C2835: 0 | D2835: AUS | E2835: NPL Western Australia | F2835: Armadale 5 vs 0 Balcatta | G2835: Armadale | H2835: 5 | I2835: 0 | J2835: Balcatta | K2835: 0 | L2835: 5 | S2835: 2026-05-09|Armadale|Balcatta | T2835: 1 | W2835: 1 | X2835: 1 | Y2835: 1
... A3147: EST-03291 | B3147: 46242 | C3147: 0.33333333 | D3147: KOR | E3147: K League 2 | F3147: Seongnam FC 3 vs 2 Cheonan City FC | G3147: Seongnam FC | H3147: 3 | I3147: 2 | J3147: Cheonan City FC | K3147: 2 | L3147: 3 | S3147: 2026-08-08|Seongnam FC|Cheonan City FC | T3147: 1 | W3147: 1 | X3147: 1 | Y3147: 1

Sheet Ligas
A1: Liga | B1: Nível no País | C1: Partidas Únicas | D1: Média de Gols por Partida (Input) | E1: Média Efetiva da Liga | F1: Perfil da Liga | H1: País (aux) | I1: Liga (aux)
A2: ARG - Liga Profesional | B2: 1ª divisão | C2: =IF(A2="","",COUNTIFS(tblDados[País],H2,tblDados[Liga],I2,tblDados[Janela_12_Liga],1)) -> 4 | D2: 2.05 | E2: =IF(A2="","",IF(AND(I2<>"MLS-Cross",C2<30),"Insuficiente",IF(C2=0,"Insuficiente",(SUMIFS(tblDados[GM_M],tblDados[País],H2,tblDados[Liga],I2,tblDados[Janela_12_Liga],1)+SUMIFS(tblDados[GS_M],tblDados[País],H2,tblDados[Liga],I2,tblDados[Janela_12_Liga],1))/C2))) -> Insuficiente | F2: Poucos Gols | H2: =IF(A2="","",LEFT(A2,3)) -> ARG | I2: =IF(A2="","",_xlfn.TEXTAFTER(A2," - ")) -> Liga Profesional
A3: ARG - Primera Nacional | B3: 2ª divisão | C3: =IF(A3="","",COUNTIFS(tblDados[País],H3,tblDados[Liga],I3,tblDados[Janela_12_Liga],1)) -> 2 | D3: 1.92 | E3: =IF(A3="","",IF(AND(I3<>"MLS-Cross",C3<30),"Insuficiente",IF(C3=0,"Insuficiente",(SUMIFS(tblDados[GM_M],tblDados[País],H3,tblDados[Liga],I3,tblDados[Janela_12_Liga],1)+SUMIFS(tblDados[GS_M],tblDados[País],H3,tblDados[Liga],I3,tblDados[Janela_12_Liga],1))/C3))) -> Insuficiente | F3: Poucos Gols | H3: =IF(A3="","",LEFT(A3,3)) -> ARG | I3: =IF(A3="","",_xlfn.TEXTAFTER(A3," - ")) -> Primera Nacional
A4: BOL - Div. Profesional | B4: 3ª divisão | C4: =IF(A4="","",COUNTIFS(tblDados[País],H4,tblDados[Liga],I4,tblDados[Janela_12_Liga],1)) -> 97 | D4: 3.62 | E4: =IF(A4="","",IF(AND(I4<>"MLS-Cross",C4<30),"Insuficiente",IF(C4=0,"Insuficiente",(SUMIFS(tblDados[GM_M],tblDados[País],H4,tblDados[Liga],I4,tblDados[Janela_12_Liga],1)+SUMIFS(tblDados[GS_M],tblDados[País],H4,tblDados[Liga],I4,tblDados[Janela_12_Liga],1))/C4))) -> 2.9793814 | F4: Muitos Gols | H4: =IF(A4="","",LEFT(A4,3)) -> BOL | I4: =IF(A4="","",_xlfn.TEXTAFTER(A4," - ")) -> Div. Profesional
A5: BRA - Série A | B5: 3ª divisão | C5: =IF(A5="","",COUNTIFS(tblDados[País],H5,tblDados[Liga],I5,tblDados[Janela_12_Liga],1)) -> 124 | D5: 2.59 | E5: =IF(A5="","",IF(AND(I5<>"MLS-Cross",C5<30),"Insuficiente",IF(C5=0,"Insuficiente",(SUMIFS(tblDados[GM_M],tblDados[País],H5,tblDados[Liga],I5,tblDados[Janela_12_Liga],1)+SUMIFS(tblDados[GS_M],tblDados[País],H5,tblDados[Liga],I5,tblDados[Janela_12_Liga],1))/C5))) -> 2.5241935 | F5: Equilibrada | H5: =IF(A5="","",LEFT(A5,3)) -> BRA | I5: =IF(A5="","",_xlfn.TEXTAFTER(A5," - ")) -> Série A
A6: BRA - Série B | B6: 3ª divisão | C6: =IF(A6="","",COUNTIFS(tblDados[País],H6,tblDados[Liga],I6,tblDados[Janela_12_Liga],1)) -> 120 | D6: 2.31 | E6: =IF(A6="","",IF(AND(I6<>"MLS-Cross",C6<30),"Insuficiente",IF(C6=0,"Insuficiente",(SUMIFS(tblDados[GM_M],tblDados[País],H6,tblDados[Liga],I6,tblDados[Janela_12_Liga],1)+SUMIFS(tblDados[GS_M],tblDados[País],H6,tblDados[Liga],I6,tblDados[Janela_12_Liga],1))/C6))) -> 2.325 | F6: Poucos Gols | H6: =IF(A6="","",LEFT(A6,3)) -> BRA | I6: =IF(A6="","",_xlfn.TEXTAFTER(A6," - ")) -> Série B
A7: BRA - Série C | B7: 3ª divisão | C7: =IF(A7="","",COUNTIFS(tblDados[País],H7,tblDados[Liga],I7,tblDados[Janela_12_Liga],1)) -> 121 | D7: 2.09 | E7: =IF(A7="","",IF(AND(I7<>"MLS-Cross",C7<30),"Insuficiente",IF(C7=0,"Insuficiente",(SUMIFS(tblDados[GM_M],tblDados[País],H7,tblDados[Liga],I7,tblDados[Janela_12_Liga],1)+SUMIFS(tblDados[GS_M],tblDados[País],H7,tblDados[Liga],I7,tblDados[Janela_12_Liga],1))/C7))) -> 2.2727273 | F7: Poucos Gols | H7: =IF(A7="","",LEFT(A7,3)) -> BRA | I7: =IF(A7="","",_xlfn.TEXTAFTER(A7," - ")) -> Série C
A8: CAN - Premier League | B8: 3ª divisão | C8: =IF(A8="","",COUNTIFS(tblDados[País],H8,tblDados[Liga],I8,tblDados[Janela_12_Liga],1)) -> 49 | D8: 2.5 | E8: =IF(A8="","",IF(AND(I8<>"MLS-Cross",C8<30),"Insuficiente",IF(C8=0,"Insuficiente",(SUMIFS(tblDados[GM_M],tblDados[País],H8,tblDados[Liga],I8,tblDados[Janela_12_Liga],1)+SUMIFS(tblDados[GS_M],tblDados[País],H8,tblDados[Liga],I8,tblDados[Janela_12_Liga],1))/C8))) -> 3.0612245 | F8: Equilibrada | H8: =IF(A8="","",LEFT(A8,3)) -> CAN | I8: =IF(A8="","",_xlfn.TEXTAFTER(A8," - ")) -> Premier League
A9: CHI - Liga de Primera | B9: 3ª divisão | C9: =IF(A9="","",COUNTIFS(tblDados[País],H9,tblDados[Liga],I9,tblDados[Janela_12_Liga],1)) -> 98 | D9: 2.5 | E9: =IF(A9="","",IF(AND(I9<>"MLS-Cross",C9<30),"Insuficiente",IF(C9=0,"Insuficiente",(SUMIFS(tblDados[GM_M],tblDados[País],H9,tblDados[Liga],I9,tblDados[Janela_12_Liga],1)+SUMIFS(tblDados[GS_M],tblDados[País],H9,tblDados[Liga],I9,tblDados[Janela_12_Liga],1))/C9))) -> 3.0714286 | F9: Equilibrada | H9: =IF(A9="","",LEFT(A9,3)) -> CHI | I9: =IF(A9="","",_xlfn.TEXTAFTER(A9," - ")) -> Liga de Primera
A10: ECU - LigaPro Serie A | B10: 1ª divisão | C10: =IF(A10="","",COUNTIFS(tblDados[País],H10,tblDados[Liga],I10,tblDados[Janela_12_Liga],1)) -> 96 | D10: 2.5 | E10: =IF(A10="","",IF(AND(I10<>"MLS-Cross",C10<30),"Insuficiente",IF(C10=0,"Insuficiente",(SUMIFS(tblDados[GM_M],tblDados[País],H10,tblDados[Liga],I10,tblDados[Janela_12_Liga],1)+SUMIFS(tblDados[GS_M],tblDados[País],H10,tblDados[Liga],I10,tblDados[Janela_12_Liga],1))/C10))) -> 2.3541667 | F10: Equilibrada | H10: =IF(A10="","",LEFT(A10,3)) -> ECU | I10: =IF(A10="","",_xlfn.TEXTAFTER(A10," - ")) -> LigaPro Serie A
A11: FIN - Veikkausliiga | B11: 2ª divisão | C11: =IF(A11="","",COUNTIFS(tblDados[País],H11,tblDados[Liga],I11,tblDados[Janela_12_Liga],1)) -> 75 | D11: 2.6 | E11: =IF(A11="","",IF(AND(I11<>"MLS-Cross",C11<30),"Insuficiente",IF(C11=0,"Insuficiente",(SUMIFS(tblDados[GM_M],tblDados[País],H11,tblDados[Liga],I11,tblDados[Janela_12_Liga],1)+SUMIFS(tblDados[GS_M],tblDados[País],H11,tblDados[Liga],I11,tblDados[Janela_12_Liga],1))/C11))) -> 2.72 | F11: Equilibrada | H11: =IF(A11="","",LEFT(A11,3)) -> FIN | I11: =IF(A11="","",_xlfn.TEXTAFTER(A11," - ")) -> Veikkausliiga
A12: FIN - Ykkösliiga | B12: 1ª divisão | C12: =IF(A12="","",COUNTIFS(tblDados[País],H12,tblDados[Liga],I12,tblDados[Janela_12_Liga],1)) -> 62 | D12: 2.51 | E12: =IF(A12="","",IF(AND(I12<>"MLS-Cross",C12<30),"Insuficiente",IF(C12=0,"Insuficiente",(SUMIFS(tblDados[GM_M],tblDados[País],H12,tblDados[Liga],I12,tblDados[Janela_12_Liga],1)+SUMIFS(tblDados[GS_M],tblDados[País],H12,tblDados[Liga],I12,tblDados[Janela_12_Liga],1))/C12))) -> 2.483871 | F12: Equilibrada | H12: =IF(A12="","",LEFT(A12,3)) -> FIN | I12: =IF(A12="","",_xlfn.TEXTAFTER(A12," - ")) -> Ykkösliiga
A13: FIN - Ykkönen | B13: 1ª divisão | C13: =IF(A13="","",COUNTIFS(tblDados[País],H13,tblDados[Liga],I13,tblDados[Janela_12_Liga],1)) -> 73 | D13: 3.57 | E13: =IF(A13="","",IF(AND(I13<>"MLS-Cross",C13<30),"Insuficiente",IF(C13=0,"Insuficiente",(SUMIFS(tblDados[GM_M],tblDados[País],H13,tblDados[Liga],I13,tblDados[Janela_12_Liga],1)+SUMIFS(tblDados[GS_M],tblDados[País],H13,tblDados[Liga],I13,tblDados[Janela_12_Liga],1))/C13))) -> 3.5068493 | F13: Muitos Gols | H13: =IF(A13="","",LEFT(A13,3)) -> FIN | I13: =IF(A13="","",_xlfn.TEXTAFTER(A13," - ")) -> Ykkönen
... A41: KOR - K League 2 | B41: 2ª divisão | C41: =IF(A41="","",COUNTIFS(tblDados[País],H41,tblDados[Liga],I41,tblDados[Janela_12_Liga],1)) -> 78 | D41: 2.7 | E41: =IF(A41="","",IF(AND(I41<>"MLS-Cross",C41<30),"Insuficiente",IF(C41=0,"Insuficiente",(SUMIFS(tblDados[GM_M],tblDados[País],H41,tblDados[Liga],I41,tblDados[Janela_12_Liga],1)+SUMIFS(tblDados[GS_M],tblDados[País],H41,tblDados[Liga],I41,tblDados[Janela_12_Liga],1))/C41))) -> 2.6025641 | F41: Equilibrada | H41: =IF(A41="","",LEFT(A41,3)) -> KOR | I41: =IF(A41="","",_xlfn.TEXTAFTER(A41," - ")) -> K League 2

Sheet Equipes
A1: Equipe | B1: País - Liga | C1: IPM | D1: IPV | E1: TJM | F1: TJV | G1: TJT | H1: Média de Gols Marcados | I1: Média Golds da Liga | J1: % Sem Marcar | K1: % Over 0.5 | L1: % Over 1.5 | M1: % Over 2.5 | N1: % Over 3.5 | O1: % BTTS | P1: Variância | Q1: Dispersão | R1: Modelo Estatístico | S1: GMC | T1: GMV | U1: TGM | V1: MGM | W1: GSC | X1: GSV | Y1: TGS | Z1: MGS | AA1: FAM | AB1: VDM | AC1: FAV | AD1: VDV
A2: Aalesunds FK | B2: NOR - Eliteserien | C2: 3.8333333 | D2: 3.3333333 | E2: 6 | F2: 6 | G2: 12 | H2: 1.3333333 | I2: 2.5 | J2: 0.16666667 | K2: 1 | L2: 0.91666667 | M2: 0.58333333 | N2: 0.41666667 | O2: 0.83333333 | P2: 0.72222222 | Q2: 0.84983659 | R2: Poisson | S2: 10 | T2: 6 | U2: 16 | V2: 1.3333333 | W2: 13 | X2: 14 | Y2: 27 | Z2: 2.25 | AA2: 1.6666667 | AB2: 2.1666667 | AC2: 1 | AD2: 2.3333333
A3: ABB | B3: BOL - Div. Profesional | C3: 3.8333333 | D3: 4.1666667 | E3: 6 | F3: 6 | G3: 12 | H3: 1.8333333 | I3: 3.62 | J3: 0.083333333 | K3: 1 | L3: 0.91666667 | M3: 0.83333333 | N3: 0.75 | O3: 0.91666667 | P3: 1.3055556 | Q3: 1.1426091 | R3: Poisson | S3: 14 | T3: 8 | U3: 22 | V3: 1.8333333 | W3: 9 | X3: 17 | Y3: 26 | Z3: 2.1666667 | AA3: 2.3333333 | AB3: 1.5 | AC3: 1.3333333 | AD3: 2.8333333
A4: AC Oulu | B4: FIN - Veikkausliiga | C4: 1.8571429 | D4: 2.4 | E4: 7 | F4: 5 | G4: 12 | H4: 0.83333333 | I4: 2.6 | J4: 0.33333333 | K4: 0.91666667 | L4: 0.58333333 | M4: 0.33333333 | N4: 0.083333333 | O4: 0.41666667 | P4: 0.47222222 | Q4: 0.68718427 | R4: Poisson | S4: 7 | T4: 3 | U4: 10 | V4: 0.83333333 | W4: 6 | X4: 9 | Y4: 15 | Z4: 1.25 | AA4: 1 | AB4: 0.85714286 | AC4: 0.6 | AD4: 1.8
A5: Adelaide City | B5: AUS - NPL South Australia | C5: 2.8571429 | D5: 1.6 | E5: 7 | F5: 5 | G5: 12 | H5: 1.8333333 | I5: 3.7 | J5: 0.16666667 | K5: 0.83333333 | L5: 0.58333333 | M5: 0.5 | N5: 0.33333333 | O5: 0.33333333 | P5: 1.6388889 | Q5: 1.280191 | R5: Poisson | S5: 15 | T5: 7 | U5: 22 | V5: 1.8333333 | W5: 5 | X5: 1 | Y5: 6 | Z5: 0.5 | AA5: 2.1428571 | AB5: 0.71428571 | AC5: 1.4 | AD5: 0.2
A6: Adelaide Comets | B6: AUS - NPL South Australia | C6: 2.8333333 | D6: 2 | E6: 6 | F6: 6 | G6: 12 | H6: 1.0833333 | I6: 3.7 | J6: 0.41666667 | K6: 0.83333333 | L6: 0.5 | M6: 0.41666667 | N6: 0.41666667 | O6: 0.41666667 | P6: 1.5763889 | Q6: 1.2555433 | R6: Poisson | S6: 9 | T6: 4 | U6: 13 | V6: 1.0833333 | W6: 8 | X6: 8 | Y6: 16 | Z6: 1.3333333 | AA6: 1.5 | AB6: 1.3333333 | AC6: 0.66666667 | AD6: 1.3333333
A7: Adelaide United U23 | B7: AUS - NPL South Australia | C7: 2.4285714 | D7: 2.6 | E7: 7 | F7: 5 | G7: 12 | H7: 1.4166667 | I7: 3.7 | J7: 0.33333333 | K7: 0.75 | L7: 0.75 | M7: 0.41666667 | N7: 0.25 | O7: 0.41666667 | P7: 2.0763889 | Q7: 1.440968 | R7: Poisson | S7: 11 | T7: 6 | U7: 17 | V7: 1.4166667 | W7: 6 | X7: 7 | Y7: 13 | Z7: 1.0833333 | AA7: 1.5714286 | AB7: 0.85714286 | AC7: 1.2 | AD7: 1.4
A8: Aegir | B8: ISL - Lengjudeildin (1ªD) | C8: 3.8333333 | D8: 5.1666667 | E8: 6 | F8: 6 | G8: 12 | H8: 1.25 | I8: 3.55 | J8: 0.33333333 | K8: 0.91666667 | L8: 0.83333333 | M8: 0.75 | N8: 0.66666667 | O8: 0.66666667 | P8: 1.1875 | Q8: 1.0897247 | R8: Poisson | S8: 6 | T8: 9 | U8: 15 | V8: 1.25 | W8: 17 | X8: 22 | Y8: 39 | Z8: 3.25 | AA8: 1 | AB8: 2.8333333 | AC8: 1.5 | AD8: 3.6666667
A9: AFC Eskilstuna | B9: SWE - 1ª D Norra | C9: 2 | D9: 3.5 | E9: 6 | F9: 6 | G9: 12 | H9: 1.5833333 | I9: 2.5 | J9: 0.25 | K9: 0.91666667 | L9: 0.75 | M9: 0.58333333 | N9: 0.33333333 | O9: 0.5 | P9: 1.5763889 | Q9: 1.2555433 | R9: Poisson | S9: 5 | T9: 14 | U9: 19 | V9: 1.5833333 | W9: 7 | X9: 7 | Y9: 14 | Z9: 1.1666667 | AA9: 0.83333333 | AB9: 1.1666667 | AC9: 2.3333333 | AD9: 1.1666667
A10: AFC Malmö (Ariana FC Malmö) | B10: SWE - 1ª D Södra | C10: 3.1428571 | D10: 3.6 | E10: 7 | F10: 5 | G10: 12 | H10: 2.25 | I10: 2.5 | J10: 0.083333333 | K10: 1 | L10: 0.83333333 | M10: 0.75 | N10: 0.41666667 | O10: 0.58333333 | P10: 1.6875 | Q10: 1.2990381 | R10: Poisson | S10: 12 | T10: 15 | U10: 27 | V10: 2.25 | W10: 10 | X10: 3 | Y10: 13 | Z10: 1.0833333 | AA10: 1.7142857 | AB10: 1.4285714 | AC10: 3 | AD10: 0.6
A11: Afturelding | B11: ISL - Lengjudeildin (1ªD) | C11: 5.6666667 | D11: 3.6666667 | E11: 6 | F11: 6 | G11: 12 | H11: 3.1666667 | I11: 3.55 | J11: 0.083333333 | K11: 1 | L11: 0.91666667 | M11: 0.75 | N11: 0.66666667 | O11: 0.75 | P11: 5.1388889 | Q11: 2.2669118 | R11: Poisson | S11: 26 | T11: 12 | U11: 38 | V11: 3.1666667 | W11: 8 | X11: 10 | Y11: 18 | Z11: 1.5 | AA11: 4.3333333 | AB11: 1.3333333 | AC11: 2 | AD11: 1.6666667
A12: Ahlafors IF | B12: SWE - 2ª D Norra Götaland | C12: 3.4 | D12: 3.1428571 | E12: 5 | F12: 7 | G12: 12 | H12: 2.1666667 | I12: 2.5 | J12: 0.083333333 | K12: 0.91666667 | L12: 0.91666667 | M12: 0.58333333 | N12: 0.5 | O12: 0.58333333 | P12: 1.9722222 | Q12: 1.4043583 | R12: Poisson | S12: 11 | T12: 15 | U12: 26 | V12: 2.1666667 | W12: 6 | X12: 7 | Y12: 13 | Z12: 1.0833333 | AA12: 2.2 | AB12: 1.2 | AC12: 2.1428571 | AD12: 1
A13: AIFK | B13: FIN - Kakkonen B | C13: 2.6666667 | D13: 3.1666667 | E13: 6 | F13: 6 | G13: 12 | H13: 2 | I13: 3.56 | J13: 0.16666667 | K13: 1 | L13: 0.75 | M13: 0.5 | N13: 0.25 | O13: 0.66666667 | P13: 2.6666667 | Q13: 1.6329932 | R13: Poisson | S13: 10 | T13: 14 | U13: 24 | V13: 2 | W13: 6 | X13: 5 | Y13: 11 | Z13: 0.91666667 | AA13: 1.6666667 | AB13: 1 | AC13: 2.3333333 | AD13: 0.83333333
... A471: Zhejiang Professional FC | B471: CHN - Super League | C471: 4.4 | D471: 3.2857143 | E471: 5 | F471: 7 | G471: 12 | H471: 1.8333333 | I471: 2.5 | J471: 0.083333333 | K471: 1 | L471: 1 | M471: 0.75 | N471: 0.58333333 | O471: 0.83333333 | P471: 1.1388889 | Q471: 1.0671874 | R471: Poisson | S471: 11 | T471: 11 | U471: 22 | V471: 1.8333333 | W471: 11 | X471: 12 | Y471: 23 | Z471: 1.9166667 | AA471: 2.2 | AB471: 2.2 | AC471: 1.5714286 | AD471: 1.7142857
A472: Argentinos Jrs | B472: ARG - Primera Nacional | C472: 3 | E472: 1 | F472: 0 | G472: 1 | H472: 3 | I472: 1.92 | J472: 0 | K472: 1 | L472: 1 | M472: 1 | N472: 0 | O472: 0 | P472: 0 | Q472: 0 | R472: Amostra Insuficiente | S472: 3 | T472: 0 | U472: 3 | V472: 3 | W472: 0 | X472: 0 | Y472: 0 | Z472: 0 | AA472: 3 | AB472: 0
A473: Chivas Guadalajara | B473: MEX - Liga MX | D473: 2 | E473: 0 | F473: 1 | G473: 1 | H473: 1 | I473: 3.91 | J473: 0 | K473: 1 | L473: 1 | M473: 0 | N473: 0 | O473: 1 | P473: 0 | Q473: 0 | R473: Amostra Insuficiente | S473: 0 | T473: 1 | U473: 1 | V473: 1 | W473: 0 | X473: 1 | Y473: 1 | Z473: 1 | AC473: 1 | AD473: 1
A474: Club León | B474: MEX - Liga MX | C474: 1 | E474: 1 | F474: 0 | G474: 1 | H474: 1 | I474: 3.91 | J474: 0 | K474: 1 | L474: 0 | M474: 0 | N474: 0 | O474: 0 | P474: 0 | Q474: 0 | R474: Amostra Insuficiente | S474: 1 | T474: 0 | U474: 1 | V474: 1 | W474: 0 | X474: 0 | Y474: 0 | Z474: 0 | AA474: 1 | AB474: 0
A475: Defensa y Justicia | B475: ARG - Liga Profesional | C475: 3 | E475: 1 | F475: 0 | G475: 1 | H475: 2 | I475: 2.05 | J475: 0 | K475: 1 | L475: 1 | M475: 1 | N475: 0 | O475: 1 | P475: 0 | Q475: 0 | R475: Amostra Insuficiente | S475: 2 | T475: 0 | U475: 2 | V475: 2 | W475: 1 | X475: 0 | Y475: 1 | Z475: 1 | AA475: 2 | AB475: 1
A476: Deportivo Riestra | B476: ARG - Liga Profesional | D476: 3 | E476: 0 | F476: 1 | G476: 1 | H476: 1 | I476: 2.05 | J476: 0 | K476: 1 | L476: 1 | M476: 1 | N476: 0 | O476: 1 | P476: 0 | Q476: 0 | R476: Amostra Insuficiente | S476: 0 | T476: 1 | U476: 1 | V476: 1 | W476: 0 | X476: 2 | Y476: 2 | Z476: 2 | AC476: 1 | AD476: 2
A477: Estudiantes Rio Cuarto | B477: ARG - Primera Nacional | D477: 3 | E477: 0 | F477: 1 | G477: 1 | H477: 0 | I477: 1.92 | J477: 1 | K477: 1 | L477: 1 | M477: 1 | N477: 0 | O477: 0 | P477: 0 | Q477: 0 | R477: Amostra Insuficiente | S477: 0 | T477: 0 | U477: 0 | V477: 0 | W477: 0 | X477: 3 | Y477: 3 | Z477: 3 | AC477: 0 | AD477: 3
A478: Gimnasia LP | B478: ARG - Liga Profesional | C478: 1 | E478: 1 | F478: 0 | G478: 1 | H478: 1 | I478: 2.05 | J478: 0 | K478: 1 | L478: 0 | M478: 0 | N478: 0 | O478: 0 | P478: 0 | Q478: 0 | R478: Amostra Insuficiente | S478: 1 | T478: 0 | U478: 1 | V478: 1 | W478: 0 | X478: 0 | Y478: 0 | Z478: 0 | AA478: 1 | AB478: 0
A479: Huracán | B479: ARG - Liga Profesional | D479: 3 | E479: 0 | F479: 1 | G479: 1 | H479: 1 | I479: 2.05 | J479: 0 | K479: 1 | L479: 1 | M479: 1 | N479: 0 | O479: 1 | P479: 0 | Q479: 0 | R479: Amostra Insuficiente | S479: 0 | T479: 1 | U479: 1 | V479: 1 | W479: 0 | X479: 2 | Y479: 2 | Z479: 2 | AC479: 1 | AD479: 2
A480: Independiente Rivadavia | B480: ARG - Liga Profesional | C480: 3 | E480: 1 | F480: 0 | G480: 1 | H480: 2 | I480: 2.05 | J480: 0 | K480: 1 | L480: 1 | M480: 1 | N480: 0 | O480: 1 | P480: 0 | Q480: 0 | R480: Amostra Insuficiente | S480: 2 | T480: 0 | U480: 2 | V480: 2 | W480: 1 | X480: 0 | Y480: 1 | Z480: 1 | AA480: 2 | AB480: 1
A481: Instituto Córdoba | B481: ARG - Liga Profesional | C481: 3 | E481: 1 | F481: 0 | G481: 1 | H481: 2 | I481: 2.05 | J481: 0 | K481: 1 | L481: 1 | M481: 1 | N481: 0 | O481: 1 | P481: 0 | Q481: 0 | R481: Amostra Insuficiente | S481: 2 | T481: 0 | U481: 2 | V481: 2 | W481: 1 | X481: 0 | Y481: 1 | Z481: 1 | AA481: 2 | AB481: 1
A482: M. Wanderers | B482: URU - Liga AUF | D482: 2 | E482: 0 | F482: 1 | G482: 1 | H482: 2 | I482: 2.5 | J482: 0 | K482: 1 | L482: 1 | M482: 0 | N482: 0 | O482: 0 | P482: 0 | Q482: 0 | R482: Amostra Insuficiente | S482: 0 | T482: 2 | U482: 2 | V482: 2 | W482: 0 | X482: 0 | Y482: 0 | Z482: 0 | AC482: 2 | AD482: 0
A483: Montevideo City Torque | B483: URU - Liga AUF | C483: 2 | E483: 1 | F483: 0 | G483: 1 | H483: 0 | I483: 2.5 | J483: 1 | K483: 1 | L483: 1 | M483: 0 | N483: 0 | O483: 0 | P483: 0 | Q483: 0 | R483: Amostra Insuficiente | S483: 0 | T483: 0 | U483: 0 | V483: 0 | W483: 2 | X483: 0 | Y483: 2 | Z483: 2 | AA483: 0 | AB483: 2
A484: Pachuca | B484: MEX - Liga MX | D484: 1 | E484: 0 | F484: 1 | G484: 1 | H484: 0 | I484: 3.91 | J484: 1 | K484: 1 | L484: 0 | M484: 0 | N484: 0 | O484: 0 | P484: 0 | Q484: 0 | R484: Amostra Insuficiente | S484: 0 | T484: 0 | U484: 0 | V484: 0 | W484: 0 | X484: 1 | Y484: 1 | Z484: 1 | AC484: 0 | AD484: 1
A485: Platense | B485: ARG - Liga Profesional | D485: 3 | E485: 0 | F485: 1 | G485: 1 | H485: 1 | I485: 2.05 | J485: 0 | K485: 1 | L485: 1 | M485: 1 | N485: 0 | O485: 1 | P485: 0 | Q485: 0 | R485: Amostra Insuficiente | S485: 0 | T485: 1 | U485: 1 | V485: 1 | W485: 0 | X485: 2 | Y485: 2 | Z485: 2 | AC485: 1 | AD485: 2
A486: Puebla | B486: MEX - Liga MX | C486: 2 | E486: 1 | F486: 0 | G486: 1 | H486: 1 | I486: 3.91 | J486: 0 | K486: 1 | L486: 1 | M486: 0 | N486: 0 | O486: 1 | P486: 0 | Q486: 0 | R486: Amostra Insuficiente | S486: 1 | T486: 0 | U486: 1 | V486: 1 | W486: 1 | X486: 0 | Y486: 1 | Z486: 1 | AA486: 1 | AB486: 1
A487: Racing Club | B487: ARG - Primera Nacional | D487: 0 | E487: 0 | F487: 1 | G487: 1 | H487: 0 | I487: 1.92 | J487: 1 | K487: 0 | L487: 0 | M487: 0 | N487: 0 | O487: 0 | P487: 0 | Q487: 0 | R487: Amostra Insuficiente | S487: 0 | T487: 0 | U487: 0 | V487: 0 | W487: 0 | X487: 0 | Y487: 0 | Z487: 0 | AC487: 0 | AD487: 0
A488: River Plate | B488: ARG - Liga Profesional | D488: 1 | E488: 0 | F488: 1 | G488: 1 | H488: 0 | I488: 2.05 | J488: 1 | K488: 1 | L488: 0 | M488: 0 | N488: 0 | O488: 0 | P488: 0 | Q488: 0 | R488: Amostra Insuficiente | S488: 0 | T488: 0 | U488: 0 | V488: 0 | W488: 0 | X488: 1 | Y488: 1 | Z488: 1 | AC488: 0 | AD488: 1
A489: Rosario Central | B489: ARG - Primera Nacional | C489: 0 | E489: 1 | F489: 0 | G489: 1 | H489: 0 | I489: 1.92 | J489: 1 | K489: 0 | L489: 0 | M489: 0 | N489: 0 | O489: 0 | P489: 0 | Q489: 0 | R489: Amostra Insuficiente | S489: 0 | T489: 0 | U489: 0 | V489: 0 | W489: 0 | X489: 0 | Y489: 0 | Z489: 0 | AA489: 0 | AB489: 0
A490: Perth Glory | B490: AUS - Australia Cup | E490: 0 | F490: 0 | G490: 0 | H490: 0 | I490: 0 | J490: 0 | K490: 0 | L490: 0 | M490: 0 | N490: 0 | O490: 0 | P490: 0 | Q490: 0 | R490: Amostra Insuficiente | S490: 0 | T490: 0 | U490: 0 | V490: 0 | W490: 0 | X490: 0 | Y490: 0 | Z490: 0
A491: Sunshine Coast Wanderers | B491: AUS - FFA Cup Qualifiers | E491: 0 | F491: 0 | G491: 0 | H491: 0 | I491: 0 | J491: 0 | K491: 0 | L491: 0 | M491: 0 | N491: 0 | O491: 0 | P491: 0 | Q491: 0 | R491: Amostra Insuficiente | S491: 0 | T491: 0 | U491: 0 | V491: 0 | W491: 0 | X491: 0 | Y491: 0 | Z491: 0
A492: Ulsan HD FC | B492: KOR - K League 1 | C492: 2.6666667 | D492: 2.8333333 | E492: 6 | F492: 6 | G492: 12 | H492: 1.5 | I492: 2.4 | J492: 0.16666667 | K492: 1 | L492: 0.83333333 | M492: 0.58333333 | N492: 0.33333333 | O492: 0.66666667 | P492: 1 | Q492: 1 | R492: Poisson | S492: 8 | T492: 10 | U492: 18 | V492: 1.5 | W492: 8 | X492: 7 | Y492: 15 | Z492: 1.25 | AA492: 1.3333333 | AB492: 1.3333333 | AC492: 1.6666667 | AD492: 1.1666667
A493: Gangwon FC | B493: KOR - K League 1 | C493: 2.3333333 | D493: 1.5 | E493: 6 | F493: 6 | G493: 12 | H493: 1.0833333 | I493: 2.4 | J493: 0.25 | K493: 0.83333333 | L493: 0.75 | M493: 0.33333333 | N493: 0 | O493: 0.41666667 | P493: 0.62878788 | Q493: 0.79296146 | R493: Poisson | S493: 8 | T493: 5 | U493: 13 | V493: 1.0833333 | W493: 6 | X493: 4 | Y493: 10 | Z493: 0.83333333 | AA493: 1.3333333 | AB493: 1 | AC493: 0.83333333 | AD493: 0.66666667
A494: Incheon United | B494: KOR - K League 1 | C494: 1.5714286 | D494: 2.6 | E494: 7 | F494: 5 | G494: 12 | H494: 1.25 | I494: 2.4 | J494: 0.41666667 | K494: 0.91666667 | L494: 0.41666667 | M494: 0.33333333 | N494: 0.16666667 | O494: 0.25 | P494: 2.0227273 | Q494: 1.4222262 | R494: Binomial Negativa | S494: 7 | T494: 8 | U494: 15 | V494: 1.25 | W494: 4 | X494: 5 | Y494: 9 | Z494: 0.75 | AA494: 1 | AB494: 0.57142857 | AC494: 1.6 | AD494: 1
A495: Gimcheon Sangmu | B495: KOR - K League 1 | C495: 2.5 | D495: 2.5 | E495: 6 | F495: 6 | G495: 12 | H495: 1.0833333 | I495: 2.4 | J495: 0.33333333 | K495: 0.91666667 | L495: 0.75 | M495: 0.41666667 | N495: 0.25 | O495: 0.58333333 | P495: 1.1742424 | Q495: 1.0836247 | R495: Poisson | S495: 6 | T495: 7 | U495: 13 | V495: 1.0833333 | W495: 9 | X495: 8 | Y495: 17 | Z495: 1.4166667 | AA495: 1 | AB495: 1.5 | AC495: 1.1666667 | AD495: 1.3333333
A496: Bucheon FC 1995 | B496: KOR - K League 1 | C496: 2 | D496: 2.1666667 | E496: 6 | F496: 6 | G496: 12 | H496: 1.0833333 | I496: 2.4 | J496: 0.33333333 | K496: 0.83333333 | L496: 0.58333333 | M496: 0.33333333 | N496: 0.25 | O496: 0.41666667 | P496: 0.99242424 | Q496: 0.99620492 | R496: Poisson | S496: 5 | T496: 8 | U496: 13 | V496: 1.0833333 | W496: 7 | X496: 5 | Y496: 12 | Z496: 1 | AA496: 0.83333333 | AB496: 1.1666667 | AC496: 1.3333333 | AD496: 0.83333333
A497: Jeonbuk FC | B497: KOR - K League 1 | C497: 2 | D497: 1.8333333 | E497: 6 | F497: 6 | G497: 12 | H497: 1.25 | I497: 2.4 | J497: 0.33333333 | K497: 0.75 | L497: 0.58333333 | M497: 0.33333333 | N497: 0.25 | O497: 0.33333333 | P497: 1.6590909 | Q497: 1.288057 | R497: Poisson | S497: 7 | T497: 8 | U497: 15 | V497: 1.25 | W497: 5 | X497: 3 | Y497: 8 | Z497: 0.66666667 | AA497: 1.1666667 | AB497: 0.83333333 | AC497: 1.3333333 | AD497: 0.5
A498: Seoul E-Land FC | B498: KOR - K League 2 | C498: 4 | D498: 2.5 | E498: 6 | F498: 6 | G498: 12 | H498: 1.75 | I498: 2.7 | J498: 0.16666667 | K498: 0.91666667 | L498: 0.83333333 | M498: 0.83333333 | N498: 0.41666667 | O498: 0.75 | P498: 1.4772727 | Q498: 1.2154311 | R498: Poisson | S498: 13 | T498: 8 | U498: 21 | V498: 1.75 | W498: 11 | X498: 7 | Y498: 18 | Z498: 1.5 | AA498: 2.1666667 | AB498: 1.8333333 | AC498: 1.3333333 | AD498: 1.1666667
A499: Ansan Greeners | B499: KOR - K League 2 | C499: 3.1428571 | D499: 2.6 | E499: 7 | F499: 5 | G499: 12 | H499: 0.91666667 | I499: 2.7 | J499: 0.33333333 | K499: 1 | L499: 0.83333333 | M499: 0.66666667 | N499: 0.33333333 | O499: 0.58333333 | P499: 0.62878788 | Q499: 0.79296146 | R499: Poisson | S499: 9 | T499: 2 | U499: 11 | V499: 0.91666667 | W499: 13 | X499: 11 | Y499: 24 | Z499: 2 | AA499: 1.2857143 | AB499: 1.8571429 | AC499: 0.4 | AD499: 2.2
A500: Daegu FC | B500: KOR - K League 2 | C500: 2.8 | D500: 3.1428571 | E500: 5 | F500: 7 | G500: 12 | H500: 1.9166667 | I500: 2.7 | J500: 0.083333333 | K500: 0.91666667 | L500: 0.75 | M500: 0.5 | N500: 0.33333333 | O500: 0.58333333 | P500: 2.2651515 | Q500: 1.505042 | R500: Poisson | S500: 10 | T500: 13 | U500: 23 | V500: 1.9166667 | W500: 4 | X500: 9 | Y500: 13 | Z500: 1.0833333 | AA500: 2 | AB500: 0.8 | AC500: 1.8571429 | AD500: 1.2857143
A501: Chungnam Asan FC | B501: KOR - K League 2 | C501: 2.6666667 | D501: 2.1666667 | E501: 6 | F501: 6 | G501: 12 | H501: 1.3333333 | I501: 2.7 | J501: 0.25 | K501: 0.91666667 | L501: 0.75 | M501: 0.41666667 | N501: 0.25 | O501: 0.5 | P501: 0.96969697 | Q501: 0.98473193 | R501: Poisson | S501: 10 | T501: 6 | U501: 16 | V501: 1.3333333 | W501: 6 | X501: 7 | Y501: 13 | Z501: 1.0833333 | AA501: 1.6666667 | AB501: 1 | AC501: 1 | AD501: 1.1666667
A502: Gimpo FC | B502: KOR - K League 2 | C502: 2.5 | D502: 2 | E502: 6 | F502: 6 | G502: 12 | H502: 1.1666667 | I502: 2.7 | J502: 0.16666667 | K502: 1 | L502: 0.83333333 | M502: 0.33333333 | N502: 0.083333333 | O502: 0.58333333 | P502: 0.6969697 | Q502: 0.83484711 | R502: Poisson | S502: 8 | T502: 6 | U502: 14 | V502: 1.1666667 | W502: 7 | X502: 6 | Y502: 13 | Z502: 1.0833333 | AA502: 1.3333333 | AB502: 1.1666667 | AC502: 1 | AD502: 1
A503: Cheonan City FC | B503: KOR - K League 2 | C503: 2 | D503: 3.7142857 | E503: 6 | F503: 7 | G503: 13 | H503: 1.3076923 | I503: 2.7 | J503: 0.30769231 | K503: 0.92307692 | L503: 0.61538462 | M503: 0.53846154 | N503: 0.46153846 | O503: 0.61538462 | P503: 1.2307692 | Q503: 1.1094004 | R503: Poisson | S503: 6 | T503: 11 | U503: 17 | V503: 1.3076923 | W503: 6 | X503: 15 | Y503: 21 | Z503: 1.6153846 | AA503: 1 | AB503: 1 | AC503: 1.5714286 | AD503: 2.1428571
... A505: Seongnam FC | B505: KOR - K League 2 | C505: 2 | D505: 2.4285714 | E505: 5 | F505: 7 | G505: 12 | H505: 1 | I505: 2.7 | J505: 0.33333333 | K505: 0.83333333 | L505: 0.66666667 | M505: 0.33333333 | N505: 0.25 | O505: 0.58333333 | P505: 0.90909091 | Q505: 0.95346259 | R505: Poisson | S505: 6 | T505: 6 | U505: 12 | V505: 1 | W505: 4 | X505: 11 | Y505: 15 | Z505: 1.25 | AA505: 1.2 | AB505: 0.8 | AC505: 0.85714286 | AD505: 1.5714286

Sheet Ranking
A1: RANKING DE EQUIPES — ADERÊNCIA ÀS LINHAS OVER | V1: _Índice | W1: _Ajustado | X1: _Chave
A2: Top 40 automático · TJT mínimo de 4 jogos · filtro Over 0.5 ≥90% · MLS-Cross excluída | V2: =IF(AND(Equipes!A2<>"",Equipes!B2<>"USA - MLS-Cross",Equipes!G2>=4,Equipes!K2>=90%),IFERROR((Equipes!C2*Equipes!E2+Equipes!D2*Equipes!F2)/Equipes!G2,0),"") -> 3.5833333 | W2: =IF(V2="","",IFERROR((Equipes!G2/(Equipes!G2+4))*V2+(1-Equipes!G2/(Equipes!G2+4))*Equipes!I2,V2)) -> 3.3125 | X2: =IF(V2="","",ROUND(Equipes!L2*1000000000,0)+ROUND(W2*1000000,0)+Equipes!G2*1000+(1001-ROW())) -> 919992166
A3: O Over 0.5 funciona como filtro obrigatório de segurança. A ordenação principal utiliza o Over 1.5; Potencial Ajustado e TJT são utilizados como desempates. | V3: =IF(AND(Equipes!A3<>"",Equipes!B3<>"USA - MLS-Cross",Equipes!G3>=4,Equipes!K3>=90%),IFERROR((Equipes!C3*Equipes!E3+Equipes!D3*Equipes!F3)/Equipes!G3,0),"") -> 4 | W3: =IF(V3="","",IFERROR((Equipes!G3/(Equipes!G3+4))*V3+(1-Equipes!G3/(Equipes!G3+4))*Equipes!I3,V3)) -> 3.905 | X3: =IF(V3="","",ROUND(Equipes!L3*1000000000,0)+ROUND(W3*1000000,0)+Equipes!G3*1000+(1001-ROW())) -> 920584665
A4: Posição | B4: Equipe | C4: País - Liga | D4: TJT | E4: IPM | F4: IPV | G4: Índice Geral | H4: Potencial Ajustado | I4: Índice Normalizado | J4: Média de Gols Marcados | K4: Média da Liga | L4: Over 0.5 | M4: Over 1.5 | N4: Over 2.5 | O4: Over 3.5 | P4: BTTS | Q4: % Sem Marcar | R4: Modelo Estatístico | S4: Qualidade da Amostra | T4: Decisão
A5: {=_xlfn.LET(_xlpm.teams,_xlfn._xlws.FILTER(Equipes!A2:A1000,(Equipes!A2:A1000<>"")*(Equipes!B2:B1000<>"USA - MLS-Cross")*(Equipes!G2:G1000>=4)*(Equipes!K2:K1000>=90%)),_xlpm.leagues,_xlfn._xlws.FILTER(Equipes!B2:B1000,(Equipes!A2:A1000<>"")*(Equipes!B2:B1000<>"USA - MLS-Cross")*(Equipes!G2:G1000>=4)*(Equipes!K2:K1000>=90%)),_xlpm.homegames,_xlfn._xlws.FILTER(Equipes!E2:E1000,(Equipes!A2:A1000<>"")*(Equipes!B2:B1000<>"USA - MLS-Cross")*(Equipes!G2:G1000>=4)*(Equipes!K2:K1000>=90%)),_xlpm.awaygames,_xlfn._xlws.FILTER(Equipes!F2:F1000,(Equipes!A2:A1000<>"")*(Equipes!B2:B1000<>"USA - MLS-Cross")*(Equipes!G2:G1000>=4)*(Equipes!K2:K1000>=90%)),_xlpm.games,_xlfn._xlws.FILTER(Equipes!G2:G1000,(Equipes!A2:A1000<>"")*(Equipes!B2:B1000<>"USA - MLS-Cross")*(Equipes!G2:G1000>=4)*(Equipes!K2:K1000>=90%)),_xlpm.homeindex,_xlfn._xlws.FILTER(Equipes!C2:C1000,(Equipes!A2:A1000<>"")*(Equipes!B2:B1000<>"USA - MLS-Cross")*(Equipes!G2:G1000>=4)*(Equipes!K2:K1000>=90%)),_xlpm.awayindex,_xlfn._xlws.FILTER(Equipes!D2:D1000,(Equipes!A2:A1000<>"")*(Equipes!B2:B1000<>"USA - MLS-Cross")*(Equipes!G2:G1000>=4)*(Equipes!K2:K1000>=90%)),_xlpm.goalsavg,_xlfn._xlws.FILTER(Equipes!H2:H1000,(Equipes!A2:A1000<>"")*(Equipes!B2:B1000<>"USA - MLS-Cross")*(Equipes!G2:G1000>=4)*(Equipes!K2:K1000>=90%)),_xlpm.leagueavg,_xlfn._xlws.FILTER(Equipes!I2:I1000,(Equipes!A2:A1000<>"")*(Equipes!B2:B1000<>"USA - MLS-Cross")*(Equipes!G2:G1000>=4)*(Equipes!K2:K1000>=90%)),_xlpm.over05,_xlfn._xlws.FILTER(Equipes!K2:K1000,(Equipes!A2:A1000<>"")*(Equipes!B2:B1000<>"USA - MLS-Cross")*(Equipes!G2:G1000>=4)*(Equipes!K2:K1000>=90%)),_xlpm.over15,_xlfn._xlws.FILTER(Equipes!L2:L1000,(Equipes!A2:A1000<>"")*(Equipes!B2:B1000<>"USA - MLS-Cross")*(Equipes!G2:G1000>=4)*(Equipes!K2:K1000>=90%)),_xlpm.over25,_xlfn._xlws.FILTER(Equipes!M2:M1000,(Equipes!A2:A1000<>"")*(Equipes!B2:B1000<>"USA - MLS-Cross")*(Equipes!G2:G1000>=4)*(Equipes!K2:K1000>=90%)),_xlpm.over35,_xlfn._xlws.FILTER(Equipes!N2:N1000,(Equipes!A2:A1000<>"")*(Equipes!B2:B1000<>"USA - MLS-Cross")*(Equipes!G2:G1000>=4)*(Equipes!K2:K1000>=90%)),_xlpm.bothscore,_xlfn._xlws.FILTER(Equipes!O2:O1000,(Equipes!A2:A1000<>"")*(Equipes!B2:B1000<>"USA - MLS-Cross")*(Equipes!G2:G1000>=4)*(Equipes!K2:K1000>=90%)),_xlpm.nomark,_xlfn._xlws.FILTER(Equipes!J2:J1000,(Equipes!A2:A1000<>"")*(Equipes!B2:B1000<>"USA - MLS-Cross")*(Equipes!G2:G1000>=4)*(Equipes!K2:K1000>=90%)),_xlpm.model,_xlfn._xlws.FILTER(Equipes!R2:R1000,(Equipes!A2:A1000<>"")*(Equipes!B2:B1000<>"USA - MLS-Cross")*(Equipes!G2:G1000>=4)*(Equipes!K2:K1000>=90%)),_xlpm.score,IFERROR((_xlpm.homeindex*_xlpm.homegames+_xlpm.awayindex*_xlpm.awaygames)/_xlpm.games,0),_xlpm.weight,_xlpm.games/(_xlpm.games+4),_xlpm.adjusted,IFERROR(_xlpm.weight*_xlpm.score+(1-_xlpm.weight)*_xlpm.leagueavg,_xlpm.score),_xlpm.normalized,IFERROR(_xlpm.score/_xlpm.leagueavg,0),_xlpm.quality,IF(_xlpm.games>=8,"Robusta","Em formação"),_xlpm.dataset,_xlfn.HSTACK(_xlpm.teams,_xlpm.leagues,_xlpm.games,_xlpm.homeindex,_xlpm.awayindex,_xlpm.score,_xlpm.adjusted,_xlpm.normalized,_xlpm.goalsavg,_xlpm.leagueavg,_xlpm.over05,_xlpm.over15,_xlpm.over25,_xlpm.over35,_xlpm.bothscore,_xlpm.nomark,_xlpm.model,_xlpm.quality),_xlpm.sorted,_xlfn.SORTBY(_xlpm.dataset,_xlpm.over15,-1,_xlpm.adjusted,-1,_xlpm.games,-1),_xlpm.topteams,_xlfn.TAKE(_xlpm.sorted,MIN(40,ROWS(_xlpm.sorted))),_xlfn.HSTACK(_xlfn.SEQUENCE(ROWS(_xlpm.topteams)),_xlpm.topteams,IF(_xlfn.SEQUENCE(ROWS(_xlpm.topteams))>0,"Selecionada","")))} -> 1 | B5: Para | C5: AUS - NPL South Australia | D5: 12 | E5: 5.8 | F5: 5.1428571 | G5: 5.4166667 | H5: 4.9875 | I5: 1.463964 | J5: 0.58333333 | K5: 3.7 | L5: 1 | M5: 1 | N5: 0.83333333 | O5: 0.66666667 | P5: 0.41666667 | Q5: 0.58333333 | R5: Poisson | S5: Robusta | T5: Selecionada
A6: 2 | B6: Närpes Kraft | C6: FIN - Kakkonen C | D6: 12 | E6: 5.4285714 | F6: 4.8 | G6: 5.1666667 | H6: 4.955 | I6: 1.1959877 | J6: 2.9166667 | K6: 4.32 | L6: 1 | M6: 1 | N6: 1 | O6: 0.75 | P6: 0.83333333 | Q6: 0 | R6: Poisson | S6: Robusta | T6: Selecionada
A7: 3 | B7: KR Reykjavik (KR Reykjavík) | C7: ISL - Besta-deild karla (PL) | D7: 12 | E7: 6 | F7: 5.1666667 | G7: 5.5833333 | H7: 4.8125 | I7: 2.2333333 | J7: 3.25 | K7: 2.5 | L7: 1 | M7: 1 | N7: 0.83333333 | O7: 0.83333333 | P7: 0.83333333 | Q7: 0.083333333 | R7: Poisson | S7: Robusta | T7: Selecionada
A8: 4 | B8: FK Haugesund | C8: NOR - OBOS-ligaen | D8: 12 | E8: 4.8333333 | F8: 6.3333333 | G8: 5.5833333 | H8: 4.8125 | I8: 2.2333333 | J8: 3.4166667 | K8: 2.5 | L8: 1 | M8: 1 | N8: 0.91666667 | O8: 0.83333333 | P8: 0.91666667 | Q8: 0 | R8: Poisson | S8: Robusta | T8: Selecionada
A9: 5 | B9: FC Cincinnati | C9: USA - MLS-East | D9: 12 | E9: 6.1666667 | F9: 4.6666667 | G9: 5.4166667 | H9: 4.6875 | I9: 2.1666667 | J9: 3 | K9: 2.5 | L9: 1 | M9: 1 | N9: 0.83333333 | O9: 0.75 | P9: 0.91666667 | Q9: 0 | R9: Poisson | S9: Robusta | T9: Selecionada
A10: 6 | B10: VPS Akatemia | C10: FIN - Kakkonen C | D10: 12 | E10: 5.6 | F10: 4.1428571 | G10: 4.75 | H10: 4.6425 | I10: 1.099537 | J10: 2.8333333 | K10: 4.32 | L10: 1 | M10: 1 | N10: 0.91666667 | O10: 0.75 | P10: 0.75 | Q10: 0.083333333 | R10: Poisson | S10: Robusta | T10: Selecionada
A11: 7 | B11: Ranheim Fotball | C11: NOR - OBOS-ligaen | D11: 12 | E11: 5.3333333 | F11: 5.1666667 | G11: 5.25 | H11: 4.5625 | I11: 2.1 | J11: 2.4166667 | K11: 2.5 | L11: 1 | M11: 1 | N11: 0.91666667 | O11: 0.83333333 | P11: 0.91666667 | Q11: 0.083333333 | R11: Poisson | S11: Robusta | T11: Selecionada
A12: 8 | B12: Magic United | C12: AUS - NPL Queensland | D12: 12 | E12: 4.8333333 | F12: 4.6666667 | G12: 4.75 | H12: 4.5025 | I12: 1.2632979 | J12: 2 | K12: 3.76 | L12: 1 | M12: 1 | N12: 1 | O12: 0.66666667 | P12: 0.83333333 | Q12: 0.16666667 | R12: Poisson | S12: Robusta | T12: Selecionada
A13: 9 | B13: HPS | C13: FIN - Kakkonen A | D13: 12 | E13: 6 | F13: 3.3333333 | G13: 4.6666667 | H13: 4.4475 | I13: 1.2313105 | J13: 2.5833333 | K13: 3.79 | L13: 1 | M13: 1 | N13: 0.66666667 | O13: 0.58333333 | P13: 0.66666667 | Q13: 0.083333333 | R13: Poisson | S13: Robusta | T13: Selecionada
A14: 10 | B14: Jaro 2 | C14: FIN - Kakkonen C | D14: 12 | E14: 3.1666667 | F14: 5.6666667 | G14: 4.4166667 | H14: 4.3925 | I14: 1.0223765 | J14: 1.3333333 | K14: 4.32 | L14: 1 | M14: 1 | N14: 0.75 | O14: 0.58333333 | P14: 0.66666667 | Q14: 0.16666667 | R14: Poisson | S14: Robusta | T14: Selecionada
A15: 11 | B15: Sogndal Fotball | C15: NOR - OBOS-ligaen | D15: 12 | E15: 4.8333333 | F15: 4.3333333 | G15: 4.5833333 | H15: 4.0625 | I15: 1.8333333 | J15: 2.0833333 | K15: 2.5 | L15: 1 | M15: 1 | N15: 0.83333333 | O15: 0.83333333 | P15: 0.83333333 | Q15: 0.16666667 | R15: Poisson | S15: Robusta | T15: Selecionada
A16: 12 | B16: Olympic Kingsway | C16: AUS - NPL Western Australia | D16: 12 | E16: 4.2 | F16: 4.2857143 | G16: 4.25 | H16: 4.015 | I16: 1.2839879 | J16: 2.5833333 | K16: 3.31 | L16: 1 | M16: 1 | N16: 0.91666667 | O16: 0.5 | P16: 0.83333333 | Q16: 0.083333333 | R16: Poisson | S16: Robusta | T16: Selecionada
A17: 13 | B17: Kongsvinger IL | C17: NOR - OBOS-ligaen | D17: 12 | E17: 5.6 | F17: 3.7142857 | G17: 4.5 | H17: 4 | I17: 1.8 | J17: 2.75 | K17: 2.5 | L17: 1 | M17: 1 | N17: 0.83333333 | O17: 0.58333333 | P17: 0.83333333 | Q17: 0.083333333 | R17: Poisson | S17: Robusta | T17: Selecionada
... A44: 40 | B44: Portland Timbers | C44: USA - MLS-West | D44: 12 | E44: 3.8333333 | F44: 3.1666667 | G44: 3.5 | H44: 3.25 | I44: 1.4 | J44: 2 | K44: 2.5 | L44: 1 | M44: 1 | N44: 0.75 | O44: 0.41666667 | P44: 0.66666667 | Q44: 0.25 | R44: Poisson | S44: Robusta | T44: Selecionada
U46: País | V46: Equipes
U47: FIN | V47: =COUNTIF($C$5:$C$44,U47&" - *") -> 7
U48: AUS | V48: =COUNTIF($C$5:$C$44,U48&" - *") -> 8
U49: BOL | V49: =COUNTIF($C$5:$C$44,U49&" - *") -> 2
U50: BRA | V50: =COUNTIF($C$5:$C$44,U50&" - *") -> 0
U51: ISL | V51: =COUNTIF($C$5:$C$44,U51&" - *") -> 2
U52: Outros | V52: =COUNTA($C$5:$C$44)-SUM($V$47:$V$51) -> 21

Sheet Avaliação Partidas
A1: AVALIAÇÃO TÉCNICA — PARTIDAS SELECIONADAS
A2: Condição mandante em casa × visitante fora · Poisson · confirmação empírica · prioridade: acerto
A4: COMPARATIVO DAS CINCO PARTIDAS
A5: Prioridade | B5: Mandante | C5: Visitante | D5: Liga | E5: J casa | F5: J fora | G5: λ total | H5: Risco 0×0 | I5: Proteção O2,0 | J5: Green O2,0 | K5: 2+ emp. mín. | L5: 3+ emp. mín. | M5: Últimos 5 | N5: Linha elegível | O5: Nível O2,0
A6: =_xlfn.RANK.EQ(J6,$J$6:$J$10,0) -> 3 | B6: Brisbane Olympic FC | C6: Rochedale Rovers | D6: =IFERROR(_xlfn.XLOOKUP(B6,Equipes!$A$2:$A$1000,Equipes!$B$2:$B$1000,"Sem histórico"),"Sem histórico") -> AUS - NPL Queensland | E6: =COUNTIFS(tblDados[Mandante],B6,tblDados[Primeira_Ocorrencia],1) -> 7 | F6: =COUNTIFS(tblDados[Visitante],C6,tblDados[Primeira_Ocorrencia],1) -> 9 | G6: =_xlfn.LET(_xlpm.h,AVERAGE(_xlfn.XLOOKUP(B6,Equipes!$A$2:$A$1000,Equipes!$AA$2:$AA$1000),_xlfn.XLOOKUP(C6,Equipes!$A$2:$A$1000,Equipes!$AD$2:$AD$1000)),_xlpm.a,AVERAGE(_xlfn.XLOOKUP(C6,Equipes!$A$2:$A$1000,Equipes!$AC$2:$AC$1000),_xlfn.XLOOKUP(B6,Equipes!$A$2:$A$1000,Equipes!$AB$2:$AB$1000)),_xlpm.h+_xlpm.a) -> 3.7 | H6: =EXP(-G6) -> 0.024723526 | I6: =1-_xlfn.POISSON.DIST(1,G6,TRUE) -> 0.88379943 | J6: =1-_xlfn.POISSON.DIST(2,G6,TRUE) -> 0.71456689 | K6: {=MIN(IFERROR(SUMPRODUCT((tblDados[Mandante]=B6)*(tblDados[Primeira_Ocorrencia]=1)*((tblDados[GM_M]+tblDados[GS_M])>=2))/E6,0),IFERROR(SUMPRODUCT((tblDados[Visitante]=C6)*(tblDados[Primeira_Ocorrencia]=1)*((tblDados[GM_V]+tblDados[GS_V])>=2))/F6,0))} -> 0.85714286 | L6: {=MIN(IFERROR(SUMPRODUCT((tblDados[Mandante]=B6)*(tblDados[Primeira_Ocorrencia]=1)*((tblDados[GM_M]+tblDados[GS_M])>=3))/E6,0),IFERROR(SUMPRODUCT((tblDados[Visitante]=C6)*(tblDados[Primeira_Ocorrencia]=1)*((tblDados[GM_V]+tblDados[GS_V])>=3))/F6,0))} -> 0.71428571 | M6: {=_xlfn.LET(_xlpm.h,_xlfn._xlws.FILTER(tblDados[GM_M]+tblDados[GS_M],(tblDados[Mandante]=B6)*(tblDados[Primeira_Ocorrencia]=1),""),_xlpm.a,_xlfn._xlws.FILTER(tblDados[GM_V]+tblDados[GS_V],(tblDados[Visitante]=C6)*(tblDados[Primeira_Ocorrencia]=1),""),AVERAGE(IFERROR(AVERAGE(_xlfn.TAKE(_xlpm.h,-MIN(5,ROWS(_xlpm.h)))),0),IFERROR(AVERAGE(_xlfn.TAKE(_xlpm.a,-MIN(5,ROWS(_xlpm.a)))),0)))} -> 3.6 | N6: =IF(AND(I6>=80%,J6>=55%),"OVER 2,00","NÃO ELEGÍVEL") -> OVER 2,00 | O6: =IF(AND(J6>=80%,L6>=75%),"FORTE",IF(AND(J6>=65%,I6>=85%),"BOA","ELEGÍVEL COM CAUTELA")) -> BOA
A7: =_xlfn.RANK.EQ(J7,$J$6:$J$10,0) -> 1 | B7: Shandong Taishan | C7: Qingdao Hainiu | D7: =IFERROR(_xlfn.XLOOKUP(B7,Equipes!$A$2:$A$1000,Equipes!$B$2:$B$1000,"Sem histórico"),"Sem histórico") -> CHN - Super League | E7: =COUNTIFS(tblDados[Mandante],B7,tblDados[Primeira_Ocorrencia],1) -> 6 | F7: =COUNTIFS(tblDados[Visitante],C7,tblDados[Primeira_Ocorrencia],1) -> 7 | G7: =_xlfn.LET(_xlpm.h,AVERAGE(_xlfn.XLOOKUP(B7,Equipes!$A$2:$A$1000,Equipes!$AA$2:$AA$1000),_xlfn.XLOOKUP(C7,Equipes!$A$2:$A$1000,Equipes!$AD$2:$AD$1000)),_xlpm.a,AVERAGE(_xlfn.XLOOKUP(C7,Equipes!$A$2:$A$1000,Equipes!$AC$2:$AC$1000),_xlfn.XLOOKUP(B7,Equipes!$A$2:$A$1000,Equipes!$AB$2:$AB$1000)),_xlpm.h+_xlpm.a) -> 4.55 | H7: =EXP(-G7) -> 0.010567204 | I7: =1-_xlfn.POISSON.DIST(1,G7,TRUE) -> 0.94135202 | J7: =1-_xlfn.POISSON.DIST(2,G7,TRUE) -> 0.83196824 | K7: {=MIN(IFERROR(SUMPRODUCT((tblDados[Mandante]=B7)*(tblDados[Primeira_Ocorrencia]=1)*((tblDados[GM_M]+tblDados[GS_M])>=2))/E7,0),IFERROR(SUMPRODUCT((tblDados[Visitante]=C7)*(tblDados[Primeira_Ocorrencia]=1)*((tblDados[GM_V]+tblDados[GS_V])>=2))/F7,0))} -> 1 | L7: {=MIN(IFERROR(SUMPRODUCT((tblDados[Mandante]=B7)*(tblDados[Primeira_Ocorrencia]=1)*((tblDados[GM_M]+tblDados[GS_M])>=3))/E7,0),IFERROR(SUMPRODUCT((tblDados[Visitante]=C7)*(tblDados[Primeira_Ocorrencia]=1)*((tblDados[GM_V]+tblDados[GS_V])>=3))/F7,0))} -> 0.85714286 | M7: {=_xlfn.LET(_xlpm.h,_xlfn._xlws.FILTER(tblDados[GM_M]+tblDados[GS_M],(tblDados[Mandante]=B7)*(tblDados[Primeira_Ocorrencia]=1),""),_xlpm.a,_xlfn._xlws.FILTER(tblDados[GM_V]+tblDados[GS_V],(tblDados[Visitante]=C7)*(tblDados[Primeira_Ocorrencia]=1),""),AVERAGE(IFERROR(AVERAGE(_xlfn.TAKE(_xlpm.h,-MIN(5,ROWS(_xlpm.h)))),0),IFERROR(AVERAGE(_xlfn.TAKE(_xlpm.a,-MIN(5,ROWS(_xlpm.a)))),0)))} -> 4.4 | N7: =IF(AND(I7>=80%,J7>=55%),"OVER 2,00","NÃO ELEGÍVEL") -> OVER 2,00 | O7: =IF(AND(J7>=80%,L7>=75%),"FORTE",IF(AND(J7>=65%,I7>=85%),"BOA","ELEGÍVEL COM CAUTELA")) -> FORTE
A8: =_xlfn.RANK.EQ(J8,$J$6:$J$10,0) -> 4 | B8: Brisbane Roar NPL | C8: Gold Coast Knights | D8: =IFERROR(_xlfn.XLOOKUP(B8,Equipes!$A$2:$A$1000,Equipes!$B$2:$B$1000,"Sem histórico"),"Sem histórico") -> AUS - NPL Queensland | E8: =COUNTIFS(tblDados[Mandante],B8,tblDados[Primeira_Ocorrencia],1) -> 6 | F8: =COUNTIFS(tblDados[Visitante],C8,tblDados[Primeira_Ocorrencia],1) -> 4 | G8: =_xlfn.LET(_xlpm.h,AVERAGE(_xlfn.XLOOKUP(B8,Equipes!$A$2:$A$1000,Equipes!$AA$2:$AA$1000),_xlfn.XLOOKUP(C8,Equipes!$A$2:$A$1000,Equipes!$AD$2:$AD$1000)),_xlpm.a,AVERAGE(_xlfn.XLOOKUP(C8,Equipes!$A$2:$A$1000,Equipes!$AC$2:$AC$1000),_xlfn.XLOOKUP(B8,Equipes!$A$2:$A$1000,Equipes!$AB$2:$AB$1000)),_xlpm.h+_xlpm.a) -> 3.2 | H8: =EXP(-G8) -> 0.040762204 | I8: =1-_xlfn.POISSON.DIST(1,G8,TRUE) -> 0.82879874 | J8: =1-_xlfn.POISSON.DIST(2,G8,TRUE) -> 0.62009626 | K8: {=MIN(IFERROR(SUMPRODUCT((tblDados[Mandante]=B8)*(tblDados[Primeira_Ocorrencia]=1)*((tblDados[GM_M]+tblDados[GS_M])>=2))/E8,0),IFERROR(SUMPRODUCT((tblDados[Visitante]=C8)*(tblDados[Primeira_Ocorrencia]=1)*((tblDados[GM_V]+tblDados[GS_V])>=2))/F8,0))} -> 0.5 | L8: {=MIN(IFERROR(SUMPRODUCT((tblDados[Mandante]=B8)*(tblDados[Primeira_Ocorrencia]=1)*((tblDados[GM_M]+tblDados[GS_M])>=3))/E8,0),IFERROR(SUMPRODUCT((tblDados[Visitante]=C8)*(tblDados[Primeira_Ocorrencia]=1)*((tblDados[GM_V]+tblDados[GS_V])>=3))/F8,0))} -> 0.5 | M8: {=_xlfn.LET(_xlpm.h,_xlfn._xlws.FILTER(tblDados[GM_M]+tblDados[GS_M],(tblDados[Mandante]=B8)*(tblDados[Primeira_Ocorrencia]=1),""),_xlpm.a,_xlfn._xlws.FILTER(tblDados[GM_V]+tblDados[GS_V],(tblDados[Visitante]=C8)*(tblDados[Primeira_Ocorrencia]=1),""),AVERAGE(IFERROR(AVERAGE(_xlfn.TAKE(_xlpm.h,-MIN(5,ROWS(_xlpm.h)))),0),IFERROR(AVERAGE(_xlfn.TAKE(_xlpm.a,-MIN(5,ROWS(_xlpm.a)))),0)))} -> 3.25 | N8: =IF(AND(I8>=80%,J8>=55%),"OVER 2,00","NÃO ELEGÍVEL") -> OVER 2,00 | O8: =IF(AND(J8>=80%,L8>=75%),"FORTE",IF(AND(J8>=65%,I8>=85%),"BOA","ELEGÍVEL COM CAUTELA")) -> ELEGÍVEL COM CAUTELA
A9: =_xlfn.RANK.EQ(J9,$J$6:$J$10,0) -> 2 | B9: Wynnum Wolves | C9: Magic United | D9: =IFERROR(_xlfn.XLOOKUP(B9,Equipes!$A$2:$A$1000,Equipes!$B$2:$B$1000,"Sem histórico"),"Sem histórico") -> AUS - NPL Queensland | E9: =COUNTIFS(tblDados[Mandante],B9,tblDados[Primeira_Ocorrencia],1) -> 6 | F9: =COUNTIFS(tblDados[Visitante],C9,tblDados[Primeira_Ocorrencia],1) -> 9 | G9: =_xlfn.LET(_xlpm.h,AVERAGE(_xlfn.XLOOKUP(B9,Equipes!$A$2:$A$1000,Equipes!$AA$2:$AA$1000),_xlfn.XLOOKUP(C9,Equipes!$A$2:$A$1000,Equipes!$AD$2:$AD$1000)),_xlpm.a,AVERAGE(_xlfn.XLOOKUP(C9,Equipes!$A$2:$A$1000,Equipes!$AC$2:$AC$1000),_xlfn.XLOOKUP(B9,Equipes!$A$2:$A$1000,Equipes!$AB$2:$AB$1000)),_xlpm.h+_xlpm.a) -> 4.0833333 | H9: =EXP(-G9) -> 0.016851201 | I9: =1-_xlfn.POISSON.DIST(1,G9,TRUE) -> 0.91433973 | J9: =1-_xlfn.POISSON.DIST(2,G9,TRUE) -> 0.77385454 | K9: {=MIN(IFERROR(SUMPRODUCT((tblDados[Mandante]=B9)*(tblDados[Primeira_Ocorrencia]=1)*((tblDados[GM_M]+tblDados[GS_M])>=2))/E9,0),IFERROR(SUMPRODUCT((tblDados[Visitante]=C9)*(tblDados[Primeira_Ocorrencia]=1)*((tblDados[GM_V]+tblDados[GS_V])>=2))/F9,0))} -> 0.88888889 | L9: {=MIN(IFERROR(SUMPRODUCT((tblDados[Mandante]=B9)*(tblDados[Primeira_Ocorrencia]=1)*((tblDados[GM_M]+tblDados[GS_M])>=3))/E9,0),IFERROR(SUMPRODUCT((tblDados[Visitante]=C9)*(tblDados[Primeira_Ocorrencia]=1)*((tblDados[GM_V]+tblDados[GS_V])>=3))/F9,0))} -> 0.66666667 | M9: {=_xlfn.LET(_xlpm.h,_xlfn._xlws.FILTER(tblDados[GM_M]+tblDados[GS_M],(tblDados[Mandante]=B9)*(tblDados[Primeira_Ocorrencia]=1),""),_xlpm.a,_xlfn._xlws.FILTER(tblDados[GM_V]+tblDados[GS_V],(tblDados[Visitante]=C9)*(tblDados[Primeira_Ocorrencia]=1),""),AVERAGE(IFERROR(AVERAGE(_xlfn.TAKE(_xlpm.h,-MIN(5,ROWS(_xlpm.h)))),0),IFERROR(AVERAGE(_xlfn.TAKE(_xlpm.a,-MIN(5,ROWS(_xlpm.a)))),0)))} -> 4.2 | N9: =IF(AND(I9>=80%,J9>=55%),"OVER 2,00","NÃO ELEGÍVEL") -> OVER 2,00 | O9: =IF(AND(J9>=80%,L9>=75%),"FORTE",IF(AND(J9>=65%,I9>=85%),"BOA","ELEGÍVEL COM CAUTELA")) -> BOA
A10: =_xlfn.RANK.EQ(J10,$J$6:$J$10,0) -> 5 | B10: Gold Coast Utd | C10: Eastern Suburbs | D10: =IFERROR(_xlfn.XLOOKUP(B10,Equipes!$A$2:$A$1000,Equipes!$B$2:$B$1000,"Sem histórico"),"Sem histórico") -> AUS - NPL Queensland | E10: =COUNTIFS(tblDados[Mandante],B10,tblDados[Primeira_Ocorrencia],1) -> 10 | F10: =COUNTIFS(tblDados[Visitante],C10,tblDados[Primeira_Ocorrencia],1) -> 6 | G10: =_xlfn.LET(_xlpm.h,AVERAGE(_xlfn.XLOOKUP(B10,Equipes!$A$2:$A$1000,Equipes!$AA$2:$AA$1000),_xlfn.XLOOKUP(C10,Equipes!$A$2:$A$1000,Equipes!$AD$2:$AD$1000)),_xlpm.a,AVERAGE(_xlfn.XLOOKUP(C10,Equipes!$A$2:$A$1000,Equipes!$AC$2:$AC$1000),_xlfn.XLOOKUP(B10,Equipes!$A$2:$A$1000,Equipes!$AB$2:$AB$1000)),_xlpm.h+_xlpm.a) -> 2.775 | H10: =EXP(-G10) -> 0.062349477 | I10: =1-_xlfn.POISSON.DIST(1,G10,TRUE) -> 0.76463073 | J10: =1-_xlfn.POISSON.DIST(2,G10,TRUE) -> 0.52456576 | K10: {=MIN(IFERROR(SUMPRODUCT((tblDados[Mandante]=B10)*(tblDados[Primeira_Ocorrencia]=1)*((tblDados[GM_M]+tblDados[GS_M])>=2))/E10,0),IFERROR(SUMPRODUCT((tblDados[Visitante]=C10)*(tblDados[Primeira_Ocorrencia]=1)*((tblDados[GM_V]+tblDados[GS_V])>=2))/F10,0))} -> 0.7 | L10: {=MIN(IFERROR(SUMPRODUCT((tblDados[Mandante]=B10)*(tblDados[Primeira_Ocorrencia]=1)*((tblDados[GM_M]+tblDados[GS_M])>=3))/E10,0),IFERROR(SUMPRODUCT((tblDados[Visitante]=C10)*(tblDados[Primeira_Ocorrencia]=1)*((tblDados[GM_V]+tblDados[GS_V])>=3))/F10,0))} -> 0.6 | M10: {=_xlfn.LET(_xlpm.h,_xlfn._xlws.FILTER(tblDados[GM_M]+tblDados[GS_M],(tblDados[Mandante]=B10)*(tblDados[Primeira_Ocorrencia]=1),""),_xlpm.a,_xlfn._xlws.FILTER(tblDados[GM_V]+tblDados[GS_V],(tblDados[Visitante]=C10)*(tblDados[Primeira_Ocorrencia]=1),""),AVERAGE(IFERROR(AVERAGE(_xlfn.TAKE(_xlpm.h,-MIN(5,ROWS(_xlpm.h)))),0),IFERROR(AVERAGE(_xlfn.TAKE(_xlpm.a,-MIN(5,ROWS(_xlpm.a)))),0)))} -> 2.9 | N10: OVER 1,25 | O10: 1ª LINHA OU NÃO APOSTAR
A12: LEITURA OPERACIONAL
A13: Quatro confrontos permanecem elegíveis ao Over 2,00: Brisbane Olympic FC × Rochedale Rovers, Shandong Taishan × Qingdao Hainiu, Brisbane Roar NPL × Gold Coast Knights e Wynnum Wolves × Magic United. Shandong Taishan × Qingdao Hainiu continua como a opção mais forte, com 83,2% de GREEN e 94,1% de GREEN ou PUSH. Gold Coast Utd × Eastern Suburbs é uma exceção operacional: a primeira e única linha aceitável é Over 1,25. Se Over 1,25 não estiver disponível ou a odd não justificar a entrada, NÃO APOSTAR. Não substituir automaticamente por Over 1,50 ou Over 2,00. Regra final: informar as linhas e odds disponíveis antes da montagem do bilhete.

Sheet Modelo 01
A1: MODELO 01 — SIMULADOR CONSERVADOR DE CONFRONTO
A2: V1 · Poisson, binomial negativa e consenso conservador de linhas asiáticas
A4: SELEÇÃO DA PARTIDA
A5: Mandante | B5: Degerfors IF | D5: País - Liga | E5: =IF($B$5="","",IFERROR(INDEX(Equipes!$B$2:$B$1000,MATCH($B$5,Equipes!$A$2:$A$1000,0)),"Sem histórico")) -> SWE - Allsvenskan | H5: =IF($B$5="","",IF(COUNTIF(Equipes!$A$2:$A$1000,TRIM($B$5))>0,"✓ Histórico disponível",IF(COUNTIF(CadastroEquipes,TRIM($B$5))>0,"⚠ Cadastrada, sem histórico","⚠ Nome não cadastrado"))) -> ✓ Histórico disponível
A6: Visitante | B6: IFK Göteborg | D6: País - Liga | E6: =IF($B$6="","",IFERROR(INDEX(Equipes!$B$2:$B$1000,MATCH($B$6,Equipes!$A$2:$A$1000,0)),"Sem histórico")) -> SWE - Allsvenskan | H6: =IF($B$6="","",IF(COUNTIF(Equipes!$A$2:$A$1000,TRIM($B$6))>0,"✓ Histórico disponível",IF(COUNTIF(CadastroEquipes,TRIM($B$6))>0,"⚠ Cadastrada, sem histórico","⚠ Nome não cadastrado"))) -> ✓ Histórico disponível
A8: PARÂMETROS DO MODELO | F8: LEITURA RÁPIDA — CONSENSO DE ENTRADA
A9: Métrica | B9: Mandante | C9: Visitante | D9: Partida | F9: Sinal | G9: Orientação | H9: Nível
A10: Gols esperados (λ) | B10: =IF(OR($B$5="",$B$6=""),"",_xlfn.LET(_xlpm.x,IFERROR(INDEX(Equipes!$AA$2:$AA$1000,MATCH($B$5,Equipes!$A$2:$A$1000,0)),""),_xlpm.y,IFERROR(INDEX(Equipes!$AD$2:$AD$1000,MATCH($B$6,Equipes!$A$2:$A$1000,0)),""),IF(OR(_xlpm.x="",_xlpm.y=""),"",AVERAGE(_xlpm.x,_xlpm.y)))) -> 2.4 | C10: =IF(OR($B$5="",$B$6=""),"",_xlfn.LET(_xlpm.x,IFERROR(INDEX(Equipes!$AC$2:$AC$1000,MATCH($B$6,Equipes!$A$2:$A$1000,0)),""),_xlpm.y,IFERROR(INDEX(Equipes!$AB$2:$AB$1000,MATCH($B$5,Equipes!$A$2:$A$1000,0)),""),IF(OR(_xlpm.x="",_xlpm.y=""),"",AVERAGE(_xlpm.x,_xlpm.y)))) -> 1.8 | D10: =IF(OR(B10="",C10=""),"",B10+C10) -> 4.2 | F10: Probabilidades | G10: =IF($H$10=0,"Sem linha aprovada","Até Over "&FIXED($H$10,2,FALSE)) -> Até Over 1,75 | H10: {=IF($D$10="",0,_xlfn.LET(_xlpm.ls,{0.5;0.75;1;1.25;1.5;1.75;2;2.25;2.5;2.75;3},_xlpm.th,{0.95;0.94;0.925;0.9125;0.9;0.88;0.86;0.84;0.82;0.8025;0.785},_xlpm.sc,_xlfn.MAP(_xlpm.ls,_xlfn.LAMBDA(_xlpm.l,_xlfn.LET(_xlpm.n,INT(_xlpm.l),_xlpm.f,ROUND(MOD(_xlpm.l,1),2),_xlpm.si,_xlfn.LAMBDA(_xlpm.k,1-_xlfn.POISSON.DIST(_xlpm.k,$D$10,TRUE)+0.5*_xlfn.POISSON.DIST(_xlpm.k,$D$10,FALSE)),_xlpm.sh,_xlfn.LAMBDA(_xlpm.k,1-_xlfn.POISSON.DIST(_xlpm.k,$D$10,TRUE)),IF(_xlpm.f=0.5,_xlpm.sh(_xlpm.n),IF(_xlpm.f=0,_xlpm.si(_xlpm.n),IF(_xlpm.f=0.25,AVERAGE(_xlpm.si(_xlpm.n),_xlpm.sh(_xlpm.n)),AVERAGE(_xlpm.sh(_xlpm.n),_xlpm.si(_xlpm.n+1)))))))),IFERROR(MAX(_xlfn._xlws.FILTER(_xlpm.ls,_xlpm.sc>=_xlpm.th)),0)))} -> 1.75
A11: Jogos na condição | B11: =IFERROR(INDEX(Equipes!$E$2:$E$1000,MATCH($B$5,Equipes!$A$2:$A$1000,0)),"") -> 5 | C11: =IFERROR(INDEX(Equipes!$F$2:$F$1000,MATCH($B$6,Equipes!$A$2:$A$1000,0)),"") -> 5 | D11: =IF(OR(B11="",C11=""),"",MIN(B11,C11)) -> 5 | F11: Potencial de gols | G11: =IF($D$10="","Aguardando histórico",IF($H$11=0,"Baixo potencial","Suporta Over "&FIXED($H$11,2,FALSE))) -> Suporta Over 2,50 | H11: =IF($D$10="",0,IF($D$10<1.5,0,IF($D$10<2.5,0.5,IF($D$10<3.5,1.5,IF($D$10<4.5,2.5,3))))) -> 2.5
A12: Índice de força | B12: =IFERROR(INDEX(Equipes!$C$2:$C$1000,MATCH($B$5,Equipes!$A$2:$A$1000,0)),"") -> 2.6 | C12: =IFERROR(INDEX(Equipes!$D$2:$D$1000,MATCH($B$6,Equipes!$A$2:$A$1000,0)),"") -> 5.8 | D12: =IF(OR(B12="",C12=""),"",AVERAGE(B12,C12)) -> 4.2 | F12: Placares Top 8 | G12: =IF($H$12=0,"Sem concentração Over","Top 8 suporta Over "&FIXED($H$12,2,FALSE)) -> Top 8 suporta Over 3,00 | H12: {=IF($D$10="",0,_xlfn.LET(_xlpm.t,VALUE(_xlfn.TEXTBEFORE($G$19:$G$26," x "))+VALUE(_xlfn.TEXTAFTER($G$19:$G$26," x ")),MAX(0,MIN(3,FLOOR(MEDIAN(_xlpm.t)-0.5,0.25)))))} -> 3
A13: Modelo da equipe | B13: =IFERROR(INDEX(Equipes!$R$2:$R$1000,MATCH($B$5,Equipes!$A$2:$A$1000,0)),"") -> Poisson | C13: =IFERROR(INDEX(Equipes!$R$2:$R$1000,MATCH($B$6,Equipes!$A$2:$A$1000,0)),"") -> Poisson | D13: =IF(OR(B13="",C13=""),"",IF(OR(B13="Amostra Insuficiente",C13="Amostra Insuficiente"),"Poisson preliminar",IF(B13=C13,B13,"Poisson base / dispersão"))) -> Poisson | F13: Linha técnica | G13: =IF($H$13=0,"SEM CONSENSO","OVER "&FIXED($H$13,2,FALSE)) -> OVER 2,50 | H13: =MEDIAN($H$10:$H$12) -> 2.5
A14: Qualidade da amostra | B14: =IF(B11="","",IF(B11>=10,"Robusta",IF(B11>=5,"Em formação","Preliminar"))) -> Em formação | C14: =IF(C11="","",IF(C11>=10,"Robusta",IF(C11>=5,"Em formação","Preliminar"))) -> Em formação | D14: =IF(OR(B11="",C11=""),"",IF(MIN(B11,C11)>=10,"Robusta",IF(MIN(B11,C11)>=5,"Em formação","Preliminar"))) -> Em formação | F14: Fase por liga | G14: =IF($H$14>=15,"FASE 2 — OTIMIZAR LUCRO","FASE 1 — PRESERVAR CAPITAL") -> FASE 1 — PRESERVAR CAPITAL | H14: =_xlfn.LET(_xlpm.l,IF($E$5=$E$6,$E$5,IF(AND(ISNUMBER(SEARCH("Kakkonen",$E$5)),ISNUMBER(SEARCH("Kakkonen",$E$6))),"FIN - Kakkonen",$E$5&" / "&$E$6)),COUNTIF(tblCalibracao[Liga],_xlpm.l)) -> 1
A15: ρ Dixon–Coles | B15: 0 | D15: 0 = Poisson puro; calibrar por liga futuramente | F15: Orientação final | G15: =IF($H$13=0,"NÃO APOSTAR",IF(1-$H$40>10%,"NÃO APOSTAR — 0x0 "&TEXT(1-$H$40,"0.0%"),"ANALISAR OVER "&FIXED(MIN(3,$H$13+IF(AND($D$10>=2.5,$D$10<3.5),IF(1-$H$40<7.5%,0.5,0.25),0)),2,FALSE))) -> ANALISAR OVER 2,50 | H15: =IF($H$13=0,"—",IF(1-$H$40>10%,"IMPEDITIVO",IF(AND($D$10>=2.5,$D$10<3.5),IF(1-$H$40<7.5%,"Avançar +0,50","Avançar +0,25"),IF($D$10>=3.5,"Sem avanço automático","Máxima proteção")))) -> Sem avanço automático
A17: PROBABILIDADES — LINHAS ASIÁTICAS OVER | F17: PLACARES MAIS PROVÁVEIS
A18: Linha | B18: Prob. ajustada | C18: Classificação | D18: Proteção / liquidação | F18: Posição | G18: Placar | H18: Probabilidade
A19: 0.5 | B19: =IF($D$10="","",_xlfn.LET(_xlpm.l,$A19,_xlpm.n,INT(_xlpm.l),_xlpm.f,ROUND(MOD(_xlpm.l,1),2),_xlpm.si,1-_xlfn.POISSON.DIST(_xlpm.n,$D$10,TRUE)+0.5*_xlfn.POISSON.DIST(_xlpm.n,$D$10,FALSE),_xlpm.sh,1-_xlfn.POISSON.DIST(_xlpm.n,$D$10,TRUE),IF(_xlpm.f=0.5,_xlpm.sh,IF(_xlpm.f=0,_xlpm.si,IF(_xlpm.f=0.25,AVERAGE(_xlpm.si,_xlpm.sh),AVERAGE(_xlpm.sh,1-_xlfn.POISSON.DIST(_xlpm.n+1,$D$10,TRUE)+0.5*_xlfn.POISSON.DIST(_xlpm.n+1,$D$10,FALSE))))))) -> 0.98500442 | C19: {=IF($B19="","",_xlfn.LET(_xlpm.l,$A19,_xlpm.lim,_xlfn.XLOOKUP(_xlpm.l,{0.5,0.75,1,1.25,1.5,1.75,2,2.25,2.5,2.75,3},{0.95,0.94,0.925,0.9125,0.9,0.88,0.86,0.84,0.82,0.8025,0.785}),IF($B19>=_xlpm.lim,"APROVADA",IF($B19>=_xlpm.lim-5%,"PRÓXIMA","ABAIXO"))))} -> APROVADA | D19: Sem proteção | F19: {=IF(OR($B$10="",$C$10=""),"",_xlfn.LET(_xlpm.n,9,_xlpm.i,_xlfn.SEQUENCE(_xlpm.n*_xlpm.n,1,0),_xlpm.h,INT(_xlpm.i/_xlpm.n),_xlpm.a,MOD(_xlpm.i,_xlpm.n),_xlpm.p,_xlfn.POISSON.DIST(_xlpm.h,$B$10,FALSE)*_xlfn.POISSON.DIST(_xlpm.a,$C$10,FALSE)*IF((_xlpm.h=0)*(_xlpm.a=0),1-$B$10*$C$10*$B$15,IF((_xlpm.h=0)*(_xlpm.a=1),1+$B$10*$B$15,IF((_xlpm.h=1)*(_xlpm.a=0),1+$C$10*$B$15,IF((_xlpm.h=1)*(_xlpm.a=1),1-$B$15,1)))),_xlpm.s,_xlfn.SORTBY(_xlfn.HSTACK(_xlpm.h&" x "&_xlpm.a,_xlpm.p),_xlpm.p,-1),_xlfn.HSTACK(_xlfn.SEQUENCE(8),_xlfn.TAKE(_xlpm.s,8))))} -> 1 | G19: 2 x 1 | H19: 0.07773707
A20: 0.75 | B20: =IF($D$10="","",_xlfn.LET(_xlpm.l,$A20,_xlpm.n,INT(_xlpm.l),_xlpm.f,ROUND(MOD(_xlpm.l,1),2),_xlpm.si,1-_xlfn.POISSON.DIST(_xlpm.n,$D$10,TRUE)+0.5*_xlfn.POISSON.DIST(_xlpm.n,$D$10,FALSE),_xlpm.sh,1-_xlfn.POISSON.DIST(_xlpm.n,$D$10,TRUE),IF(_xlpm.f=0.5,_xlpm.sh,IF(_xlpm.f=0,_xlpm.si,IF(_xlpm.f=0.25,AVERAGE(_xlpm.si,_xlpm.sh),AVERAGE(_xlpm.sh,1-_xlfn.POISSON.DIST(_xlpm.n+1,$D$10,TRUE)+0.5*_xlfn.POISSON.DIST(_xlpm.n+1,$D$10,FALSE))))))) -> 0.96925907 | C20: {=IF($B20="","",_xlfn.LET(_xlpm.l,$A20,_xlpm.lim,_xlfn.XLOOKUP(_xlpm.l,{0.5,0.75,1,1.25,1.5,1.75,2,2.25,2.5,2.75,3},{0.95,0.94,0.925,0.9125,0.9,0.88,0.86,0.84,0.82,0.8025,0.785}),IF($B20>=_xlpm.lim,"APROVADA",IF($B20>=_xlpm.lim-5%,"PRÓXIMA","ABAIXO"))))} -> APROVADA | D20: ½ GREEN com 1 gol | F20: 2 | G20: 2 x 2 | H20: 0.069963363
A21: 1 | B21: =IF($D$10="","",_xlfn.LET(_xlpm.l,$A21,_xlpm.n,INT(_xlpm.l),_xlpm.f,ROUND(MOD(_xlpm.l,1),2),_xlpm.si,1-_xlfn.POISSON.DIST(_xlpm.n,$D$10,TRUE)+0.5*_xlfn.POISSON.DIST(_xlpm.n,$D$10,FALSE),_xlpm.sh,1-_xlfn.POISSON.DIST(_xlpm.n,$D$10,TRUE),IF(_xlpm.f=0.5,_xlpm.sh,IF(_xlpm.f=0,_xlpm.si,IF(_xlpm.f=0.25,AVERAGE(_xlpm.si,_xlpm.sh),AVERAGE(_xlpm.sh,1-_xlfn.POISSON.DIST(_xlpm.n+1,$D$10,TRUE)+0.5*_xlfn.POISSON.DIST(_xlpm.n+1,$D$10,FALSE))))))) -> 0.95351371 | C21: {=IF($B21="","",_xlfn.LET(_xlpm.l,$A21,_xlpm.lim,_xlfn.XLOOKUP(_xlpm.l,{0.5,0.75,1,1.25,1.5,1.75,2,2.25,2.5,2.75,3},{0.95,0.94,0.925,0.9125,0.9,0.88,0.86,0.84,0.82,0.8025,0.785}),IF($B21>=_xlpm.lim,"APROVADA",IF($B21>=_xlpm.lim-5%,"PRÓXIMA","ABAIXO"))))} -> APROVADA | D21: PUSH com 1 gol | F21: 3 | G21: 1 x 1 | H21: 0.064780892
A22: 1.25 | B22: =IF($D$10="","",_xlfn.LET(_xlpm.l,$A22,_xlpm.n,INT(_xlpm.l),_xlpm.f,ROUND(MOD(_xlpm.l,1),2),_xlpm.si,1-_xlfn.POISSON.DIST(_xlpm.n,$D$10,TRUE)+0.5*_xlfn.POISSON.DIST(_xlpm.n,$D$10,FALSE),_xlpm.sh,1-_xlfn.POISSON.DIST(_xlpm.n,$D$10,TRUE),IF(_xlpm.f=0.5,_xlpm.sh,IF(_xlpm.f=0,_xlpm.si,IF(_xlpm.f=0.25,AVERAGE(_xlpm.si,_xlpm.sh),AVERAGE(_xlpm.sh,1-_xlfn.POISSON.DIST(_xlpm.n+1,$D$10,TRUE)+0.5*_xlfn.POISSON.DIST(_xlpm.n+1,$D$10,FALSE))))))) -> 0.93776836 | C22: {=IF($B22="","",_xlfn.LET(_xlpm.l,$A22,_xlpm.lim,_xlfn.XLOOKUP(_xlpm.l,{0.5,0.75,1,1.25,1.5,1.75,2,2.25,2.5,2.75,3},{0.95,0.94,0.925,0.9125,0.9,0.88,0.86,0.84,0.82,0.8025,0.785}),IF($B22>=_xlpm.lim,"APROVADA",IF($B22>=_xlpm.lim-5%,"PRÓXIMA","ABAIXO"))))} -> APROVADA | D22: ½ RED com 1 gol | F22: 4 | G22: 3 x 1 | H22: 0.062189656
A23: 1.5 | B23: =IF($D$10="","",_xlfn.LET(_xlpm.l,$A23,_xlpm.n,INT(_xlpm.l),_xlpm.f,ROUND(MOD(_xlpm.l,1),2),_xlpm.si,1-_xlfn.POISSON.DIST(_xlpm.n,$D$10,TRUE)+0.5*_xlfn.POISSON.DIST(_xlpm.n,$D$10,FALSE),_xlpm.sh,1-_xlfn.POISSON.DIST(_xlpm.n,$D$10,TRUE),IF(_xlpm.f=0.5,_xlpm.sh,IF(_xlpm.f=0,_xlpm.si,IF(_xlpm.f=0.25,AVERAGE(_xlpm.si,_xlpm.sh),AVERAGE(_xlpm.sh,1-_xlfn.POISSON.DIST(_xlpm.n+1,$D$10,TRUE)+0.5*_xlfn.POISSON.DIST(_xlpm.n+1,$D$10,FALSE))))))) -> 0.922023 | C23: {=IF($B23="","",_xlfn.LET(_xlpm.l,$A23,_xlpm.lim,_xlfn.XLOOKUP(_xlpm.l,{0.5,0.75,1,1.25,1.5,1.75,2,2.25,2.5,2.75,3},{0.95,0.94,0.925,0.9125,0.9,0.88,0.86,0.84,0.82,0.8025,0.785}),IF($B23>=_xlpm.lim,"APROVADA",IF($B23>=_xlpm.lim-5%,"PRÓXIMA","ABAIXO"))))} -> APROVADA | D23: Sem proteção | F23: 5 | G23: 1 x 2 | H23: 0.058302803
A24: 1.75 | B24: =IF($D$10="","",_xlfn.LET(_xlpm.l,$A24,_xlpm.n,INT(_xlpm.l),_xlpm.f,ROUND(MOD(_xlpm.l,1),2),_xlpm.si,1-_xlfn.POISSON.DIST(_xlpm.n,$D$10,TRUE)+0.5*_xlfn.POISSON.DIST(_xlpm.n,$D$10,FALSE),_xlpm.sh,1-_xlfn.POISSON.DIST(_xlpm.n,$D$10,TRUE),IF(_xlpm.f=0.5,_xlpm.sh,IF(_xlpm.f=0,_xlpm.si,IF(_xlpm.f=0.25,AVERAGE(_xlpm.si,_xlpm.sh),AVERAGE(_xlpm.sh,1-_xlfn.POISSON.DIST(_xlpm.n+1,$D$10,TRUE)+0.5*_xlfn.POISSON.DIST(_xlpm.n+1,$D$10,FALSE))))))) -> 0.88895775 | C24: {=IF($B24="","",_xlfn.LET(_xlpm.l,$A24,_xlpm.lim,_xlfn.XLOOKUP(_xlpm.l,{0.5,0.75,1,1.25,1.5,1.75,2,2.25,2.5,2.75,3},{0.95,0.94,0.925,0.9125,0.9,0.88,0.86,0.84,0.82,0.8025,0.785}),IF($B24>=_xlpm.lim,"APROVADA",IF($B24>=_xlpm.lim-5%,"PRÓXIMA","ABAIXO"))))} -> APROVADA | D24: ½ GREEN com 2 gols | F24: 6 | G24: 3 x 2 | H24: 0.055970691
A25: 2 | B25: =IF($D$10="","",_xlfn.LET(_xlpm.l,$A25,_xlpm.n,INT(_xlpm.l),_xlpm.f,ROUND(MOD(_xlpm.l,1),2),_xlpm.si,1-_xlfn.POISSON.DIST(_xlpm.n,$D$10,TRUE)+0.5*_xlfn.POISSON.DIST(_xlpm.n,$D$10,FALSE),_xlpm.sh,1-_xlfn.POISSON.DIST(_xlpm.n,$D$10,TRUE),IF(_xlpm.f=0.5,_xlpm.sh,IF(_xlpm.f=0,_xlpm.si,IF(_xlpm.f=0.25,AVERAGE(_xlpm.si,_xlpm.sh),AVERAGE(_xlpm.sh,1-_xlfn.POISSON.DIST(_xlpm.n+1,$D$10,TRUE)+0.5*_xlfn.POISSON.DIST(_xlpm.n+1,$D$10,FALSE))))))) -> 0.85589251 | C25: {=IF($B25="","",_xlfn.LET(_xlpm.l,$A25,_xlpm.lim,_xlfn.XLOOKUP(_xlpm.l,{0.5,0.75,1,1.25,1.5,1.75,2,2.25,2.5,2.75,3},{0.95,0.94,0.925,0.9125,0.9,0.88,0.86,0.84,0.82,0.8025,0.785}),IF($B25>=_xlpm.lim,"APROVADA",IF($B25>=_xlpm.lim-5%,"PRÓXIMA","ABAIXO"))))} -> PRÓXIMA | D25: PUSH com 2 gols | F25: 7 | G25: 2 x 0 | H25: 0.043187261
A26: 2.25 | B26: =IF($D$10="","",_xlfn.LET(_xlpm.l,$A26,_xlpm.n,INT(_xlpm.l),_xlpm.f,ROUND(MOD(_xlpm.l,1),2),_xlpm.si,1-_xlfn.POISSON.DIST(_xlpm.n,$D$10,TRUE)+0.5*_xlfn.POISSON.DIST(_xlpm.n,$D$10,FALSE),_xlpm.sh,1-_xlfn.POISSON.DIST(_xlpm.n,$D$10,TRUE),IF(_xlpm.f=0.5,_xlpm.sh,IF(_xlpm.f=0,_xlpm.si,IF(_xlpm.f=0.25,AVERAGE(_xlpm.si,_xlpm.sh),AVERAGE(_xlpm.sh,1-_xlfn.POISSON.DIST(_xlpm.n+1,$D$10,TRUE)+0.5*_xlfn.POISSON.DIST(_xlpm.n+1,$D$10,FALSE))))))) -> 0.82282726 | C26: {=IF($B26="","",_xlfn.LET(_xlpm.l,$A26,_xlpm.lim,_xlfn.XLOOKUP(_xlpm.l,{0.5,0.75,1,1.25,1.5,1.75,2,2.25,2.5,2.75,3},{0.95,0.94,0.925,0.9125,0.9,0.88,0.86,0.84,0.82,0.8025,0.785}),IF($B26>=_xlpm.lim,"APROVADA",IF($B26>=_xlpm.lim-5%,"PRÓXIMA","ABAIXO"))))} -> PRÓXIMA | D26: ½ RED com 2 gols | F26: 8 | G26: 2 x 3 | H26: 0.041978018
A27: 2.5 | B27: =IF($D$10="","",_xlfn.LET(_xlpm.l,$A27,_xlpm.n,INT(_xlpm.l),_xlpm.f,ROUND(MOD(_xlpm.l,1),2),_xlpm.si,1-_xlfn.POISSON.DIST(_xlpm.n,$D$10,TRUE)+0.5*_xlfn.POISSON.DIST(_xlpm.n,$D$10,FALSE),_xlpm.sh,1-_xlfn.POISSON.DIST(_xlpm.n,$D$10,TRUE),IF(_xlpm.f=0.5,_xlpm.sh,IF(_xlpm.f=0,_xlpm.si,IF(_xlpm.f=0.25,AVERAGE(_xlpm.si,_xlpm.sh),AVERAGE(_xlpm.sh,1-_xlfn.POISSON.DIST(_xlpm.n+1,$D$10,TRUE)+0.5*_xlfn.POISSON.DIST(_xlpm.n+1,$D$10,FALSE))))))) -> 0.78976201 | C27: {=IF($B27="","",_xlfn.LET(_xlpm.l,$A27,_xlpm.lim,_xlfn.XLOOKUP(_xlpm.l,{0.5,0.75,1,1.25,1.5,1.75,2,2.25,2.5,2.75,3},{0.95,0.94,0.925,0.9125,0.9,0.88,0.86,0.84,0.82,0.8025,0.785}),IF($B27>=_xlpm.lim,"APROVADA",IF($B27>=_xlpm.lim-5%,"PRÓXIMA","ABAIXO"))))} -> PRÓXIMA | D27: Sem proteção
A28: 2.75 | B28: =IF($D$10="","",_xlfn.LET(_xlpm.l,$A28,_xlpm.n,INT(_xlpm.l),_xlpm.f,ROUND(MOD(_xlpm.l,1),2),_xlpm.si,1-_xlfn.POISSON.DIST(_xlpm.n,$D$10,TRUE)+0.5*_xlfn.POISSON.DIST(_xlpm.n,$D$10,FALSE),_xlpm.sh,1-_xlfn.POISSON.DIST(_xlpm.n,$D$10,TRUE),IF(_xlpm.f=0.5,_xlpm.sh,IF(_xlpm.f=0,_xlpm.si,IF(_xlpm.f=0.25,AVERAGE(_xlpm.si,_xlpm.sh),AVERAGE(_xlpm.sh,1-_xlfn.POISSON.DIST(_xlpm.n+1,$D$10,TRUE)+0.5*_xlfn.POISSON.DIST(_xlpm.n+1,$D$10,FALSE))))))) -> 0.74347067 | C28: {=IF($B28="","",_xlfn.LET(_xlpm.l,$A28,_xlpm.lim,_xlfn.XLOOKUP(_xlpm.l,{0.5,0.75,1,1.25,1.5,1.75,2,2.25,2.5,2.75,3},{0.95,0.94,0.925,0.9125,0.9,0.88,0.86,0.84,0.82,0.8025,0.785}),IF($B28>=_xlpm.lim,"APROVADA",IF($B28>=_xlpm.lim-5%,"PRÓXIMA","ABAIXO"))))} -> ABAIXO | D28: ½ GREEN com 3 gols
A29: 3 | B29: =IF($D$10="","",_xlfn.LET(_xlpm.l,$A29,_xlpm.n,INT(_xlpm.l),_xlpm.f,ROUND(MOD(_xlpm.l,1),2),_xlpm.si,1-_xlfn.POISSON.DIST(_xlpm.n,$D$10,TRUE)+0.5*_xlfn.POISSON.DIST(_xlpm.n,$D$10,FALSE),_xlpm.sh,1-_xlfn.POISSON.DIST(_xlpm.n,$D$10,TRUE),IF(_xlpm.f=0.5,_xlpm.sh,IF(_xlpm.f=0,_xlpm.si,IF(_xlpm.f=0.25,AVERAGE(_xlpm.si,_xlpm.sh),AVERAGE(_xlpm.sh,1-_xlfn.POISSON.DIST(_xlpm.n+1,$D$10,TRUE)+0.5*_xlfn.POISSON.DIST(_xlpm.n+1,$D$10,FALSE))))))) -> 0.69717932 | C29: {=IF($B29="","",_xlfn.LET(_xlpm.l,$A29,_xlpm.lim,_xlfn.XLOOKUP(_xlpm.l,{0.5,0.75,1,1.25,1.5,1.75,2,2.25,2.5,2.75,3},{0.95,0.94,0.925,0.9125,0.9,0.88,0.86,0.84,0.82,0.8025,0.785}),IF($B29>=_xlpm.lim,"APROVADA",IF($B29>=_xlpm.lim-5%,"PRÓXIMA","ABAIXO"))))} -> ABAIXO | D29: PUSH com 3 gols
A30: Probabilidade ajustada pondera GREEN=100%, meio GREEN=75%, PUSH=50%, meio RED=25% e RED=0%.
A33: COMPARAÇÃO DE LINHAS — POISSON × BINOMIAL NEGATIVA
A34: Atualiza automaticamente para qualquer confronto selecionado em B5 e B6
A36: λ total | B36: =$D$10 -> 4.2 | C36: Variância usada | D36: =IF(OR(B36="",NOT(ISNUMBER(I36)),NOT(ISNUMBER(J36))),"",MAX(B36*1.05,AVERAGE(I36,J36))) -> 4.41 | E36: Modelo alternativo | F36: Binomial Negativa | G36: Diagnóstico | H36: =IF(D36="","",IF(D36>B36*1.15,"SUPERDISPERSÃO","PRÓXIMA DO POISSON")) -> PRÓXIMA DO POISSON | I36: {=_xlfn.LET(_xlpm.n,$B$5,_xlpm.c,SUMPRODUCT((TRIM(tblDados[Mandante])=_xlpm.n)*tblDados[Primeira_Ocorrencia])+SUMPRODUCT((TRIM(tblDados[Visitante])=_xlpm.n)*tblDados[Primeira_Ocorrencia]),_xlpm.s,SUMPRODUCT((TRIM(tblDados[Mandante])=_xlpm.n)*tblDados[Primeira_Ocorrencia]*(tblDados[GM_M]+tblDados[GS_M]))+SUMPRODUCT((TRIM(tblDados[Visitante])=_xlpm.n)*tblDados[Primeira_Ocorrencia]*(tblDados[GM_V]+tblDados[GS_V])),_xlpm.q,SUMPRODUCT((TRIM(tblDados[Mandante])=_xlpm.n)*tblDados[Primeira_Ocorrencia]*(tblDados[GM_M]+tblDados[GS_M])^2)+SUMPRODUCT((TRIM(tblDados[Visitante])=_xlpm.n)*tblDados[Primeira_Ocorrencia]*(tblDados[GM_V]+tblDados[GS_V])^2),IF(_xlpm.c>1,(_xlpm.q-_xlpm.s^2/_xlpm.c)/(_xlpm.c-1),$B$36))} -> 1.5378788 | J36: {=_xlfn.LET(_xlpm.n,$B$6,_xlpm.c,SUMPRODUCT((TRIM(tblDados[Mandante])=_xlpm.n)*tblDados[Primeira_Ocorrencia])+SUMPRODUCT((TRIM(tblDados[Visitante])=_xlpm.n)*tblDados[Primeira_Ocorrencia]),_xlpm.s,SUMPRODUCT((TRIM(tblDados[Mandante])=_xlpm.n)*tblDados[Primeira_Ocorrencia]*(tblDados[GM_M]+tblDados[GS_M]))+SUMPRODUCT((TRIM(tblDados[Visitante])=_xlpm.n)*tblDados[Primeira_Ocorrencia]*(tblDados[GM_V]+tblDados[GS_V])),_xlpm.q,SUMPRODUCT((TRIM(tblDados[Mandante])=_xlpm.n)*tblDados[Primeira_Ocorrencia]*(tblDados[GM_M]+tblDados[GS_M])^2)+SUMPRODUCT((TRIM(tblDados[Visitante])=_xlpm.n)*tblDados[Primeira_Ocorrencia]*(tblDados[GM_V]+tblDados[GS_V])^2),IF(_xlpm.c>1,(_xlpm.q-_xlpm.s^2/_xlpm.c)/(_xlpm.c-1),$B$36))} -> 4.6287879
A37: Amostra combinada | B37: {=SUMPRODUCT((TRIM(tblDados[Mandante])=$B$5)*tblDados[Primeira_Ocorrencia])+SUMPRODUCT((TRIM(tblDados[Visitante])=$B$5)*tblDados[Primeira_Ocorrencia])+SUMPRODUCT((TRIM(tblDados[Mandante])=$B$6)*tblDados[Primeira_Ocorrencia])+SUMPRODUCT((TRIM(tblDados[Visitante])=$B$6)*tblDados[Primeira_Ocorrencia])} -> 24 | C37: Parâmetro r | D37: =IF(OR(D36="",B36="",D36<=B36),"",B36^2/(D36-B36)) -> 84 | E37: Probabilidade p | F37: =IF(OR(D37="",B36=""),"",D37/(D37+B36)) -> 0.95238095 | G37: Critério | H37: 0.75
A39: Linha | B39: Green Poisson | C39: Sem Red Poisson | D39: Green Binomial Neg. | F39: Sem Red Binomial Neg. | G39: Green consenso | H39: Proteção consenso | I39: Leitura
A40: 0.5 | B40: =IF($B$36="","",1-_xlfn.POISSON.DIST(IF(ROUND(MOD($A40,1),2)=0.75,INT($A40)+1,INT($A40)),$B$36,TRUE)) -> 0.98500442 | C40: =IF($B$36="","",1-_xlfn.POISSON.DIST(IF(ROUND(MOD($A40,1),2)=0.5,INT($A40),IF(ROUND(MOD($A40,1),2)=0,INT($A40)-1,IF(ROUND(MOD($A40,1),2)=0.25,INT($A40)-1,INT($A40)))),$B$36,TRUE)) -> 0.98500442 | D40: =IF(OR($D$37="",$F$37=""),"",1-_xlfn.NEGBINOM.DIST(IF(ROUND(MOD($A40,1),2)=0.75,INT($A40)+1,INT($A40)),$D$37,$F$37,TRUE)) -> 0.98340035 | F40: =IF(OR($D$37="",$F$37=""),"",1-_xlfn.NEGBINOM.DIST(IF(ROUND(MOD($A40,1),2)=0.5,INT($A40),IF(ROUND(MOD($A40,1),2)=0,INT($A40)-1,IF(ROUND(MOD($A40,1),2)=0.25,INT($A40)-1,INT($A40)))),$D$37,$F$37,TRUE)) -> 0.98340035 | G40: =IF(OR(B40="",D40=""),"",MIN(B40,D40)) -> 0.98340035 | H40: =IF(OR(C40="",F40=""),"",MIN(C40,F40)) -> 0.98340035 | I40: =IF(G40="","",IF(G40>=75%,"GREEN ≥75%",IF(H40>=75%,"PROTEÇÃO ≥75%","ABAIXO"))) -> GREEN ≥75%
A41: 0.75 | B41: =IF($B$36="","",1-_xlfn.POISSON.DIST(IF(ROUND(MOD($A41,1),2)=0.75,INT($A41)+1,INT($A41)),$B$36,TRUE)) -> 0.922023 | C41: =IF($B$36="","",1-_xlfn.POISSON.DIST(IF(ROUND(MOD($A41,1),2)=0.5,INT($A41),IF(ROUND(MOD($A41,1),2)=0,INT($A41)-1,IF(ROUND(MOD($A41,1),2)=0.25,INT($A41)-1,INT($A41)))),$B$36,TRUE)) -> 0.98500442 | D41: =IF(OR($D$37="",$F$37=""),"",1-_xlfn.NEGBINOM.DIST(IF(ROUND(MOD($A41,1),2)=0.75,INT($A41)+1,INT($A41)),$D$37,$F$37,TRUE)) -> 0.91700176 | F41: =IF(OR($D$37="",$F$37=""),"",1-_xlfn.NEGBINOM.DIST(IF(ROUND(MOD($A41,1),2)=0.5,INT($A41),IF(ROUND(MOD($A41,1),2)=0,INT($A41)-1,IF(ROUND(MOD($A41,1),2)=0.25,INT($A41)-1,INT($A41)))),$D$37,$F$37,TRUE)) -> 0.98340035 | G41: =IF(OR(B41="",D41=""),"",MIN(B41,D41)) -> 0.91700176 | H41: =IF(OR(C41="",F41=""),"",MIN(C41,F41)) -> 0.98340035 | I41: =IF(G41="","",IF(G41>=75%,"GREEN ≥75%",IF(H41>=75%,"PROTEÇÃO ≥75%","ABAIXO"))) -> GREEN ≥75%
A42: 1 | B42: =IF($B$36="","",1-_xlfn.POISSON.DIST(IF(ROUND(MOD($A42,1),2)=0.75,INT($A42)+1,INT($A42)),$B$36,TRUE)) -> 0.922023 | C42: =IF($B$36="","",1-_xlfn.POISSON.DIST(IF(ROUND(MOD($A42,1),2)=0.5,INT($A42),IF(ROUND(MOD($A42,1),2)=0,INT($A42)-1,IF(ROUND(MOD($A42,1),2)=0.25,INT($A42)-1,INT($A42)))),$B$36,TRUE)) -> 0.98500442 | D42: =IF(OR($D$37="",$F$37=""),"",1-_xlfn.NEGBINOM.DIST(IF(ROUND(MOD($A42,1),2)=0.75,INT($A42)+1,INT($A42)),$D$37,$F$37,TRUE)) -> 0.91700176 | F42: =IF(OR($D$37="",$F$37=""),"",1-_xlfn.NEGBINOM.DIST(IF(ROUND(MOD($A42,1),2)=0.5,INT($A42),IF(ROUND(MOD($A42,1),2)=0,INT($A42)-1,IF(ROUND(MOD($A42,1),2)=0.25,INT($A42)-1,INT($A42)))),$D$37,$F$37,TRUE)) -> 0.98340035 | G42: =IF(OR(B42="",D42=""),"",MIN(B42,D42)) -> 0.91700176 | H42: =IF(OR(C42="",F42=""),"",MIN(C42,F42)) -> 0.98340035 | I42: =IF(G42="","",IF(G42>=75%,"GREEN ≥75%",IF(H42>=75%,"PROTEÇÃO ≥75%","ABAIXO"))) -> GREEN ≥75%
A43: 1.25 | B43: =IF($B$36="","",1-_xlfn.POISSON.DIST(IF(ROUND(MOD($A43,1),2)=0.75,INT($A43)+1,INT($A43)),$B$36,TRUE)) -> 0.922023 | C43: =IF($B$36="","",1-_xlfn.POISSON.DIST(IF(ROUND(MOD($A43,1),2)=0.5,INT($A43),IF(ROUND(MOD($A43,1),2)=0,INT($A43)-1,IF(ROUND(MOD($A43,1),2)=0.25,INT($A43)-1,INT($A43)))),$B$36,TRUE)) -> 0.98500442 | D43: =IF(OR($D$37="",$F$37=""),"",1-_xlfn.NEGBINOM.DIST(IF(ROUND(MOD($A43,1),2)=0.75,INT($A43)+1,INT($A43)),$D$37,$F$37,TRUE)) -> 0.91700176 | F43: =IF(OR($D$37="",$F$37=""),"",1-_xlfn.NEGBINOM.DIST(IF(ROUND(MOD($A43,1),2)=0.5,INT($A43),IF(ROUND(MOD($A43,1),2)=0,INT($A43)-1,IF(ROUND(MOD($A43,1),2)=0.25,INT($A43)-1,INT($A43)))),$D$37,$F$37,TRUE)) -> 0.98340035 | G43: =IF(OR(B43="",D43=""),"",MIN(B43,D43)) -> 0.91700176 | H43: =IF(OR(C43="",F43=""),"",MIN(C43,F43)) -> 0.98340035 | I43: =IF(G43="","",IF(G43>=75%,"GREEN ≥75%",IF(H43>=75%,"PROTEÇÃO ≥75%","ABAIXO"))) -> GREEN ≥75%
A44: 1.5 | B44: =IF($B$36="","",1-_xlfn.POISSON.DIST(IF(ROUND(MOD($A44,1),2)=0.75,INT($A44)+1,INT($A44)),$B$36,TRUE)) -> 0.922023 | C44: =IF($B$36="","",1-_xlfn.POISSON.DIST(IF(ROUND(MOD($A44,1),2)=0.5,INT($A44),IF(ROUND(MOD($A44,1),2)=0,INT($A44)-1,IF(ROUND(MOD($A44,1),2)=0.25,INT($A44)-1,INT($A44)))),$B$36,TRUE)) -> 0.922023 | D44: =IF(OR($D$37="",$F$37=""),"",1-_xlfn.NEGBINOM.DIST(IF(ROUND(MOD($A44,1),2)=0.75,INT($A44)+1,INT($A44)),$D$37,$F$37,TRUE)) -> 0.91700176 | F44: =IF(OR($D$37="",$F$37=""),"",1-_xlfn.NEGBINOM.DIST(IF(ROUND(MOD($A44,1),2)=0.5,INT($A44),IF(ROUND(MOD($A44,1),2)=0,INT($A44)-1,IF(ROUND(MOD($A44,1),2)=0.25,INT($A44)-1,INT($A44)))),$D$37,$F$37,TRUE)) -> 0.91700176 | G44: =IF(OR(B44="",D44=""),"",MIN(B44,D44)) -> 0.91700176 | H44: =IF(OR(C44="",F44=""),"",MIN(C44,F44)) -> 0.91700176 | I44: =IF(G44="","",IF(G44>=75%,"GREEN ≥75%",IF(H44>=75%,"PROTEÇÃO ≥75%","ABAIXO"))) -> GREEN ≥75%
A45: 1.75 | B45: =IF($B$36="","",1-_xlfn.POISSON.DIST(IF(ROUND(MOD($A45,1),2)=0.75,INT($A45)+1,INT($A45)),$B$36,TRUE)) -> 0.78976201 | C45: =IF($B$36="","",1-_xlfn.POISSON.DIST(IF(ROUND(MOD($A45,1),2)=0.5,INT($A45),IF(ROUND(MOD($A45,1),2)=0,INT($A45)-1,IF(ROUND(MOD($A45,1),2)=0.25,INT($A45)-1,INT($A45)))),$B$36,TRUE)) -> 0.922023 | D45: =IF(OR($D$37="",$F$37=""),"",1-_xlfn.NEGBINOM.DIST(IF(ROUND(MOD($A45,1),2)=0.75,INT($A45)+1,INT($A45)),$D$37,$F$37,TRUE)) -> 0.78262366 | F45: =IF(OR($D$37="",$F$37=""),"",1-_xlfn.NEGBINOM.DIST(IF(ROUND(MOD($A45,1),2)=0.5,INT($A45),IF(ROUND(MOD($A45,1),2)=0,INT($A45)-1,IF(ROUND(MOD($A45,1),2)=0.25,INT($A45)-1,INT($A45)))),$D$37,$F$37,TRUE)) -> 0.91700176 | G45: =IF(OR(B45="",D45=""),"",MIN(B45,D45)) -> 0.78262366 | H45: =IF(OR(C45="",F45=""),"",MIN(C45,F45)) -> 0.91700176 | I45: =IF(G45="","",IF(G45>=75%,"GREEN ≥75%",IF(H45>=75%,"PROTEÇÃO ≥75%","ABAIXO"))) -> GREEN ≥75%
A46: 2 | B46: =IF($B$36="","",1-_xlfn.POISSON.DIST(IF(ROUND(MOD($A46,1),2)=0.75,INT($A46)+1,INT($A46)),$B$36,TRUE)) -> 0.78976201 | C46: =IF($B$36="","",1-_xlfn.POISSON.DIST(IF(ROUND(MOD($A46,1),2)=0.5,INT($A46),IF(ROUND(MOD($A46,1),2)=0,INT($A46)-1,IF(ROUND(MOD($A46,1),2)=0.25,INT($A46)-1,INT($A46)))),$B$36,TRUE)) -> 0.922023 | D46: =IF(OR($D$37="",$F$37=""),"",1-_xlfn.NEGBINOM.DIST(IF(ROUND(MOD($A46,1),2)=0.75,INT($A46)+1,INT($A46)),$D$37,$F$37,TRUE)) -> 0.78262366 | F46: =IF(OR($D$37="",$F$37=""),"",1-_xlfn.NEGBINOM.DIST(IF(ROUND(MOD($A46,1),2)=0.5,INT($A46),IF(ROUND(MOD($A46,1),2)=0,INT($A46)-1,IF(ROUND(MOD($A46,1),2)=0.25,INT($A46)-1,INT($A46)))),$D$37,$F$37,TRUE)) -> 0.91700176 | G46: =IF(OR(B46="",D46=""),"",MIN(B46,D46)) -> 0.78262366 | H46: =IF(OR(C46="",F46=""),"",MIN(C46,F46)) -> 0.91700176 | I46: =IF(G46="","",IF(G46>=75%,"GREEN ≥75%",IF(H46>=75%,"PROTEÇÃO ≥75%","ABAIXO"))) -> GREEN ≥75%
A47: 2.25 | B47: =IF($B$36="","",1-_xlfn.POISSON.DIST(IF(ROUND(MOD($A47,1),2)=0.75,INT($A47)+1,INT($A47)),$B$36,TRUE)) -> 0.78976201 | C47: =IF($B$36="","",1-_xlfn.POISSON.DIST(IF(ROUND(MOD($A47,1),2)=0.5,INT($A47),IF(ROUND(MOD($A47,1),2)=0,INT($A47)-1,IF(ROUND(MOD($A47,1),2)=0.25,INT($A47)-1,INT($A47)))),$B$36,TRUE)) -> 0.922023 | D47: =IF(OR($D$37="",$F$37=""),"",1-_xlfn.NEGBINOM.DIST(IF(ROUND(MOD($A47,1),2)=0.75,INT($A47)+1,INT($A47)),$D$37,$F$37,TRUE)) -> 0.78262366 | F47: =IF(OR($D$37="",$F$37=""),"",1-_xlfn.NEGBINOM.DIST(IF(ROUND(MOD($A47,1),2)=0.5,INT($A47),IF(ROUND(MOD($A47,1),2)=0,INT($A47)-1,IF(ROUND(MOD($A47,1),2)=0.25,INT($A47)-1,INT($A47)))),$D$37,$F$37,TRUE)) -> 0.91700176 | G47: =IF(OR(B47="",D47=""),"",MIN(B47,D47)) -> 0.78262366 | H47: =IF(OR(C47="",F47=""),"",MIN(C47,F47)) -> 0.91700176 | I47: =IF(G47="","",IF(G47>=75%,"GREEN ≥75%",IF(H47>=75%,"PROTEÇÃO ≥75%","ABAIXO"))) -> GREEN ≥75%
A48: 2.5 | B48: =IF($B$36="","",1-_xlfn.POISSON.DIST(IF(ROUND(MOD($A48,1),2)=0.75,INT($A48)+1,INT($A48)),$B$36,TRUE)) -> 0.78976201 | C48: =IF($B$36="","",1-_xlfn.POISSON.DIST(IF(ROUND(MOD($A48,1),2)=0.5,INT($A48),IF(ROUND(MOD($A48,1),2)=0,INT($A48)-1,IF(ROUND(MOD($A48,1),2)=0.25,INT($A48)-1,INT($A48)))),$B$36,TRUE)) -> 0.78976201 | D48: =IF(OR($D$37="",$F$37=""),"",1-_xlfn.NEGBINOM.DIST(IF(ROUND(MOD($A48,1),2)=0.75,INT($A48)+1,INT($A48)),$D$37,$F$37,TRUE)) -> 0.78262366 | F48: =IF(OR($D$37="",$F$37=""),"",1-_xlfn.NEGBINOM.DIST(IF(ROUND(MOD($A48,1),2)=0.5,INT($A48),IF(ROUND(MOD($A48,1),2)=0,INT($A48)-1,IF(ROUND(MOD($A48,1),2)=0.25,INT($A48)-1,INT($A48)))),$D$37,$F$37,TRUE)) -> 0.78262366 | G48: =IF(OR(B48="",D48=""),"",MIN(B48,D48)) -> 0.78262366 | H48: =IF(OR(C48="",F48=""),"",MIN(C48,F48)) -> 0.78262366 | I48: =IF(G48="","",IF(G48>=75%,"GREEN ≥75%",IF(H48>=75%,"PROTEÇÃO ≥75%","ABAIXO"))) -> GREEN ≥75%
A49: 2.75 | B49: =IF($B$36="","",1-_xlfn.POISSON.DIST(IF(ROUND(MOD($A49,1),2)=0.75,INT($A49)+1,INT($A49)),$B$36,TRUE)) -> 0.60459663 | C49: =IF($B$36="","",1-_xlfn.POISSON.DIST(IF(ROUND(MOD($A49,1),2)=0.5,INT($A49),IF(ROUND(MOD($A49,1),2)=0,INT($A49)-1,IF(ROUND(MOD($A49,1),2)=0.25,INT($A49)-1,INT($A49)))),$B$36,TRUE)) -> 0.78976201 | D49: =IF(OR($D$37="",$F$37=""),"",1-_xlfn.NEGBINOM.DIST(IF(ROUND(MOD($A49,1),2)=0.75,INT($A49)+1,INT($A49)),$D$37,$F$37,TRUE)) -> 0.59918688 | F49: =IF(OR($D$37="",$F$37=""),"",1-_xlfn.NEGBINOM.DIST(IF(ROUND(MOD($A49,1),2)=0.5,INT($A49),IF(ROUND(MOD($A49,1),2)=0,INT($A49)-1,IF(ROUND(MOD($A49,1),2)=0.25,INT($A49)-1,INT($A49)))),$D$37,$F$37,TRUE)) -> 0.78262366 | G49: =IF(OR(B49="",D49=""),"",MIN(B49,D49)) -> 0.59918688 | H49: =IF(OR(C49="",F49=""),"",MIN(C49,F49)) -> 0.78262366 | I49: =IF(G49="","",IF(G49>=75%,"GREEN ≥75%",IF(H49>=75%,"PROTEÇÃO ≥75%","ABAIXO"))) -> PROTEÇÃO ≥75%
A50: 3 | B50: =IF($B$36="","",1-_xlfn.POISSON.DIST(IF(ROUND(MOD($A50,1),2)=0.75,INT($A50)+1,INT($A50)),$B$36,TRUE)) -> 0.60459663 | C50: =IF($B$36="","",1-_xlfn.POISSON.DIST(IF(ROUND(MOD($A50,1),2)=0.5,INT($A50),IF(ROUND(MOD($A50,1),2)=0,INT($A50)-1,IF(ROUND(MOD($A50,1),2)=0.25,INT($A50)-1,INT($A50)))),$B$36,TRUE)) -> 0.78976201 | D50: =IF(OR($D$37="",$F$37=""),"",1-_xlfn.NEGBINOM.DIST(IF(ROUND(MOD($A50,1),2)=0.75,INT($A50)+1,INT($A50)),$D$37,$F$37,TRUE)) -> 0.59918688 | F50: =IF(OR($D$37="",$F$37=""),"",1-_xlfn.NEGBINOM.DIST(IF(ROUND(MOD($A50,1),2)=0.5,INT($A50),IF(ROUND(MOD($A50,1),2)=0,INT($A50)-1,IF(ROUND(MOD($A50,1),2)=0.25,INT($A50)-1,INT($A50)))),$D$37,$F$37,TRUE)) -> 0.78262366 | G50: =IF(OR(B50="",D50=""),"",MIN(B50,D50)) -> 0.59918688 | H50: =IF(OR(C50="",F50=""),"",MIN(C50,F50)) -> 0.78262366 | I50: =IF(G50="","",IF(G50>=75%,"GREEN ≥75%",IF(H50>=75%,"PROTEÇÃO ≥75%","ABAIXO"))) -> PROTEÇÃO ≥75%
A51: Faixa ≥75% | B51: Green até | C51: {=IFERROR(MAX(_xlfn._xlws.FILTER($A$40:$A$50,$G$40:$G$50>=75%)),"")} -> 2.5 | F51: Proteção até | G51: {=IFERROR(MAX(_xlfn._xlws.FILTER($A$40:$A$50,$H$40:$H$50>=75%)),"")} -> 3 | H51: Odds entram depois
A53: DIRETRIZ PROVISÓRIA — AJUSTE DE LINHA POR λ E RISCO DE 0×0
A54: Base: 30 bilhetes contabilizados, 29 com λ · regra experimental até nova calibração
A56: Critério | B56: Valor | C56: Leitura | D56: Aplicação | F56: Sinal | G56: Resultado | H56: Estado | I56: Observação
A57: λ total | B57: =$D$10 -> 4.2 | C57: =IF(B57<2.5,"Proteção máxima",IF(B57<3.5,"Faixa de avanço","Sem avanço automático")) -> Sem avanço automático | D57: Corte provisório | F57: Regime de λ | G57: =C57 -> Sem avanço automático | H57: Provisório | I57: 29 bilhetes com λ
A58: Risco 0×0 consenso | B58: =IF($H$40="","",1-$H$40) -> 0.016599648 | C58: =IF(B58<=5%,"Baixo",IF(B58<=10%,"Atenção","Impeditivo")) -> Baixo | D58: Filtro de cauda | F58: Filtro 0×0 | G58: =$B$58 -> 0.016599648 | H58: Dinâmico | I58: ≤5% baixo · 5–10% atenção · >10% impeditivo
A59: Ajuste provisório | B59: =IF(OR($D$10="",$B$58>10%),0,IF(AND($D$10>=2.5,$D$10<3.5),IF($B$58<7.5%,0.5,0.25),0)) -> 0 | C59: =IF(B58>10%,"Bloqueado",IF(B59=0.5,"Avançar 0,50",IF(B59=0.25,"Avançar 0,25","Sem avanço"))) -> Sem avanço | D59: Somente λ 2,50–3,49 | F59: Ajuste de linha | G59: =$B$59 -> 0 | H59: Dinâmico | I59: +0,50 se 0×0 <7,5%; senão +0,25
A60: Linha técnica | B60: =$H$13 -> 2.5 | C60: Mediana técnica atual | D60: Base do simulador | F60: Linha sugerida | G60: =IF(B61=0,"—","OVER "&FIXED(B61,2,FALSE)) -> OVER 2,50 | H60: Dinâmico | I60: λ ≥3,50 não avança automaticamente
A61: Linha operacional | B61: =IF(OR($H$13=0,$B$58>10%),0,MIN(3,$H$13+$B$59)) -> 2.5 | C61: =IF(B61=0,"Sem entrada","OVER "&FIXED(B61,2,FALSE)) -> OVER 2,50 | D61: Limitada a Over 3,00 | F61: Orientação final | G61: =$G$15 -> ANALISAR OVER 2,50 | H61: Ativo | I61: Odds entram depois da triagem

Sheet Modelo 02
A1: MODELO 02 — DETECÇÃO DE PARTIDAS EXPLOSIVAS
A2: V2 · Modelo 01 acrescido de teto empírico, dispersão, regime da liga e dominância unilateral
A4: SELEÇÃO DA PARTIDA
A5: Mandante | B5: Degerfors IF | D5: País - Liga | E5: =IF($B$5="","",IFERROR(INDEX(Equipes!$B$2:$B$1000,MATCH($B$5,Equipes!$A$2:$A$1000,0)),"Sem histórico")) -> SWE - Allsvenskan | H5: =IF($B$5="","",IF(COUNTIF(Equipes!$A$2:$A$1000,TRIM($B$5))>0,"✓ Histórico disponível",IF(COUNTIF(CadastroEquipes,TRIM($B$5))>0,"⚠ Cadastrada, sem histórico","⚠ Nome não cadastrado"))) -> ✓ Histórico disponível
A6: Visitante | B6: IFK Göteborg | D6: País - Liga | E6: =IF($B$6="","",IFERROR(INDEX(Equipes!$B$2:$B$1000,MATCH($B$6,Equipes!$A$2:$A$1000,0)),"Sem histórico")) -> SWE - Allsvenskan | H6: =IF($B$6="","",IF(COUNTIF(Equipes!$A$2:$A$1000,TRIM($B$6))>0,"✓ Histórico disponível",IF(COUNTIF(CadastroEquipes,TRIM($B$6))>0,"⚠ Cadastrada, sem histórico","⚠ Nome não cadastrado"))) -> ✓ Histórico disponível
A8: PARÂMETROS DO MODELO | F8: LEITURA RÁPIDA — CONSENSO DE ENTRADA
A9: Métrica | B9: Mandante | C9: Visitante | D9: Partida | F9: Sinal | G9: Orientação | H9: Nível
A10: Gols esperados (λ) | B10: =IF(OR($B$5="",$B$6=""),"",_xlfn.LET(_xlpm.x,IFERROR(INDEX(Equipes!$AA$2:$AA$1000,MATCH($B$5,Equipes!$A$2:$A$1000,0)),""),_xlpm.y,IFERROR(INDEX(Equipes!$AD$2:$AD$1000,MATCH($B$6,Equipes!$A$2:$A$1000,0)),""),IF(OR(_xlpm.x="",_xlpm.y=""),"",AVERAGE(_xlpm.x,_xlpm.y)))) -> 2.4 | C10: =IF(OR($B$5="",$B$6=""),"",_xlfn.LET(_xlpm.x,IFERROR(INDEX(Equipes!$AC$2:$AC$1000,MATCH($B$6,Equipes!$A$2:$A$1000,0)),""),_xlpm.y,IFERROR(INDEX(Equipes!$AB$2:$AB$1000,MATCH($B$5,Equipes!$A$2:$A$1000,0)),""),IF(OR(_xlpm.x="",_xlpm.y=""),"",AVERAGE(_xlpm.x,_xlpm.y)))) -> 1.8 | D10: =IF(OR(B10="",C10=""),"",B10+C10) -> 4.2 | F10: Probabilidades | G10: =IF($H$10=0,"Sem linha aprovada","Até Over "&FIXED($H$10,2,FALSE)) -> Até Over 1,75 | H10: {=IF($D$10="",0,_xlfn.LET(_xlpm.ls,{0.5;0.75;1;1.25;1.5;1.75;2;2.25;2.5;2.75;3},_xlpm.th,{0.95;0.94;0.925;0.9125;0.9;0.88;0.86;0.84;0.82;0.8025;0.785},_xlpm.sc,_xlfn.MAP(_xlpm.ls,_xlfn.LAMBDA(_xlpm.l,_xlfn.LET(_xlpm.n,INT(_xlpm.l),_xlpm.f,ROUND(MOD(_xlpm.l,1),2),_xlpm.si,_xlfn.LAMBDA(_xlpm.k,1-_xlfn.POISSON.DIST(_xlpm.k,$D$10,TRUE)+0.5*_xlfn.POISSON.DIST(_xlpm.k,$D$10,FALSE)),_xlpm.sh,_xlfn.LAMBDA(_xlpm.k,1-_xlfn.POISSON.DIST(_xlpm.k,$D$10,TRUE)),IF(_xlpm.f=0.5,_xlpm.sh(_xlpm.n),IF(_xlpm.f=0,_xlpm.si(_xlpm.n),IF(_xlpm.f=0.25,AVERAGE(_xlpm.si(_xlpm.n),_xlpm.sh(_xlpm.n)),AVERAGE(_xlpm.sh(_xlpm.n),_xlpm.si(_xlpm.n+1)))))))),IFERROR(MAX(_xlfn._xlws.FILTER(_xlpm.ls,_xlpm.sc>=_xlpm.th)),0)))} -> 1.75
A11: Jogos na condição | B11: =IFERROR(INDEX(Equipes!$E$2:$E$1000,MATCH($B$5,Equipes!$A$2:$A$1000,0)),"") -> 5 | C11: =IFERROR(INDEX(Equipes!$F$2:$F$1000,MATCH($B$6,Equipes!$A$2:$A$1000,0)),"") -> 5 | D11: =IF(OR(B11="",C11=""),"",MIN(B11,C11)) -> 5 | F11: Potencial de gols | G11: =IF($D$10="","Aguardando histórico",IF($H$11=0,"Baixo potencial","Suporta Over "&FIXED($H$11,2,FALSE))) -> Suporta Over 2,50 | H11: =IF($D$10="",0,IF($D$10<1.5,0,IF($D$10<2.5,0.5,IF($D$10<3.5,1.5,IF($D$10<4.5,2.5,3))))) -> 2.5
A12: Índice de força | B12: =IFERROR(INDEX(Equipes!$C$2:$C$1000,MATCH($B$5,Equipes!$A$2:$A$1000,0)),"") -> 2.6 | C12: =IFERROR(INDEX(Equipes!$D$2:$D$1000,MATCH($B$6,Equipes!$A$2:$A$1000,0)),"") -> 5.8 | D12: =IF(OR(B12="",C12=""),"",AVERAGE(B12,C12)) -> 4.2 | F12: Placares Top 8 | G12: =IF($H$12=0,"Sem concentração Over","Top 8 suporta Over "&FIXED($H$12,2,FALSE)) -> Top 8 suporta Over 3,00 | H12: {=IF($D$10="",0,_xlfn.LET(_xlpm.t,VALUE(_xlfn.TEXTBEFORE($G$19:$G$26," x "))+VALUE(_xlfn.TEXTAFTER($G$19:$G$26," x ")),MAX(0,MIN(3,FLOOR(MEDIAN(_xlpm.t)-0.5,0.25)))))} -> 3
A13: Modelo da equipe | B13: =IFERROR(INDEX(Equipes!$R$2:$R$1000,MATCH($B$5,Equipes!$A$2:$A$1000,0)),"") -> Poisson | C13: =IFERROR(INDEX(Equipes!$R$2:$R$1000,MATCH($B$6,Equipes!$A$2:$A$1000,0)),"") -> Poisson | D13: =IF(OR(B13="",C13=""),"",IF(OR(B13="Amostra Insuficiente",C13="Amostra Insuficiente"),"Poisson preliminar",IF(B13=C13,B13,"Poisson base / dispersão"))) -> Poisson | F13: Linha técnica | G13: =IF($H$13=0,"SEM CONSENSO","OVER "&FIXED($H$13,2,FALSE)) -> OVER 2,50 | H13: =MEDIAN($H$10:$H$12) -> 2.5
A14: Qualidade da amostra | B14: =IF(B11="","",IF(B11>=10,"Robusta",IF(B11>=5,"Em formação","Preliminar"))) -> Em formação | C14: =IF(C11="","",IF(C11>=10,"Robusta",IF(C11>=5,"Em formação","Preliminar"))) -> Em formação | D14: =IF(OR(B11="",C11=""),"",IF(MIN(B11,C11)>=10,"Robusta",IF(MIN(B11,C11)>=5,"Em formação","Preliminar"))) -> Em formação | F14: Fase por liga | G14: =IF($H$14>=15,"FASE 2 — OTIMIZAR LUCRO","FASE 1 — PRESERVAR CAPITAL") -> FASE 1 — PRESERVAR CAPITAL | H14: =_xlfn.LET(_xlpm.l,IF($E$5=$E$6,$E$5,IF(AND(ISNUMBER(SEARCH("Kakkonen",$E$5)),ISNUMBER(SEARCH("Kakkonen",$E$6))),"FIN - Kakkonen",$E$5&" / "&$E$6)),COUNTIF(tblCalibracao[Liga],_xlpm.l)) -> 1
A15: ρ Dixon–Coles | B15: 0 | D15: 0 = Poisson puro; calibrar por liga futuramente | F15: Orientação final | G15: =IF($H$13=0,"NÃO APOSTAR",IF(1-$H$40>10%,"NÃO APOSTAR — 0x0 "&TEXT(1-$H$40,"0.0%"),"ANALISAR OVER "&FIXED(MIN(3,$H$13+IF(AND($D$10>=2.5,$D$10<3.5),IF(1-$H$40<7.5%,0.5,0.25),0)),2,FALSE))) -> ANALISAR OVER 2,50 | H15: =IF($H$13=0,"—",IF(1-$H$40>10%,"IMPEDITIVO",IF(AND($D$10>=2.5,$D$10<3.5),IF(1-$H$40<7.5%,"Avançar +0,50","Avançar +0,25"),IF($D$10>=3.5,"Sem avanço automático","Máxima proteção")))) -> Sem avanço automático
A17: PROBABILIDADES — LINHAS ASIÁTICAS OVER | F17: PLACARES MAIS PROVÁVEIS
A18: Linha | B18: Prob. ajustada | C18: Classificação | D18: Proteção / liquidação | F18: Posição | G18: Placar | H18: Probabilidade
A19: 0.5 | B19: =IF($D$10="","",_xlfn.LET(_xlpm.l,$A19,_xlpm.n,INT(_xlpm.l),_xlpm.f,ROUND(MOD(_xlpm.l,1),2),_xlpm.si,1-_xlfn.POISSON.DIST(_xlpm.n,$D$10,TRUE)+0.5*_xlfn.POISSON.DIST(_xlpm.n,$D$10,FALSE),_xlpm.sh,1-_xlfn.POISSON.DIST(_xlpm.n,$D$10,TRUE),IF(_xlpm.f=0.5,_xlpm.sh,IF(_xlpm.f=0,_xlpm.si,IF(_xlpm.f=0.25,AVERAGE(_xlpm.si,_xlpm.sh),AVERAGE(_xlpm.sh,1-_xlfn.POISSON.DIST(_xlpm.n+1,$D$10,TRUE)+0.5*_xlfn.POISSON.DIST(_xlpm.n+1,$D$10,FALSE))))))) -> 0.98500442 | C19: {=IF($B19="","",_xlfn.LET(_xlpm.l,$A19,_xlpm.lim,_xlfn.XLOOKUP(_xlpm.l,{0.5,0.75,1,1.25,1.5,1.75,2,2.25,2.5,2.75,3},{0.95,0.94,0.925,0.9125,0.9,0.88,0.86,0.84,0.82,0.8025,0.785}),IF($B19>=_xlpm.lim,"APROVADA",IF($B19>=_xlpm.lim-5%,"PRÓXIMA","ABAIXO"))))} -> APROVADA | D19: Sem proteção | F19: {=IF(OR($B$10="",$C$10=""),"",_xlfn.LET(_xlpm.n,9,_xlpm.i,_xlfn.SEQUENCE(_xlpm.n*_xlpm.n,1,0),_xlpm.h,INT(_xlpm.i/_xlpm.n),_xlpm.a,MOD(_xlpm.i,_xlpm.n),_xlpm.p,_xlfn.POISSON.DIST(_xlpm.h,$B$10,FALSE)*_xlfn.POISSON.DIST(_xlpm.a,$C$10,FALSE)*IF((_xlpm.h=0)*(_xlpm.a=0),1-$B$10*$C$10*$B$15,IF((_xlpm.h=0)*(_xlpm.a=1),1+$B$10*$B$15,IF((_xlpm.h=1)*(_xlpm.a=0),1+$C$10*$B$15,IF((_xlpm.h=1)*(_xlpm.a=1),1-$B$15,1)))),_xlpm.s,_xlfn.SORTBY(_xlfn.HSTACK(_xlpm.h&" x "&_xlpm.a,_xlpm.p),_xlpm.p,-1),_xlfn.HSTACK(_xlfn.SEQUENCE(8),_xlfn.TAKE(_xlpm.s,8))))} -> 1 | G19: 2 x 1 | H19: 0.07773707
A20: 0.75 | B20: =IF($D$10="","",_xlfn.LET(_xlpm.l,$A20,_xlpm.n,INT(_xlpm.l),_xlpm.f,ROUND(MOD(_xlpm.l,1),2),_xlpm.si,1-_xlfn.POISSON.DIST(_xlpm.n,$D$10,TRUE)+0.5*_xlfn.POISSON.DIST(_xlpm.n,$D$10,FALSE),_xlpm.sh,1-_xlfn.POISSON.DIST(_xlpm.n,$D$10,TRUE),IF(_xlpm.f=0.5,_xlpm.sh,IF(_xlpm.f=0,_xlpm.si,IF(_xlpm.f=0.25,AVERAGE(_xlpm.si,_xlpm.sh),AVERAGE(_xlpm.sh,1-_xlfn.POISSON.DIST(_xlpm.n+1,$D$10,TRUE)+0.5*_xlfn.POISSON.DIST(_xlpm.n+1,$D$10,FALSE))))))) -> 0.96925907 | C20: {=IF($B20="","",_xlfn.LET(_xlpm.l,$A20,_xlpm.lim,_xlfn.XLOOKUP(_xlpm.l,{0.5,0.75,1,1.25,1.5,1.75,2,2.25,2.5,2.75,3},{0.95,0.94,0.925,0.9125,0.9,0.88,0.86,0.84,0.82,0.8025,0.785}),IF($B20>=_xlpm.lim,"APROVADA",IF($B20>=_xlpm.lim-5%,"PRÓXIMA","ABAIXO"))))} -> APROVADA | D20: ½ GREEN com 1 gol | F20: 2 | G20: 2 x 2 | H20: 0.069963363
A21: 1 | B21: =IF($D$10="","",_xlfn.LET(_xlpm.l,$A21,_xlpm.n,INT(_xlpm.l),_xlpm.f,ROUND(MOD(_xlpm.l,1),2),_xlpm.si,1-_xlfn.POISSON.DIST(_xlpm.n,$D$10,TRUE)+0.5*_xlfn.POISSON.DIST(_xlpm.n,$D$10,FALSE),_xlpm.sh,1-_xlfn.POISSON.DIST(_xlpm.n,$D$10,TRUE),IF(_xlpm.f=0.5,_xlpm.sh,IF(_xlpm.f=0,_xlpm.si,IF(_xlpm.f=0.25,AVERAGE(_xlpm.si,_xlpm.sh),AVERAGE(_xlpm.sh,1-_xlfn.POISSON.DIST(_xlpm.n+1,$D$10,TRUE)+0.5*_xlfn.POISSON.DIST(_xlpm.n+1,$D$10,FALSE))))))) -> 0.95351371 | C21: {=IF($B21="","",_xlfn.LET(_xlpm.l,$A21,_xlpm.lim,_xlfn.XLOOKUP(_xlpm.l,{0.5,0.75,1,1.25,1.5,1.75,2,2.25,2.5,2.75,3},{0.95,0.94,0.925,0.9125,0.9,0.88,0.86,0.84,0.82,0.8025,0.785}),IF($B21>=_xlpm.lim,"APROVADA",IF($B21>=_xlpm.lim-5%,"PRÓXIMA","ABAIXO"))))} -> APROVADA | D21: PUSH com 1 gol | F21: 3 | G21: 1 x 1 | H21: 0.064780892
A22: 1.25 | B22: =IF($D$10="","",_xlfn.LET(_xlpm.l,$A22,_xlpm.n,INT(_xlpm.l),_xlpm.f,ROUND(MOD(_xlpm.l,1),2),_xlpm.si,1-_xlfn.POISSON.DIST(_xlpm.n,$D$10,TRUE)+0.5*_xlfn.POISSON.DIST(_xlpm.n,$D$10,FALSE),_xlpm.sh,1-_xlfn.POISSON.DIST(_xlpm.n,$D$10,TRUE),IF(_xlpm.f=0.5,_xlpm.sh,IF(_xlpm.f=0,_xlpm.si,IF(_xlpm.f=0.25,AVERAGE(_xlpm.si,_xlpm.sh),AVERAGE(_xlpm.sh,1-_xlfn.POISSON.DIST(_xlpm.n+1,$D$10,TRUE)+0.5*_xlfn.POISSON.DIST(_xlpm.n+1,$D$10,FALSE))))))) -> 0.93776836 | C22: {=IF($B22="","",_xlfn.LET(_xlpm.l,$A22,_xlpm.lim,_xlfn.XLOOKUP(_xlpm.l,{0.5,0.75,1,1.25,1.5,1.75,2,2.25,2.5,2.75,3},{0.95,0.94,0.925,0.9125,0.9,0.88,0.86,0.84,0.82,0.8025,0.785}),IF($B22>=_xlpm.lim,"APROVADA",IF($B22>=_xlpm.lim-5%,"PRÓXIMA","ABAIXO"))))} -> APROVADA | D22: ½ RED com 1 gol | F22: 4 | G22: 3 x 1 | H22: 0.062189656
A23: 1.5 | B23: =IF($D$10="","",_xlfn.LET(_xlpm.l,$A23,_xlpm.n,INT(_xlpm.l),_xlpm.f,ROUND(MOD(_xlpm.l,1),2),_xlpm.si,1-_xlfn.POISSON.DIST(_xlpm.n,$D$10,TRUE)+0.5*_xlfn.POISSON.DIST(_xlpm.n,$D$10,FALSE),_xlpm.sh,1-_xlfn.POISSON.DIST(_xlpm.n,$D$10,TRUE),IF(_xlpm.f=0.5,_xlpm.sh,IF(_xlpm.f=0,_xlpm.si,IF(_xlpm.f=0.25,AVERAGE(_xlpm.si,_xlpm.sh),AVERAGE(_xlpm.sh,1-_xlfn.POISSON.DIST(_xlpm.n+1,$D$10,TRUE)+0.5*_xlfn.POISSON.DIST(_xlpm.n+1,$D$10,FALSE))))))) -> 0.922023 | C23: {=IF($B23="","",_xlfn.LET(_xlpm.l,$A23,_xlpm.lim,_xlfn.XLOOKUP(_xlpm.l,{0.5,0.75,1,1.25,1.5,1.75,2,2.25,2.5,2.75,3},{0.95,0.94,0.925,0.9125,0.9,0.88,0.86,0.84,0.82,0.8025,0.785}),IF($B23>=_xlpm.lim,"APROVADA",IF($B23>=_xlpm.lim-5%,"PRÓXIMA","ABAIXO"))))} -> APROVADA | D23: Sem proteção | F23: 5 | G23: 1 x 2 | H23: 0.058302803
A24: 1.75 | B24: =IF($D$10="","",_xlfn.LET(_xlpm.l,$A24,_xlpm.n,INT(_xlpm.l),_xlpm.f,ROUND(MOD(_xlpm.l,1),2),_xlpm.si,1-_xlfn.POISSON.DIST(_xlpm.n,$D$10,TRUE)+0.5*_xlfn.POISSON.DIST(_xlpm.n,$D$10,FALSE),_xlpm.sh,1-_xlfn.POISSON.DIST(_xlpm.n,$D$10,TRUE),IF(_xlpm.f=0.5,_xlpm.sh,IF(_xlpm.f=0,_xlpm.si,IF(_xlpm.f=0.25,AVERAGE(_xlpm.si,_xlpm.sh),AVERAGE(_xlpm.sh,1-_xlfn.POISSON.DIST(_xlpm.n+1,$D$10,TRUE)+0.5*_xlfn.POISSON.DIST(_xlpm.n+1,$D$10,FALSE))))))) -> 0.88895775 | C24: {=IF($B24="","",_xlfn.LET(_xlpm.l,$A24,_xlpm.lim,_xlfn.XLOOKUP(_xlpm.l,{0.5,0.75,1,1.25,1.5,1.75,2,2.25,2.5,2.75,3},{0.95,0.94,0.925,0.9125,0.9,0.88,0.86,0.84,0.82,0.8025,0.785}),IF($B24>=_xlpm.lim,"APROVADA",IF($B24>=_xlpm.lim-5%,"PRÓXIMA","ABAIXO"))))} -> APROVADA | D24: ½ GREEN com 2 gols | F24: 6 | G24: 3 x 2 | H24: 0.055970691
A25: 2 | B25: =IF($D$10="","",_xlfn.LET(_xlpm.l,$A25,_xlpm.n,INT(_xlpm.l),_xlpm.f,ROUND(MOD(_xlpm.l,1),2),_xlpm.si,1-_xlfn.POISSON.DIST(_xlpm.n,$D$10,TRUE)+0.5*_xlfn.POISSON.DIST(_xlpm.n,$D$10,FALSE),_xlpm.sh,1-_xlfn.POISSON.DIST(_xlpm.n,$D$10,TRUE),IF(_xlpm.f=0.5,_xlpm.sh,IF(_xlpm.f=0,_xlpm.si,IF(_xlpm.f=0.25,AVERAGE(_xlpm.si,_xlpm.sh),AVERAGE(_xlpm.sh,1-_xlfn.POISSON.DIST(_xlpm.n+1,$D$10,TRUE)+0.5*_xlfn.POISSON.DIST(_xlpm.n+1,$D$10,FALSE))))))) -> 0.85589251 | C25: {=IF($B25="","",_xlfn.LET(_xlpm.l,$A25,_xlpm.lim,_xlfn.XLOOKUP(_xlpm.l,{0.5,0.75,1,1.25,1.5,1.75,2,2.25,2.5,2.75,3},{0.95,0.94,0.925,0.9125,0.9,0.88,0.86,0.84,0.82,0.8025,0.785}),IF($B25>=_xlpm.lim,"APROVADA",IF($B25>=_xlpm.lim-5%,"PRÓXIMA","ABAIXO"))))} -> PRÓXIMA | D25: PUSH com 2 gols | F25: 7 | G25: 2 x 0 | H25: 0.043187261
A26: 2.25 | B26: =IF($D$10="","",_xlfn.LET(_xlpm.l,$A26,_xlpm.n,INT(_xlpm.l),_xlpm.f,ROUND(MOD(_xlpm.l,1),2),_xlpm.si,1-_xlfn.POISSON.DIST(_xlpm.n,$D$10,TRUE)+0.5*_xlfn.POISSON.DIST(_xlpm.n,$D$10,FALSE),_xlpm.sh,1-_xlfn.POISSON.DIST(_xlpm.n,$D$10,TRUE),IF(_xlpm.f=0.5,_xlpm.sh,IF(_xlpm.f=0,_xlpm.si,IF(_xlpm.f=0.25,AVERAGE(_xlpm.si,_xlpm.sh),AVERAGE(_xlpm.sh,1-_xlfn.POISSON.DIST(_xlpm.n+1,$D$10,TRUE)+0.5*_xlfn.POISSON.DIST(_xlpm.n+1,$D$10,FALSE))))))) -> 0.82282726 | C26: {=IF($B26="","",_xlfn.LET(_xlpm.l,$A26,_xlpm.lim,_xlfn.XLOOKUP(_xlpm.l,{0.5,0.75,1,1.25,1.5,1.75,2,2.25,2.5,2.75,3},{0.95,0.94,0.925,0.9125,0.9,0.88,0.86,0.84,0.82,0.8025,0.785}),IF($B26>=_xlpm.lim,"APROVADA",IF($B26>=_xlpm.lim-5%,"PRÓXIMA","ABAIXO"))))} -> PRÓXIMA | D26: ½ RED com 2 gols | F26: 8 | G26: 2 x 3 | H26: 0.041978018
A27: 2.5 | B27: =IF($D$10="","",_xlfn.LET(_xlpm.l,$A27,_xlpm.n,INT(_xlpm.l),_xlpm.f,ROUND(MOD(_xlpm.l,1),2),_xlpm.si,1-_xlfn.POISSON.DIST(_xlpm.n,$D$10,TRUE)+0.5*_xlfn.POISSON.DIST(_xlpm.n,$D$10,FALSE),_xlpm.sh,1-_xlfn.POISSON.DIST(_xlpm.n,$D$10,TRUE),IF(_xlpm.f=0.5,_xlpm.sh,IF(_xlpm.f=0,_xlpm.si,IF(_xlpm.f=0.25,AVERAGE(_xlpm.si,_xlpm.sh),AVERAGE(_xlpm.sh,1-_xlfn.POISSON.DIST(_xlpm.n+1,$D$10,TRUE)+0.5*_xlfn.POISSON.DIST(_xlpm.n+1,$D$10,FALSE))))))) -> 0.78976201 | C27: {=IF($B27="","",_xlfn.LET(_xlpm.l,$A27,_xlpm.lim,_xlfn.XLOOKUP(_xlpm.l,{0.5,0.75,1,1.25,1.5,1.75,2,2.25,2.5,2.75,3},{0.95,0.94,0.925,0.9125,0.9,0.88,0.86,0.84,0.82,0.8025,0.785}),IF($B27>=_xlpm.lim,"APROVADA",IF($B27>=_xlpm.lim-5%,"PRÓXIMA","ABAIXO"))))} -> PRÓXIMA | D27: Sem proteção
A28: 2.75 | B28: =IF($D$10="","",_xlfn.LET(_xlpm.l,$A28,_xlpm.n,INT(_xlpm.l),_xlpm.f,ROUND(MOD(_xlpm.l,1),2),_xlpm.si,1-_xlfn.POISSON.DIST(_xlpm.n,$D$10,TRUE)+0.5*_xlfn.POISSON.DIST(_xlpm.n,$D$10,FALSE),_xlpm.sh,1-_xlfn.POISSON.DIST(_xlpm.n,$D$10,TRUE),IF(_xlpm.f=0.5,_xlpm.sh,IF(_xlpm.f=0,_xlpm.si,IF(_xlpm.f=0.25,AVERAGE(_xlpm.si,_xlpm.sh),AVERAGE(_xlpm.sh,1-_xlfn.POISSON.DIST(_xlpm.n+1,$D$10,TRUE)+0.5*_xlfn.POISSON.DIST(_xlpm.n+1,$D$10,FALSE))))))) -> 0.74347067 | C28: {=IF($B28="","",_xlfn.LET(_xlpm.l,$A28,_xlpm.lim,_xlfn.XLOOKUP(_xlpm.l,{0.5,0.75,1,1.25,1.5,1.75,2,2.25,2.5,2.75,3},{0.95,0.94,0.925,0.9125,0.9,0.88,0.86,0.84,0.82,0.8025,0.785}),IF($B28>=_xlpm.lim,"APROVADA",IF($B28>=_xlpm.lim-5%,"PRÓXIMA","ABAIXO"))))} -> ABAIXO | D28: ½ GREEN com 3 gols
A29: 3 | B29: =IF($D$10="","",_xlfn.LET(_xlpm.l,$A29,_xlpm.n,INT(_xlpm.l),_xlpm.f,ROUND(MOD(_xlpm.l,1),2),_xlpm.si,1-_xlfn.POISSON.DIST(_xlpm.n,$D$10,TRUE)+0.5*_xlfn.POISSON.DIST(_xlpm.n,$D$10,FALSE),_xlpm.sh,1-_xlfn.POISSON.DIST(_xlpm.n,$D$10,TRUE),IF(_xlpm.f=0.5,_xlpm.sh,IF(_xlpm.f=0,_xlpm.si,IF(_xlpm.f=0.25,AVERAGE(_xlpm.si,_xlpm.sh),AVERAGE(_xlpm.sh,1-_xlfn.POISSON.DIST(_xlpm.n+1,$D$10,TRUE)+0.5*_xlfn.POISSON.DIST(_xlpm.n+1,$D$10,FALSE))))))) -> 0.69717932 | C29: {=IF($B29="","",_xlfn.LET(_xlpm.l,$A29,_xlpm.lim,_xlfn.XLOOKUP(_xlpm.l,{0.5,0.75,1,1.25,1.5,1.75,2,2.25,2.5,2.75,3},{0.95,0.94,0.925,0.9125,0.9,0.88,0.86,0.84,0.82,0.8025,0.785}),IF($B29>=_xlpm.lim,"APROVADA",IF($B29>=_xlpm.lim-5%,"PRÓXIMA","ABAIXO"))))} -> ABAIXO | D29: PUSH com 3 gols
A30: Probabilidade ajustada pondera GREEN=100%, meio GREEN=75%, PUSH=50%, meio RED=25% e RED=0%.
A33: COMPARAÇÃO DE LINHAS — POISSON × BINOMIAL NEGATIVA
A34: Atualiza automaticamente para qualquer confronto selecionado em B5 e B6
A36: λ total | B36: =$D$10 -> 4.2 | C36: Variância usada | D36: =IF(OR(B36="",NOT(ISNUMBER(I36)),NOT(ISNUMBER(J36))),"",MAX(B36*1.05,AVERAGE(I36,J36))) -> 4.41 | E36: Modelo alternativo | F36: Binomial Negativa | G36: Diagnóstico | H36: =IF(D36="","",IF(D36>B36*1.15,"SUPERDISPERSÃO","PRÓXIMA DO POISSON")) -> PRÓXIMA DO POISSON | I36: {=_xlfn.LET(_xlpm.n,$B$5,_xlpm.c,SUMPRODUCT((TRIM(tblDados[Mandante])=_xlpm.n)*tblDados[Primeira_Ocorrencia])+SUMPRODUCT((TRIM(tblDados[Visitante])=_xlpm.n)*tblDados[Primeira_Ocorrencia]),_xlpm.s,SUMPRODUCT((TRIM(tblDados[Mandante])=_xlpm.n)*tblDados[Primeira_Ocorrencia]*(tblDados[GM_M]+tblDados[GS_M]))+SUMPRODUCT((TRIM(tblDados[Visitante])=_xlpm.n)*tblDados[Primeira_Ocorrencia]*(tblDados[GM_V]+tblDados[GS_V])),_xlpm.q,SUMPRODUCT((TRIM(tblDados[Mandante])=_xlpm.n)*tblDados[Primeira_Ocorrencia]*(tblDados[GM_M]+tblDados[GS_M])^2)+SUMPRODUCT((TRIM(tblDados[Visitante])=_xlpm.n)*tblDados[Primeira_Ocorrencia]*(tblDados[GM_V]+tblDados[GS_V])^2),IF(_xlpm.c>1,(_xlpm.q-_xlpm.s^2/_xlpm.c)/(_xlpm.c-1),$B$36))} -> 1.5378788 | J36: {=_xlfn.LET(_xlpm.n,$B$6,_xlpm.c,SUMPRODUCT((TRIM(tblDados[Mandante])=_xlpm.n)*tblDados[Primeira_Ocorrencia])+SUMPRODUCT((TRIM(tblDados[Visitante])=_xlpm.n)*tblDados[Primeira_Ocorrencia]),_xlpm.s,SUMPRODUCT((TRIM(tblDados[Mandante])=_xlpm.n)*tblDados[Primeira_Ocorrencia]*(tblDados[GM_M]+tblDados[GS_M]))+SUMPRODUCT((TRIM(tblDados[Visitante])=_xlpm.n)*tblDados[Primeira_Ocorrencia]*(tblDados[GM_V]+tblDados[GS_V])),_xlpm.q,SUMPRODUCT((TRIM(tblDados[Mandante])=_xlpm.n)*tblDados[Primeira_Ocorrencia]*(tblDados[GM_M]+tblDados[GS_M])^2)+SUMPRODUCT((TRIM(tblDados[Visitante])=_xlpm.n)*tblDados[Primeira_Ocorrencia]*(tblDados[GM_V]+tblDados[GS_V])^2),IF(_xlpm.c>1,(_xlpm.q-_xlpm.s^2/_xlpm.c)/(_xlpm.c-1),$B$36))} -> 4.6287879
A37: Amostra combinada | B37: {=SUMPRODUCT((TRIM(tblDados[Mandante])=$B$5)*tblDados[Primeira_Ocorrencia])+SUMPRODUCT((TRIM(tblDados[Visitante])=$B$5)*tblDados[Primeira_Ocorrencia])+SUMPRODUCT((TRIM(tblDados[Mandante])=$B$6)*tblDados[Primeira_Ocorrencia])+SUMPRODUCT((TRIM(tblDados[Visitante])=$B$6)*tblDados[Primeira_Ocorrencia])} -> 24 | C37: Parâmetro r | D37: =IF(OR(D36="",B36="",D36<=B36),"",B36^2/(D36-B36)) -> 84 | E37: Probabilidade p | F37: =IF(OR(D37="",B36=""),"",D37/(D37+B36)) -> 0.95238095 | G37: Critério | H37: 0.75
A39: Linha | B39: Green Poisson | C39: Sem Red Poisson | D39: Green Binomial Neg. | F39: Sem Red Binomial Neg. | G39: Green consenso | H39: Proteção consenso | I39: Leitura
A40: 0.5 | B40: =IF($B$36="","",1-_xlfn.POISSON.DIST(IF(ROUND(MOD($A40,1),2)=0.75,INT($A40)+1,INT($A40)),$B$36,TRUE)) -> 0.98500442 | C40: =IF($B$36="","",1-_xlfn.POISSON.DIST(IF(ROUND(MOD($A40,1),2)=0.5,INT($A40),IF(ROUND(MOD($A40,1),2)=0,INT($A40)-1,IF(ROUND(MOD($A40,1),2)=0.25,INT($A40)-1,INT($A40)))),$B$36,TRUE)) -> 0.98500442 | D40: =IF(OR($D$37="",$F$37=""),"",1-_xlfn.NEGBINOM.DIST(IF(ROUND(MOD($A40,1),2)=0.75,INT($A40)+1,INT($A40)),$D$37,$F$37,TRUE)) -> 0.98340035 | F40: =IF(OR($D$37="",$F$37=""),"",1-_xlfn.NEGBINOM.DIST(IF(ROUND(MOD($A40,1),2)=0.5,INT($A40),IF(ROUND(MOD($A40,1),2)=0,INT($A40)-1,IF(ROUND(MOD($A40,1),2)=0.25,INT($A40)-1,INT($A40)))),$D$37,$F$37,TRUE)) -> 0.98340035 | G40: =IF(OR(B40="",D40=""),"",MIN(B40,D40)) -> 0.98340035 | H40: =IF(OR(C40="",F40=""),"",MIN(C40,F40)) -> 0.98340035 | I40: =IF(G40="","",IF(G40>=75%,"GREEN ≥75%",IF(H40>=75%,"PROTEÇÃO ≥75%","ABAIXO"))) -> GREEN ≥75%
A41: 0.75 | B41: =IF($B$36="","",1-_xlfn.POISSON.DIST(IF(ROUND(MOD($A41,1),2)=0.75,INT($A41)+1,INT($A41)),$B$36,TRUE)) -> 0.922023 | C41: =IF($B$36="","",1-_xlfn.POISSON.DIST(IF(ROUND(MOD($A41,1),2)=0.5,INT($A41),IF(ROUND(MOD($A41,1),2)=0,INT($A41)-1,IF(ROUND(MOD($A41,1),2)=0.25,INT($A41)-1,INT($A41)))),$B$36,TRUE)) -> 0.98500442 | D41: =IF(OR($D$37="",$F$37=""),"",1-_xlfn.NEGBINOM.DIST(IF(ROUND(MOD($A41,1),2)=0.75,INT($A41)+1,INT($A41)),$D$37,$F$37,TRUE)) -> 0.91700176 | F41: =IF(OR($D$37="",$F$37=""),"",1-_xlfn.NEGBINOM.DIST(IF(ROUND(MOD($A41,1),2)=0.5,INT($A41),IF(ROUND(MOD($A41,1),2)=0,INT($A41)-1,IF(ROUND(MOD($A41,1),2)=0.25,INT($A41)-1,INT($A41)))),$D$37,$F$37,TRUE)) -> 0.98340035 | G41: =IF(OR(B41="",D41=""),"",MIN(B41,D41)) -> 0.91700176 | H41: =IF(OR(C41="",F41=""),"",MIN(C41,F41)) -> 0.98340035 | I41: =IF(G41="","",IF(G41>=75%,"GREEN ≥75%",IF(H41>=75%,"PROTEÇÃO ≥75%","ABAIXO"))) -> GREEN ≥75%
A42: 1 | B42: =IF($B$36="","",1-_xlfn.POISSON.DIST(IF(ROUND(MOD($A42,1),2)=0.75,INT($A42)+1,INT($A42)),$B$36,TRUE)) -> 0.922023 | C42: =IF($B$36="","",1-_xlfn.POISSON.DIST(IF(ROUND(MOD($A42,1),2)=0.5,INT($A42),IF(ROUND(MOD($A42,1),2)=0,INT($A42)-1,IF(ROUND(MOD($A42,1),2)=0.25,INT($A42)-1,INT($A42)))),$B$36,TRUE)) -> 0.98500442 | D42: =IF(OR($D$37="",$F$37=""),"",1-_xlfn.NEGBINOM.DIST(IF(ROUND(MOD($A42,1),2)=0.75,INT($A42)+1,INT($A42)),$D$37,$F$37,TRUE)) -> 0.91700176 | F42: =IF(OR($D$37="",$F$37=""),"",1-_xlfn.NEGBINOM.DIST(IF(ROUND(MOD($A42,1),2)=0.5,INT($A42),IF(ROUND(MOD($A42,1),2)=0,INT($A42)-1,IF(ROUND(MOD($A42,1),2)=0.25,INT($A42)-1,INT($A42)))),$D$37,$F$37,TRUE)) -> 0.98340035 | G42: =IF(OR(B42="",D42=""),"",MIN(B42,D42)) -> 0.91700176 | H42: =IF(OR(C42="",F42=""),"",MIN(C42,F42)) -> 0.98340035 | I42: =IF(G42="","",IF(G42>=75%,"GREEN ≥75%",IF(H42>=75%,"PROTEÇÃO ≥75%","ABAIXO"))) -> GREEN ≥75%
A43: 1.25 | B43: =IF($B$36="","",1-_xlfn.POISSON.DIST(IF(ROUND(MOD($A43,1),2)=0.75,INT($A43)+1,INT($A43)),$B$36,TRUE)) -> 0.922023 | C43: =IF($B$36="","",1-_xlfn.POISSON.DIST(IF(ROUND(MOD($A43,1),2)=0.5,INT($A43),IF(ROUND(MOD($A43,1),2)=0,INT($A43)-1,IF(ROUND(MOD($A43,1),2)=0.25,INT($A43)-1,INT($A43)))),$B$36,TRUE)) -> 0.98500442 | D43: =IF(OR($D$37="",$F$37=""),"",1-_xlfn.NEGBINOM.DIST(IF(ROUND(MOD($A43,1),2)=0.75,INT($A43)+1,INT($A43)),$D$37,$F$37,TRUE)) -> 0.91700176 | F43: =IF(OR($D$37="",$F$37=""),"",1-_xlfn.NEGBINOM.DIST(IF(ROUND(MOD($A43,1),2)=0.5,INT($A43),IF(ROUND(MOD($A43,1),2)=0,INT($A43)-1,IF(ROUND(MOD($A43,1),2)=0.25,INT($A43)-1,INT($A43)))),$D$37,$F$37,TRUE)) -> 0.98340035 | G43: =IF(OR(B43="",D43=""),"",MIN(B43,D43)) -> 0.91700176 | H43: =IF(OR(C43="",F43=""),"",MIN(C43,F43)) -> 0.98340035 | I43: =IF(G43="","",IF(G43>=75%,"GREEN ≥75%",IF(H43>=75%,"PROTEÇÃO ≥75%","ABAIXO"))) -> GREEN ≥75%
A44: 1.5 | B44: =IF($B$36="","",1-_xlfn.POISSON.DIST(IF(ROUND(MOD($A44,1),2)=0.75,INT($A44)+1,INT($A44)),$B$36,TRUE)) -> 0.922023 | C44: =IF($B$36="","",1-_xlfn.POISSON.DIST(IF(ROUND(MOD($A44,1),2)=0.5,INT($A44),IF(ROUND(MOD($A44,1),2)=0,INT($A44)-1,IF(ROUND(MOD($A44,1),2)=0.25,INT($A44)-1,INT($A44)))),$B$36,TRUE)) -> 0.922023 | D44: =IF(OR($D$37="",$F$37=""),"",1-_xlfn.NEGBINOM.DIST(IF(ROUND(MOD($A44,1),2)=0.75,INT($A44)+1,INT($A44)),$D$37,$F$37,TRUE)) -> 0.91700176 | F44: =IF(OR($D$37="",$F$37=""),"",1-_xlfn.NEGBINOM.DIST(IF(ROUND(MOD($A44,1),2)=0.5,INT($A44),IF(ROUND(MOD($A44,1),2)=0,INT($A44)-1,IF(ROUND(MOD($A44,1),2)=0.25,INT($A44)-1,INT($A44)))),$D$37,$F$37,TRUE)) -> 0.91700176 | G44: =IF(OR(B44="",D44=""),"",MIN(B44,D44)) -> 0.91700176 | H44: =IF(OR(C44="",F44=""),"",MIN(C44,F44)) -> 0.91700176 | I44: =IF(G44="","",IF(G44>=75%,"GREEN ≥75%",IF(H44>=75%,"PROTEÇÃO ≥75%","ABAIXO"))) -> GREEN ≥75%
A45: 1.75 | B45: =IF($B$36="","",1-_xlfn.POISSON.DIST(IF(ROUND(MOD($A45,1),2)=0.75,INT($A45)+1,INT($A45)),$B$36,TRUE)) -> 0.78976201 | C45: =IF($B$36="","",1-_xlfn.POISSON.DIST(IF(ROUND(MOD($A45,1),2)=0.5,INT($A45),IF(ROUND(MOD($A45,1),2)=0,INT($A45)-1,IF(ROUND(MOD($A45,1),2)=0.25,INT($A45)-1,INT($A45)))),$B$36,TRUE)) -> 0.922023 | D45: =IF(OR($D$37="",$F$37=""),"",1-_xlfn.NEGBINOM.DIST(IF(ROUND(MOD($A45,1),2)=0.75,INT($A45)+1,INT($A45)),$D$37,$F$37,TRUE)) -> 0.78262366 | F45: =IF(OR($D$37="",$F$37=""),"",1-_xlfn.NEGBINOM.DIST(IF(ROUND(MOD($A45,1),2)=0.5,INT($A45),IF(ROUND(MOD($A45,1),2)=0,INT($A45)-1,IF(ROUND(MOD($A45,1),2)=0.25,INT($A45)-1,INT($A45)))),$D$37,$F$37,TRUE)) -> 0.91700176 | G45: =IF(OR(B45="",D45=""),"",MIN(B45,D45)) -> 0.78262366 | H45: =IF(OR(C45="",F45=""),"",MIN(C45,F45)) -> 0.91700176 | I45: =IF(G45="","",IF(G45>=75%,"GREEN ≥75%",IF(H45>=75%,"PROTEÇÃO ≥75%","ABAIXO"))) -> GREEN ≥75%
A46: 2 | B46: =IF($B$36="","",1-_xlfn.POISSON.DIST(IF(ROUND(MOD($A46,1),2)=0.75,INT($A46)+1,INT($A46)),$B$36,TRUE)) -> 0.78976201 | C46: =IF($B$36="","",1-_xlfn.POISSON.DIST(IF(ROUND(MOD($A46,1),2)=0.5,INT($A46),IF(ROUND(MOD($A46,1),2)=0,INT($A46)-1,IF(ROUND(MOD($A46,1),2)=0.25,INT($A46)-1,INT($A46)))),$B$36,TRUE)) -> 0.922023 | D46: =IF(OR($D$37="",$F$37=""),"",1-_xlfn.NEGBINOM.DIST(IF(ROUND(MOD($A46,1),2)=0.75,INT($A46)+1,INT($A46)),$D$37,$F$37,TRUE)) -> 0.78262366 | F46: =IF(OR($D$37="",$F$37=""),"",1-_xlfn.NEGBINOM.DIST(IF(ROUND(MOD($A46,1),2)=0.5,INT($A46),IF(ROUND(MOD($A46,1),2)=0,INT($A46)-1,IF(ROUND(MOD($A46,1),2)=0.25,INT($A46)-1,INT($A46)))),$D$37,$F$37,TRUE)) -> 0.91700176 | G46: =IF(OR(B46="",D46=""),"",MIN(B46,D46)) -> 0.78262366 | H46: =IF(OR(C46="",F46=""),"",MIN(C46,F46)) -> 0.91700176 | I46: =IF(G46="","",IF(G46>=75%,"GREEN ≥75%",IF(H46>=75%,"PROTEÇÃO ≥75%","ABAIXO"))) -> GREEN ≥75%
A47: 2.25 | B47: =IF($B$36="","",1-_xlfn.POISSON.DIST(IF(ROUND(MOD($A47,1),2)=0.75,INT($A47)+1,INT($A47)),$B$36,TRUE)) -> 0.78976201 | C47: =IF($B$36="","",1-_xlfn.POISSON.DIST(IF(ROUND(MOD($A47,1),2)=0.5,INT($A47),IF(ROUND(MOD($A47,1),2)=0,INT($A47)-1,IF(ROUND(MOD($A47,1),2)=0.25,INT($A47)-1,INT($A47)))),$B$36,TRUE)) -> 0.922023 | D47: =IF(OR($D$37="",$F$37=""),"",1-_xlfn.NEGBINOM.DIST(IF(ROUND(MOD($A47,1),2)=0.75,INT($A47)+1,INT($A47)),$D$37,$F$37,TRUE)) -> 0.78262366 | F47: =IF(OR($D$37="",$F$37=""),"",1-_xlfn.NEGBINOM.DIST(IF(ROUND(MOD($A47,1),2)=0.5,INT($A47),IF(ROUND(MOD($A47,1),2)=0,INT($A47)-1,IF(ROUND(MOD($A47,1),2)=0.25,INT($A47)-1,INT($A47)))),$D$37,$F$37,TRUE)) -> 0.91700176 | G47: =IF(OR(B47="",D47=""),"",MIN(B47,D47)) -> 0.78262366 | H47: =IF(OR(C47="",F47=""),"",MIN(C47,F47)) -> 0.91700176 | I47: =IF(G47="","",IF(G47>=75%,"GREEN ≥75%",IF(H47>=75%,"PROTEÇÃO ≥75%","ABAIXO"))) -> GREEN ≥75%
A48: 2.5 | B48: =IF($B$36="","",1-_xlfn.POISSON.DIST(IF(ROUND(MOD($A48,1),2)=0.75,INT($A48)+1,INT($A48)),$B$36,TRUE)) -> 0.78976201 | C48: =IF($B$36="","",1-_xlfn.POISSON.DIST(IF(ROUND(MOD($A48,1),2)=0.5,INT($A48),IF(ROUND(MOD($A48,1),2)=0,INT($A48)-1,IF(ROUND(MOD($A48,1),2)=0.25,INT($A48)-1,INT($A48)))),$B$36,TRUE)) -> 0.78976201 | D48: =IF(OR($D$37="",$F$37=""),"",1-_xlfn.NEGBINOM.DIST(IF(ROUND(MOD($A48,1),2)=0.75,INT($A48)+1,INT($A48)),$D$37,$F$37,TRUE)) -> 0.78262366 | F48: =IF(OR($D$37="",$F$37=""),"",1-_xlfn.NEGBINOM.DIST(IF(ROUND(MOD($A48,1),2)=0.5,INT($A48),IF(ROUND(MOD($A48,1),2)=0,INT($A48)-1,IF(ROUND(MOD($A48,1),2)=0.25,INT($A48)-1,INT($A48)))),$D$37,$F$37,TRUE)) -> 0.78262366 | G48: =IF(OR(B48="",D48=""),"",MIN(B48,D48)) -> 0.78262366 | H48: =IF(OR(C48="",F48=""),"",MIN(C48,F48)) -> 0.78262366 | I48: =IF(G48="","",IF(G48>=75%,"GREEN ≥75%",IF(H48>=75%,"PROTEÇÃO ≥75%","ABAIXO"))) -> GREEN ≥75%
A49: 2.75 | B49: =IF($B$36="","",1-_xlfn.POISSON.DIST(IF(ROUND(MOD($A49,1),2)=0.75,INT($A49)+1,INT($A49)),$B$36,TRUE)) -> 0.60459663 | C49: =IF($B$36="","",1-_xlfn.POISSON.DIST(IF(ROUND(MOD($A49,1),2)=0.5,INT($A49),IF(ROUND(MOD($A49,1),2)=0,INT($A49)-1,IF(ROUND(MOD($A49,1),2)=0.25,INT($A49)-1,INT($A49)))),$B$36,TRUE)) -> 0.78976201 | D49: =IF(OR($D$37="",$F$37=""),"",1-_xlfn.NEGBINOM.DIST(IF(ROUND(MOD($A49,1),2)=0.75,INT($A49)+1,INT($A49)),$D$37,$F$37,TRUE)) -> 0.59918688 | F49: =IF(OR($D$37="",$F$37=""),"",1-_xlfn.NEGBINOM.DIST(IF(ROUND(MOD($A49,1),2)=0.5,INT($A49),IF(ROUND(MOD($A49,1),2)=0,INT($A49)-1,IF(ROUND(MOD($A49,1),2)=0.25,INT($A49)-1,INT($A49)))),$D$37,$F$37,TRUE)) -> 0.78262366 | G49: =IF(OR(B49="",D49=""),"",MIN(B49,D49)) -> 0.59918688 | H49: =IF(OR(C49="",F49=""),"",MIN(C49,F49)) -> 0.78262366 | I49: =IF(G49="","",IF(G49>=75%,"GREEN ≥75%",IF(H49>=75%,"PROTEÇÃO ≥75%","ABAIXO"))) -> PROTEÇÃO ≥75%
A50: 3 | B50: =IF($B$36="","",1-_xlfn.POISSON.DIST(IF(ROUND(MOD($A50,1),2)=0.75,INT($A50)+1,INT($A50)),$B$36,TRUE)) -> 0.60459663 | C50: =IF($B$36="","",1-_xlfn.POISSON.DIST(IF(ROUND(MOD($A50,1),2)=0.5,INT($A50),IF(ROUND(MOD($A50,1),2)=0,INT($A50)-1,IF(ROUND(MOD($A50,1),2)=0.25,INT($A50)-1,INT($A50)))),$B$36,TRUE)) -> 0.78976201 | D50: =IF(OR($D$37="",$F$37=""),"",1-_xlfn.NEGBINOM.DIST(IF(ROUND(MOD($A50,1),2)=0.75,INT($A50)+1,INT($A50)),$D$37,$F$37,TRUE)) -> 0.59918688 | F50: =IF(OR($D$37="",$F$37=""),"",1-_xlfn.NEGBINOM.DIST(IF(ROUND(MOD($A50,1),2)=0.5,INT($A50),IF(ROUND(MOD($A50,1),2)=0,INT($A50)-1,IF(ROUND(MOD($A50,1),2)=0.25,INT($A50)-1,INT($A50)))),$D$37,$F$37,TRUE)) -> 0.78262366 | G50: =IF(OR(B50="",D50=""),"",MIN(B50,D50)) -> 0.59918688 | H50: =IF(OR(C50="",F50=""),"",MIN(C50,F50)) -> 0.78262366 | I50: =IF(G50="","",IF(G50>=75%,"GREEN ≥75%",IF(H50>=75%,"PROTEÇÃO ≥75%","ABAIXO"))) -> PROTEÇÃO ≥75%
A51: Faixa ≥75% | B51: Green até | C51: {=IFERROR(MAX(_xlfn._xlws.FILTER($A$40:$A$50,$G$40:$G$50>=75%)),"")} -> 2.5 | F51: Proteção até | G51: {=IFERROR(MAX(_xlfn._xlws.FILTER($A$40:$A$50,$H$40:$H$50>=75%)),"")} -> 3 | H51: Odds entram depois
A53: MOTOR TURBO — PERFIL EXPLOSIVO E REGIME DA LIGA
A54: O V1 permanece intacto nas linhas 8–51. O V2 abaixo amplia a leitura quando teto empírico e dispersão confirmam potencial de cauda.
A56: Métrica | B56: Valor | C56: Peso / referência | D56: Interpretação | F56: Regra da liga | G56: Green mínimo | H56: Proteção mínima | I56: V1 | J56: V2 Turbo
A57: Frequência de 1+ gol | B57: =IFERROR(AVERAGE(INDEX(Equipes!$K$2:$K$1000,MATCH($B$5,Equipes!$A$2:$A$1000,0)),INDEX(Equipes!$K$2:$K$1000,MATCH($B$6,Equipes!$A$2:$A$1000,0))),"") -> 1 | C57: Base empírica | D57: =IF(B57="","",IF(B57>=95%,"Muito segura",IF(B57>=90%,"Forte","Moderada"))) -> Muito segura | F57: Liga fechada (<2,60) | G57: 0.8 | H57: 0.9 | I57: =$G$15 -> ANALISAR OVER 2,50 | J57: =IF($J$78="","Aguardando",$J$78) -> MANTER V1 — OVER 2,50
A58: Frequência de 2+ gols | B58: =IFERROR(AVERAGE(INDEX(Equipes!$L$2:$L$1000,MATCH($B$5,Equipes!$A$2:$A$1000,0)),INDEX(Equipes!$L$2:$L$1000,MATCH($B$6,Equipes!$A$2:$A$1000,0))),"") -> 0.875 | C58: Base empírica | D58: =IF(B58="","",IF(B58>=90%,"Elite 2+",IF(B58>=80%,"Forte 2+","Moderada"))) -> Forte 2+ | F58: Liga neutra (2,60–3,19) | G58: 0.75 | H58: 0.85 | I58: Consenso conservador | J58: Mistura adaptativa
A59: Frequência de 3+ gols | B59: =IFERROR(AVERAGE(INDEX(Equipes!$M$2:$M$1000,MATCH($B$5,Equipes!$A$2:$A$1000,0)),INDEX(Equipes!$M$2:$M$1000,MATCH($B$6,Equipes!$A$2:$A$1000,0))),"") -> 0.58333333 | C59: Base empírica | D59: =IF(B59="","",IF(B59>=80%,"Teto alto",IF(B59>=65%,"Teto médio","Teto limitado"))) -> Teto limitado | F59: Liga aberta (≥3,20) | G59: 0.7 | H59: 0.82 | I59: MIN(Poisson; BN) | J59: V1 + teto + dominância + radar
A60: Frequência de 4+ gols | B60: =IFERROR(AVERAGE(INDEX(Equipes!$N$2:$N$1000,MATCH($B$5,Equipes!$A$2:$A$1000,0)),INDEX(Equipes!$N$2:$N$1000,MATCH($B$6,Equipes!$A$2:$A$1000,0))),"") -> 0.41666667 | C60: Base empírica | D60: =IF(B60="","",IF(B60>=65%,"Explosiva",IF(B60>=45%,"Cauda presente","Cauda fraca"))) -> Cauda fraca | F60: Regra ativa | G60: =IF($B$62<1.04,80%,IF($B$62<1.28,75%,70%)) -> 0.75 | H60: =IF($B$62<1.04,90%,IF($B$62<1.28,85%,82%)) -> 0.85 | I60: Linha base | J60: =$H$13 -> 2.5
A61: Dispersão média | B61: =IFERROR(AVERAGE(INDEX(Equipes!$Q$2:$Q$1000,MATCH($B$5,Equipes!$A$2:$A$1000,0)),INDEX(Equipes!$Q$2:$Q$1000,MATCH($B$6,Equipes!$A$2:$A$1000,0))),"") -> 1.0777044 | C61: 1,00 = Poisson | D61: =IF(B61="","",IF(B61>=1.5,"Superdispersão forte",IF(B61>=1.1,"Superdispersão","Próxima do Poisson"))) -> Próxima do Poisson
A62: Fator da liga | B62: =IFERROR(_xlfn.LET(_xlpm.x,_xlfn.XLOOKUP($E$5,Ligas!$A$2:$A$100,Ligas!$E$2:$E$100),IF(ISNUMBER(_xlpm.x),_xlpm.x/2.5,1)),1) -> 1.2371134 | C62: 1,00 = liga neutra | D62: =IF(B62="","",IF(B62>=1.25,"Liga aberta",IF(B62<0.95,"Liga fechada","Liga neutra"))) -> Liga neutra | F62: RADAR OVER | G62: Mandante | H62: Visitante | I62: Bônus V2 | J62: Leitura
A63: Peso Turbo | B63: =IF(OR(B59="",B60="",B61=""),"",MIN(65%,MAX(15%,15%+25%*MAX(0,MIN(1,(B61-1)/1.5))+15%*MAX(0,MIN(1,(B62-0.9)/0.5))+10%*B59+10%*B60))) -> 0.36408475 | C63: 15% a 65% | D63: =IF(B63="","",IF(B63>=50%,"Turbo alto",IF(B63>=30%,"Turbo moderado","Turbo baixo"))) -> Turbo moderado | F63: Over 3 — 4+ gols | G63: =IFERROR(_xlfn.XLOOKUP($B$5,'Radar Over'!$A$16:$A$30,'Radar Over'!$K$16:$K$30),"FORA") -> FORA | H63: =IFERROR(_xlfn.XLOOKUP($B$6,'Radar Over'!$A$16:$A$30,'Radar Over'!$K$16:$K$30),"FORA") -> FORA | I63: =MIN(12%,IF(COUNTIF(G63:H63,"ELITE")>0,8%,IF(COUNTIF(G63:H63,"FORTE")>0,4%,0%))+IF(COUNTIF(G63:H63,"ELITE")=2,4%,IF(AND(COUNTIF(G63:H63,"ELITE")=1,COUNTIF(G63:H63,"FORTE")=1),2%,0%))) -> 0 | J63: =IF(I63=0,"Sem confirmação",IF(I63>=8%,"Radar alto teto","Radar parcial")) -> Sem confirmação
A64: Dominância unilateral | B64: =IFERROR(_xlfn.LET(_xlpm.tresM,INDEX(Equipes!$M$2:$M$1000,MATCH($B$5,Equipes!$A$2:$A$1000,0)),_xlpm.tresV,INDEX(Equipes!$M$2:$M$1000,MATCH($B$6,Equipes!$A$2:$A$1000,0)),_xlpm.quatroM,INDEX(Equipes!$N$2:$N$1000,MATCH($B$5,Equipes!$A$2:$A$1000,0)),_xlpm.quatroV,INDEX(Equipes!$N$2:$N$1000,MATCH($B$6,Equipes!$A$2:$A$1000,0)),_xlpm.dispM,INDEX(Equipes!$Q$2:$Q$1000,MATCH($B$5,Equipes!$A$2:$A$1000,0)),_xlpm.dispV,INDEX(Equipes!$Q$2:$Q$1000,MATCH($B$6,Equipes!$A$2:$A$1000,0)),_xlpm.difTeto,45%*(MAX(_xlpm.tresM,_xlpm.tresV)-AVERAGE(_xlpm.tresM,_xlpm.tresV))+35%*(MAX(_xlpm.quatroM,_xlpm.quatroV)-AVERAGE(_xlpm.quatroM,_xlpm.quatroV)),_xlpm.bonusDisp,MAX(0,MAX(_xlpm.dispM,_xlpm.dispV)-1)*4%,MIN(20%,MAX(0,_xlpm.difTeto+_xlpm.bonusDisp))),"") -> 0.15068217 | C64: =IF(B64="","",IF(INDEX(Equipes!$N$2:$N$1000,MATCH($B$5,Equipes!$A$2:$A$1000,0))>=INDEX(Equipes!$N$2:$N$1000,MATCH($B$6,Equipes!$A$2:$A$1000,0)),$B$5,$B$6)) -> IFK Göteborg | D64: =IF(B64="","",IF(B64>=12%,"Dominância forte",IF(B64>=6%,"Dominância moderada","Sem dominância material"))) -> Dominância forte | F64: Over 2 — 3+ gols | G64: =IFERROR(_xlfn.XLOOKUP($B$5,'Radar Over'!$A$34:$A$48,'Radar Over'!$K$34:$K$48),"FORA") -> FORA | H64: =IFERROR(_xlfn.XLOOKUP($B$6,'Radar Over'!$A$34:$A$48,'Radar Over'!$K$34:$K$48),"FORA") -> FORA | I64: =MIN(10%,IF(COUNTIF(G64:H64,"ELITE")>0,6%,IF(COUNTIF(G64:H64,"FORTE")>0,3%,0%))+IF(COUNTIF(G64:H64,"ELITE")=2,4%,IF(AND(COUNTIF(G64:H64,"ELITE")=1,COUNTIF(G64:H64,"FORTE")=1),2%,0%))) -> 0 | J64: =IF(I64=0,"Sem confirmação",IF(I64>=6%,"Radar ofensivo","Radar parcial")) -> Sem confirmação
A65: COMPARAÇÃO V1 × VERSÃO TURBO POR LINHA
A66: Linha | B66: V1 Green | C66: Empírico Green | D66: Turbo Green | E66: V1 Proteção | F66: Empírico Proteção | G66: Turbo Proteção | H66: Δ Turbo | I66: Status | J66: Linha elegível
A67: =A40 -> 0.5 | B67: =G40 -> 0.98340035 | C67: =IF(A67<=0.5,$B$57,IF(A67<=1.5,$B$58,IF(A67<=2.5,MIN(100%,$B$59+$B$64+$I$64),MIN(100%,$B$60+$B$64+$I$63)))) -> 1 | D67: =IF(OR(B67="",C67=""),"",B67*(1-$B$63)+C67*$B$63) -> 0.98944403 | E67: =H40 -> 0.98340035 | F67: =IF(A67<1.5,$B$57,IF(A67<2.5,$B$58,MIN(100%,$B$59+$B$64+$I$64))) -> 1 | G67: =IF(OR(E67="",F67=""),"",MAX(D67,E67*(1-$B$63)+F67*$B$63)) -> 0.98944403 | H67: =IF(OR(D67="",B67=""),"",D67-B67) -> 0.0060436786 | I67: =IF(D67>=$G$60,IF(G67>=$H$60,"APROVADA TURBO","GREEN SEM PROTEÇÃO"),IF(G67>=$H$60,"SÓ PROTEÇÃO","ABAIXO")) -> APROVADA TURBO | J67: =IF(AND(I67="APROVADA TURBO",A67>$H$13),A67,"")
A68: =A41 -> 0.75 | B68: =G41 -> 0.91700176 | C68: =IF(A68<=0.5,$B$57,IF(A68<=1.5,$B$58,IF(A68<=2.5,MIN(100%,$B$59+$B$64+$I$64),MIN(100%,$B$60+$B$64+$I$63)))) -> 0.875 | D68: =IF(OR(B68="",C68=""),"",B68*(1-$B$63)+C68*$B$63) -> 0.90170956 | E68: =H41 -> 0.98340035 | F68: =IF(A68<1.5,$B$57,IF(A68<2.5,$B$58,MIN(100%,$B$59+$B$64+$I$64))) -> 1 | G68: =IF(OR(E68="",F68=""),"",MAX(D68,E68*(1-$B$63)+F68*$B$63)) -> 0.98944403 | H68: =IF(OR(D68="",B68=""),"",D68-B68) -> -0.0152922 | I68: =IF(D68>=$G$60,IF(G68>=$H$60,"APROVADA TURBO","GREEN SEM PROTEÇÃO"),IF(G68>=$H$60,"SÓ PROTEÇÃO","ABAIXO")) -> APROVADA TURBO | J68: =IF(AND(I68="APROVADA TURBO",A68>$H$13),A68,"")
A69: =A42 -> 1 | B69: =G42 -> 0.91700176 | C69: =IF(A69<=0.5,$B$57,IF(A69<=1.5,$B$58,IF(A69<=2.5,MIN(100%,$B$59+$B$64+$I$64),MIN(100%,$B$60+$B$64+$I$63)))) -> 0.875 | D69: =IF(OR(B69="",C69=""),"",B69*(1-$B$63)+C69*$B$63) -> 0.90170956 | E69: =H42 -> 0.98340035 | F69: =IF(A69<1.5,$B$57,IF(A69<2.5,$B$58,MIN(100%,$B$59+$B$64+$I$64))) -> 1 | G69: =IF(OR(E69="",F69=""),"",MAX(D69,E69*(1-$B$63)+F69*$B$63)) -> 0.98944403 | H69: =IF(OR(D69="",B69=""),"",D69-B69) -> -0.0152922 | I69: =IF(D69>=$G$60,IF(G69>=$H$60,"APROVADA TURBO","GREEN SEM PROTEÇÃO"),IF(G69>=$H$60,"SÓ PROTEÇÃO","ABAIXO")) -> APROVADA TURBO | J69: =IF(AND(I69="APROVADA TURBO",A69>$H$13),A69,"")
A70: =A43 -> 1.25 | B70: =G43 -> 0.91700176 | C70: =IF(A70<=0.5,$B$57,IF(A70<=1.5,$B$58,IF(A70<=2.5,MIN(100%,$B$59+$B$64+$I$64),MIN(100%,$B$60+$B$64+$I$63)))) -> 0.875 | D70: =IF(OR(B70="",C70=""),"",B70*(1-$B$63)+C70*$B$63) -> 0.90170956 | E70: =H43 -> 0.98340035 | F70: =IF(A70<1.5,$B$57,IF(A70<2.5,$B$58,MIN(100%,$B$59+$B$64+$I$64))) -> 1 | G70: =IF(OR(E70="",F70=""),"",MAX(D70,E70*(1-$B$63)+F70*$B$63)) -> 0.98944403 | H70: =IF(OR(D70="",B70=""),"",D70-B70) -> -0.0152922 | I70: =IF(D70>=$G$60,IF(G70>=$H$60,"APROVADA TURBO","GREEN SEM PROTEÇÃO"),IF(G70>=$H$60,"SÓ PROTEÇÃO","ABAIXO")) -> APROVADA TURBO | J70: =IF(AND(I70="APROVADA TURBO",A70>$H$13),A70,"")
A71: =A44 -> 1.5 | B71: =G44 -> 0.91700176 | C71: =IF(A71<=0.5,$B$57,IF(A71<=1.5,$B$58,IF(A71<=2.5,MIN(100%,$B$59+$B$64+$I$64),MIN(100%,$B$60+$B$64+$I$63)))) -> 0.875 | D71: =IF(OR(B71="",C71=""),"",B71*(1-$B$63)+C71*$B$63) -> 0.90170956 | E71: =H44 -> 0.91700176 | F71: =IF(A71<1.5,$B$57,IF(A71<2.5,$B$58,MIN(100%,$B$59+$B$64+$I$64))) -> 0.875 | G71: =IF(OR(E71="",F71=""),"",MAX(D71,E71*(1-$B$63)+F71*$B$63)) -> 0.90170956 | H71: =IF(OR(D71="",B71=""),"",D71-B71) -> -0.0152922 | I71: =IF(D71>=$G$60,IF(G71>=$H$60,"APROVADA TURBO","GREEN SEM PROTEÇÃO"),IF(G71>=$H$60,"SÓ PROTEÇÃO","ABAIXO")) -> APROVADA TURBO | J71: =IF(AND(I71="APROVADA TURBO",A71>$H$13),A71,"")
A72: =A45 -> 1.75 | B72: =G45 -> 0.78262366 | C72: =IF(A72<=0.5,$B$57,IF(A72<=1.5,$B$58,IF(A72<=2.5,MIN(100%,$B$59+$B$64+$I$64),MIN(100%,$B$60+$B$64+$I$63)))) -> 0.7340155 | D72: =IF(OR(B72="",C72=""),"",B72*(1-$B$63)+C72*$B$63) -> 0.76492617 | E72: =H45 -> 0.91700176 | F72: =IF(A72<1.5,$B$57,IF(A72<2.5,$B$58,MIN(100%,$B$59+$B$64+$I$64))) -> 0.875 | G72: =IF(OR(E72="",F72=""),"",MAX(D72,E72*(1-$B$63)+F72*$B$63)) -> 0.90170956 | H72: =IF(OR(D72="",B72=""),"",D72-B72) -> -0.017697488 | I72: =IF(D72>=$G$60,IF(G72>=$H$60,"APROVADA TURBO","GREEN SEM PROTEÇÃO"),IF(G72>=$H$60,"SÓ PROTEÇÃO","ABAIXO")) -> APROVADA TURBO | J72: =IF(AND(I72="APROVADA TURBO",A72>$H$13),A72,"")
A73: =A46 -> 2 | B73: =G46 -> 0.78262366 | C73: =IF(A73<=0.5,$B$57,IF(A73<=1.5,$B$58,IF(A73<=2.5,MIN(100%,$B$59+$B$64+$I$64),MIN(100%,$B$60+$B$64+$I$63)))) -> 0.7340155 | D73: =IF(OR(B73="",C73=""),"",B73*(1-$B$63)+C73*$B$63) -> 0.76492617 | E73: =H46 -> 0.91700176 | F73: =IF(A73<1.5,$B$57,IF(A73<2.5,$B$58,MIN(100%,$B$59+$B$64+$I$64))) -> 0.875 | G73: =IF(OR(E73="",F73=""),"",MAX(D73,E73*(1-$B$63)+F73*$B$63)) -> 0.90170956 | H73: =IF(OR(D73="",B73=""),"",D73-B73) -> -0.017697488 | I73: =IF(D73>=$G$60,IF(G73>=$H$60,"APROVADA TURBO","GREEN SEM PROTEÇÃO"),IF(G73>=$H$60,"SÓ PROTEÇÃO","ABAIXO")) -> APROVADA TURBO | J73: =IF(AND(I73="APROVADA TURBO",A73>$H$13),A73,"")
A74: =A47 -> 2.25 | B74: =G47 -> 0.78262366 | C74: =IF(A74<=0.5,$B$57,IF(A74<=1.5,$B$58,IF(A74<=2.5,MIN(100%,$B$59+$B$64+$I$64),MIN(100%,$B$60+$B$64+$I$63)))) -> 0.7340155 | D74: =IF(OR(B74="",C74=""),"",B74*(1-$B$63)+C74*$B$63) -> 0.76492617 | E74: =H47 -> 0.91700176 | F74: =IF(A74<1.5,$B$57,IF(A74<2.5,$B$58,MIN(100%,$B$59+$B$64+$I$64))) -> 0.875 | G74: =IF(OR(E74="",F74=""),"",MAX(D74,E74*(1-$B$63)+F74*$B$63)) -> 0.90170956 | H74: =IF(OR(D74="",B74=""),"",D74-B74) -> -0.017697488 | I74: =IF(D74>=$G$60,IF(G74>=$H$60,"APROVADA TURBO","GREEN SEM PROTEÇÃO"),IF(G74>=$H$60,"SÓ PROTEÇÃO","ABAIXO")) -> APROVADA TURBO | J74: =IF(AND(I74="APROVADA TURBO",A74>$H$13),A74,"")
A75: =A48 -> 2.5 | B75: =G48 -> 0.78262366 | C75: =IF(A75<=0.5,$B$57,IF(A75<=1.5,$B$58,IF(A75<=2.5,MIN(100%,$B$59+$B$64+$I$64),MIN(100%,$B$60+$B$64+$I$63)))) -> 0.7340155 | D75: =IF(OR(B75="",C75=""),"",B75*(1-$B$63)+C75*$B$63) -> 0.76492617 | E75: =H48 -> 0.78262366 | F75: =IF(A75<1.5,$B$57,IF(A75<2.5,$B$58,MIN(100%,$B$59+$B$64+$I$64))) -> 0.7340155 | G75: =IF(OR(E75="",F75=""),"",MAX(D75,E75*(1-$B$63)+F75*$B$63)) -> 0.76492617 | H75: =IF(OR(D75="",B75=""),"",D75-B75) -> -0.017697488 | I75: =IF(D75>=$G$60,IF(G75>=$H$60,"APROVADA TURBO","GREEN SEM PROTEÇÃO"),IF(G75>=$H$60,"SÓ PROTEÇÃO","ABAIXO")) -> GREEN SEM PROTEÇÃO | J75: =IF(AND(I75="APROVADA TURBO",A75>$H$13),A75,"")
A76: =A49 -> 2.75 | B76: =G49 -> 0.59918688 | C76: =IF(A76<=0.5,$B$57,IF(A76<=1.5,$B$58,IF(A76<=2.5,MIN(100%,$B$59+$B$64+$I$64),MIN(100%,$B$60+$B$64+$I$63)))) -> 0.56734884 | D76: =IF(OR(B76="",C76=""),"",B76*(1-$B$63)+C76*$B$63) -> 0.58759514 | E76: =H49 -> 0.78262366 | F76: =IF(A76<1.5,$B$57,IF(A76<2.5,$B$58,MIN(100%,$B$59+$B$64+$I$64))) -> 0.7340155 | G76: =IF(OR(E76="",F76=""),"",MAX(D76,E76*(1-$B$63)+F76*$B$63)) -> 0.76492617 | H76: =IF(OR(D76="",B76=""),"",D76-B76) -> -0.011591747 | I76: =IF(D76>=$G$60,IF(G76>=$H$60,"APROVADA TURBO","GREEN SEM PROTEÇÃO"),IF(G76>=$H$60,"SÓ PROTEÇÃO","ABAIXO")) -> ABAIXO | J76: =IF(AND(I76="APROVADA TURBO",A76>$H$13),A76,"")
A77: =A50 -> 3 | B77: =G50 -> 0.59918688 | C77: =IF(A77<=0.5,$B$57,IF(A77<=1.5,$B$58,IF(A77<=2.5,MIN(100%,$B$59+$B$64+$I$64),MIN(100%,$B$60+$B$64+$I$63)))) -> 0.56734884 | D77: =IF(OR(B77="",C77=""),"",B77*(1-$B$63)+C77*$B$63) -> 0.58759514 | E77: =H50 -> 0.78262366 | F77: =IF(A77<1.5,$B$57,IF(A77<2.5,$B$58,MIN(100%,$B$59+$B$64+$I$64))) -> 0.7340155 | G77: =IF(OR(E77="",F77=""),"",MAX(D77,E77*(1-$B$63)+F77*$B$63)) -> 0.76492617 | H77: =IF(OR(D77="",B77=""),"",D77-B77) -> -0.011591747 | I77: =IF(D77>=$G$60,IF(G77>=$H$60,"APROVADA TURBO","GREEN SEM PROTEÇÃO"),IF(G77>=$H$60,"SÓ PROTEÇÃO","ABAIXO")) -> ABAIXO | J77: =IF(AND(I77="APROVADA TURBO",A77>$H$13),A77,"")
A78: ORIENTAÇÃO MODELO 02 — maior linha acima do Modelo 01 confirmada por Green, proteção, explosividade e Radar Over | J78: {=_xlfn.LET(_xlpm.x,IFERROR(MAX(_xlfn._xlws.FILTER($J$67:$J$77,$J$67:$J$77<>"")),0),IF(_xlpm.x=0,"MANTER V1 — OVER "&FIXED($H$13,2,FALSE),"TURBO — ANALISAR OVER "&FIXED(_xlpm.x,2,FALSE)))} -> MANTER V1 — OVER 2,50

Sheet Prova Real
A1: PROVA REAL — DIAGNÓSTICO ROBUSTO DA PARTIDA
A2: Condição casa/fora · recência · distribuição empírica · convergência dos modelos · prioridade: acerto
A4: SELEÇÃO E CONTEXTO
A5: Mandante | B5: ='Modelo 01'!B5 -> Degerfors IF | D5: País — Liga | E5: ='Modelo 01'!E5 -> SWE - Allsvenskan | G5: Histórico | H5: ='Modelo 01'!H5 -> ✓ Histórico disponível
A6: Visitante | B6: ='Modelo 01'!B6 -> IFK Göteborg | D6: País — Liga | E6: ='Modelo 01'!E6 -> SWE - Allsvenskan | G6: Histórico | H6: ='Modelo 01'!H6 -> ✓ Histórico disponível
A8: CONDIÇÃO ESPECÍFICA — MANDANTE EM CASA × VISITANTE FORA | F8: CONVERGÊNCIA DO RISCO DE 0 x 0
A9: Métrica | B9: Mandante em casa | C9: Visitante fora | D9: Leitura combinada | F9: Indicador | G9: Risco | H9: Interpretação
A10: Jogos na condição | B10: =COUNTIFS(tblDados[Mandante],$B$5,tblDados[Janela_12_Mandante],1) -> 5 | C10: =COUNTIFS(tblDados[Visitante],$B$6,tblDados[Janela_12_Visitante],1) -> 5 | D10: =MIN(B10,C10) -> 5 | F10: Poisson direto | G10: =IFERROR(EXP(-'Modelo 01'!D10),0) -> 0.014995577 | H10: =IF(G10>10%,"Alto",IF(G10>7.5%,"Moderado","Baixo")) -> Baixo
A11: Gols marcados / jogo | B11: =IFERROR(SUMIFS(tblDados[GM_M],tblDados[Mandante],$B$5,tblDados[Janela_12_Mandante],1)/B10,0) -> 0.8 | C11: =IFERROR(SUMIFS(tblDados[GM_V],tblDados[Visitante],$B$6,tblDados[Janela_12_Visitante],1)/C10,0) -> 1.8 | D11: =AVERAGE(B11,C11) -> 1.3 | F11: Conservador (pior modelo) | G11: =IFERROR(1-'Modelo 01'!H40,0) -> 0.016599648 | H11: =IF(G11>10%,"Alto",IF(G11>7.5%,"Moderado","Baixo")) -> Baixo
A12: Gols sofridos / jogo | B12: =IFERROR(SUMIFS(tblDados[GS_M],tblDados[Mandante],$B$5,tblDados[Janela_12_Mandante],1)/B10,0) -> 1.8 | C12: =IFERROR(SUMIFS(tblDados[GS_V],tblDados[Visitante],$B$6,tblDados[Janela_12_Visitante],1)/C10,0) -> 4 | D12: =AVERAGE(B12,C12) -> 2.9 | F12: Empírico mandante/casa | G12: =B14 -> 0 | H12: =B10&" jogos na condição" -> 5 jogos na condição
A13: Gols totais / jogo | B13: =IFERROR((SUMIFS(tblDados[GM_M],tblDados[Mandante],$B$5,tblDados[Janela_12_Mandante],1)+SUMIFS(tblDados[GS_M],tblDados[Mandante],$B$5,tblDados[Janela_12_Mandante],1))/B10,0) -> 2.6 | C13: =IFERROR((SUMIFS(tblDados[GM_V],tblDados[Visitante],$B$6,tblDados[Janela_12_Visitante],1)+SUMIFS(tblDados[GS_V],tblDados[Visitante],$B$6,tblDados[Janela_12_Visitante],1))/C10,0) -> 5.8 | D13: =AVERAGE(B13,C13) -> 4.2 | F13: Empírico visitante/fora | G13: =C14 -> 0 | H13: =C10&" jogos na condição" -> 5 jogos na condição
A14: 0 x 0 | B14: =IFERROR(COUNTIFS(tblDados[Mandante],$B$5,tblDados[GM_M],0,tblDados[GS_M],0,tblDados[Janela_12_Mandante],1)/B10,0) -> 0 | C14: =IFERROR(COUNTIFS(tblDados[Visitante],$B$6,tblDados[GM_V],0,tblDados[GS_V],0,tblDados[Janela_12_Visitante],1)/C10,0) -> 0 | D14: =AVERAGE(B14,C14) -> 0 | F14: Taxa da liga | G14: =IFERROR(COUNTIFS(tblDados[País],LEFT($E$5,3),tblDados[Liga],TRIM(MID($E$5,7,99)),tblDados[GM_M],0,tblDados[GS_M],0,tblDados[Janela_12_Liga],1)/COUNTIFS(tblDados[País],LEFT($E$5,3),tblDados[Liga],TRIM(MID($E$5,7,99)),tblDados[Janela_12_Liga],1),0) -> 0.041237113 | H14: ="Base: "&COUNTIFS(tblDados[País],LEFT($E$5,3),tblDados[Liga],TRIM(MID($E$5,7,99)),tblDados[Janela_12_Liga],1)&" jogos" -> Base: 97 jogos
A15: Exatamente 1 gol | B15: {=IFERROR(SUMPRODUCT((tblDados[Mandante]=$B$5)*(tblDados[Janela_12_Mandante]=1)*((tblDados[GM_M]+tblDados[GS_M])=1))/B10,0)} -> 0.4 | C15: {=IFERROR(SUMPRODUCT((tblDados[Visitante]=$B$6)*(tblDados[Janela_12_Visitante]=1)*((tblDados[GM_V]+tblDados[GS_V])=1))/C10,0)} -> 0 | D15: =AVERAGE(B15,C15) -> 0.2 | F15: Empírico ajustado | G15: =AVERAGE((B10*B14+5*G14)/(B10+5),(C10*C14+5*G14)/(C10+5)) -> 0.020618557 | H15: =IF(G15>10%,"Confirma risco elevado","Não confirma veto") -> Não confirma veto
A16: 2+ gols | B16: {=IFERROR(SUMPRODUCT((tblDados[Mandante]=$B$5)*(tblDados[Janela_12_Mandante]=1)*((tblDados[GM_M]+tblDados[GS_M])>=2))/B10,0)} -> 0.6 | C16: {=IFERROR(SUMPRODUCT((tblDados[Visitante]=$B$6)*(tblDados[Janela_12_Visitante]=1)*((tblDados[GM_V]+tblDados[GS_V])>=2))/C10,0)} -> 1 | D16: =AVERAGE(B16,C16) -> 0.8 | F16: Confirmação dupla | G16: =--AND(G11>10%,G15>10%) -> 0 | H16: =IF(G16=1,"VETO CONFIRMADO","SEM CONFIRMAÇÃO DUPLA") -> SEM CONFIRMAÇÃO DUPLA
A17: BTTS | B17: =IFERROR(COUNTIFS(tblDados[Mandante],$B$5,tblDados[GM_M],">0",tblDados[GS_M],">0",tblDados[Janela_12_Mandante],1)/B10,0) -> 0.6 | C17: =IFERROR(COUNTIFS(tblDados[Visitante],$B$6,tblDados[GM_V],">0",tblDados[GS_V],">0",tblDados[Janela_12_Visitante],1)/C10,0) -> 0.6 | D17: =AVERAGE(B17,C17) -> 0.6
A18: Últimos 5 — gols/jogo | B18: {=IFERROR(AVERAGE(_xlfn.TAKE(_xlfn.SORTBY(_xlfn._xlws.FILTER(tblDados[GM_M]+tblDados[GS_M],(tblDados[Mandante]=$B$5)*(tblDados[Janela_12_Mandante]=1)),_xlfn._xlws.FILTER(tblDados[Data],(tblDados[Mandante]=$B$5)*(tblDados[Janela_12_Mandante]=1)),-1),5)),0)} -> 2.6 | C18: {=IFERROR(AVERAGE(_xlfn.TAKE(_xlfn.SORTBY(_xlfn._xlws.FILTER(tblDados[GM_V]+tblDados[GS_V],(tblDados[Visitante]=$B$6)*(tblDados[Janela_12_Visitante]=1)),_xlfn._xlws.FILTER(tblDados[Data],(tblDados[Visitante]=$B$6)*(tblDados[Janela_12_Visitante]=1)),-1),5)),0)} -> 5.8 | D18: =AVERAGE(B18,C18) -> 4.2
A20: DISTRIBUIÇÃO E PROTEÇÃO DAS LINHAS
A21: Linha | B21: Green Poisson | C21: Sem Red Poisson | D21: Green alternativo | E21: Sem Red alternativo | F21: Green consenso | G21: Proteção consenso | H21: Leitura
A22: 0.5 | B22: ='Modelo 01'!B40 -> 0.98500442 | C22: ='Modelo 01'!C40 -> 0.98500442 | D22: ='Modelo 01'!D40 -> 0.98340035 | E22: ='Modelo 01'!F40 -> 0.98340035 | F22: ='Modelo 01'!G40 -> 0.98340035 | G22: ='Modelo 01'!H40 -> 0.98340035 | H22: ='Modelo 01'!I40 -> GREEN ≥75%
A23: 0.75 | B23: ='Modelo 01'!B41 -> 0.922023 | C23: ='Modelo 01'!C41 -> 0.98500442 | D23: ='Modelo 01'!D41 -> 0.91700176 | E23: ='Modelo 01'!F41 -> 0.98340035 | F23: ='Modelo 01'!G41 -> 0.91700176 | G23: ='Modelo 01'!H41 -> 0.98340035 | H23: ='Modelo 01'!I41 -> GREEN ≥75%
A24: 1 | B24: ='Modelo 01'!B42 -> 0.922023 | C24: ='Modelo 01'!C42 -> 0.98500442 | D24: ='Modelo 01'!D42 -> 0.91700176 | E24: ='Modelo 01'!F42 -> 0.98340035 | F24: ='Modelo 01'!G42 -> 0.91700176 | G24: ='Modelo 01'!H42 -> 0.98340035 | H24: ='Modelo 01'!I42 -> GREEN ≥75%
A25: 1.25 | B25: ='Modelo 01'!B43 -> 0.922023 | C25: ='Modelo 01'!C43 -> 0.98500442 | D25: ='Modelo 01'!D43 -> 0.91700176 | E25: ='Modelo 01'!F43 -> 0.98340035 | F25: ='Modelo 01'!G43 -> 0.91700176 | G25: ='Modelo 01'!H43 -> 0.98340035 | H25: ='Modelo 01'!I43 -> GREEN ≥75%
A26: 1.5 | B26: ='Modelo 01'!B44 -> 0.922023 | C26: ='Modelo 01'!C44 -> 0.922023 | D26: ='Modelo 01'!D44 -> 0.91700176 | E26: ='Modelo 01'!F44 -> 0.91700176 | F26: ='Modelo 01'!G44 -> 0.91700176 | G26: ='Modelo 01'!H44 -> 0.91700176 | H26: ='Modelo 01'!I44 -> GREEN ≥75%
A27: 1.75 | B27: ='Modelo 01'!B45 -> 0.78976201 | C27: ='Modelo 01'!C45 -> 0.922023 | D27: ='Modelo 01'!D45 -> 0.78262366 | E27: ='Modelo 01'!F45 -> 0.91700176 | F27: ='Modelo 01'!G45 -> 0.78262366 | G27: ='Modelo 01'!H45 -> 0.91700176 | H27: ='Modelo 01'!I45 -> GREEN ≥75%
A28: 2 | B28: ='Modelo 01'!B46 -> 0.78976201 | C28: ='Modelo 01'!C46 -> 0.922023 | D28: ='Modelo 01'!D46 -> 0.78262366 | E28: ='Modelo 01'!F46 -> 0.91700176 | F28: ='Modelo 01'!G46 -> 0.78262366 | G28: ='Modelo 01'!H46 -> 0.91700176 | H28: ='Modelo 01'!I46 -> GREEN ≥75%
A29: 2.25 | B29: ='Modelo 01'!B47 -> 0.78976201 | C29: ='Modelo 01'!C47 -> 0.922023 | D29: ='Modelo 01'!D47 -> 0.78262366 | E29: ='Modelo 01'!F47 -> 0.91700176 | F29: ='Modelo 01'!G47 -> 0.78262366 | G29: ='Modelo 01'!H47 -> 0.91700176 | H29: ='Modelo 01'!I47 -> GREEN ≥75%
A30: 2.5 | B30: ='Modelo 01'!B48 -> 0.78976201 | C30: ='Modelo 01'!C48 -> 0.78976201 | D30: ='Modelo 01'!D48 -> 0.78262366 | E30: ='Modelo 01'!F48 -> 0.78262366 | F30: ='Modelo 01'!G48 -> 0.78262366 | G30: ='Modelo 01'!H48 -> 0.78262366 | H30: ='Modelo 01'!I48 -> GREEN ≥75%
A31: 2.75 | B31: ='Modelo 01'!B49 -> 0.60459663 | C31: ='Modelo 01'!C49 -> 0.78976201 | D31: ='Modelo 01'!D49 -> 0.59918688 | E31: ='Modelo 01'!F49 -> 0.78262366 | F31: ='Modelo 01'!G49 -> 0.59918688 | G31: ='Modelo 01'!H49 -> 0.78262366 | H31: ='Modelo 01'!I49 -> PROTEÇÃO ≥75%
A32: 3 | B32: ='Modelo 01'!B50 -> 0.60459663 | C32: ='Modelo 01'!C50 -> 0.78976201 | D32: ='Modelo 01'!D50 -> 0.59918688 | E32: ='Modelo 01'!F50 -> 0.78262366 | F32: ='Modelo 01'!G50 -> 0.59918688 | G32: ='Modelo 01'!H50 -> 0.78262366 | H32: ='Modelo 01'!I50 -> PROTEÇÃO ≥75%
A34: CONCLUSÃO TÉCNICA
A35: =IF($G$16=1,"VETO CONFIRMADO: distribuições e histórico casa/fora apontam risco de 0 x 0 acima de 10%.",IF($G$11>10%,"DIVERGÊNCIA: o pior modelo supera 10%, mas o histórico casa/fora não confirma o veto. Priorizar a menor linha realmente disponível e máxima proteção.","SEM VETO POR 0 x 0: modelos e histórico não confirmam risco impeditivo. Avaliar somente as linhas realmente disponíveis, priorizando a maior probabilidade de acerto.")) -> SEM VETO POR 0 x 0: modelos e histórico não confirmam risco impeditivo. Avaliar somente as linhas realmente disponíveis, priorizando a maior probabilidade de acerto.
A38: Regra operacional | B38: A linha e a odd disponíveis devem ser informadas antes da decisão final. Odd/EV entram somente após a aprovação técnica por probabilidade de acerto.

Sheet Bilhetes
A1: BILHETES — DECISÕES PRÉ E PÓS-JOGO
A2: Unidade R$ 0,50 · análise, odds recebidas, escolha e resultado preservados
A3: PLACAR: digite os gols nas células azul-claro
A4: 46242 | C4: 1. Magic United × Rochedale Rovers
A5: AUS - NPL Queensland | E5: Data/Hora | G5: A definir
A6: MODELO | B6: λ 4,04 · Over 2,0: 86,8% · Over 2,25: 83,8% · Over 2,5: 80,7% | E6: Técnica | F6: Over 2,50 | G6: Orientação | H6: Analisar Over 2,50
A7: ODDS | B7: Over 2,0 @ 1,13 | Over 2,25 @ 1,124 | Over 2,5 @ 1,25
A8: DECISÃO | B8: Over 2,0 @ 1,13 | D8: Motivo | E8: Linha conservadora; proteção com devolução em exatamente 2 gols
A9: BILHETE | B9: Over 2,00 | C9: Odd | D9: 1.13 | E9: Stake | F9: 0.5 | G9: Status | H9: =IF(C10="","Pendente","Finalizado") -> Finalizado
A10: PLACAR | B10: Mandante | C10: 2 | D10: Visitante | E10: 1 | F10: Total | G10: =IF(OR(C10="",E10=""),"",C10+E10) -> 3
A11: LIQUIDAÇÃO | B11: Resultado | C11: =IF(G10="","",IF(G10>2,"Green",IF(G10=2,"Devolvida","Red"))) -> Green | D11: P/L | E11: =IF(C11="","",IF(C11="Green",F9*(D9-1),IF(C11="Red",-F9,IF(C11="Meio Green",F9*(D9-1)/2,IF(C11="Meio Red",-F9/2,IF(C11="Devolvida",0,"")))))) -> 0.065 | F11: Escolha conservadora; 2 gols = devolução
A13: 46242 | C13: 2. Brisbane Olympic FC × Moreton City Excelsior
A14: AUS - NPL Queensland | E14: Data/Hora | G14: A definir
A15: MODELO | B15: λ 3,12 · Over 1,5: 81,8% · Over 1,75: 76,4% · Over 2,0: 71,0% | E15: Técnica | F15: Over 1,50 | G15: Orientação | H15: Analisar Over 1,50
A16: ODDS | B16: Over 1,5 @ 1,10 | Over 1,75 @ 1,11 | Over 2,0 @ 1,125
A17: DECISÃO | B17: Over 2,00 @ 1,125 | D17: Motivo | E17: Proteção por devolução em 2 gols; diferença pequena de odd para linhas inferiores
A18: BILHETE | B18: Over 2,00 | C18: Odd | D18: 1.125 | E18: Stake | F18: 0.5 | G18: Status | H18: =IF(C19="","Pendente","Finalizado") -> Finalizado
A19: PLACAR | B19: Mandante | C19: 1 | D19: Visitante | E19: 2 | F19: Total | G19: =IF(OR(C19="",E19=""),"",C19+E19) -> 3
A20: LIQUIDAÇÃO | B20: Resultado | C20: =IF(G19="","",IF(G19>2,"Green",IF(G19=2,"Devolvida","Red"))) -> Green | D20: P/L | E20: =IF(C20="","",IF(C20="Green",F18*(D18-1),IF(C20="Red",-F18,IF(C20="Meio Green",F18*(D18-1)/2,IF(C20="Meio Red",-F18/2,IF(C20="Devolvida",0,"")))))) -> 0.0625
A22: 46242 | C22: 3. Brisbane City × Gold Coast Utd
A23: AUS - NPL Queensland | E23: Data/Hora | G23: A definir
A24: MODELO | B24: λ 3,61 · Over 1,5: 87,5% · Over 1,75: 83,1% · Over 2,0: 78,7% · Over 2,25: 74,3% · Over 2,5: 69,9% | E24: Técnica | F24: Over 2,50 | G24: Orientação | H24: Analisar Over 2,50
A25: ODDS | B25: Over 1,5 @ 1,115 | Over 1,75 @ 1,13 | Over 2,0 @ 1,15 | Over 2,25 @ 1,1275 | Over 2,5 @ 1,40
A26: DECISÃO | B26: Over 2,00 @ 1,15 | D26: Motivo | E26: Revisão operacional: preserva a projeção de 3+ gols, com devolução se houver exatamente 2
A27: BILHETE | B27: Over 2,00 | C27: Odd | D27: 1.15 | E27: Stake | F27: 0.5 | G27: Status | H27: =IF(C28="","Pendente","Finalizado") -> Finalizado
A28: PLACAR | B28: Mandante | C28: 2 | D28: Visitante | E28: 0 | F28: Total | G28: =IF(OR(C28="",E28=""),"",C28+E28) -> 2
A29: LIQUIDAÇÃO | B29: Resultado | C29: =IF(G28="","",IF(G28>2,"Green",IF(G28=2,"Devolvida","Red"))) -> Devolvida | D29: P/L | E29: =IF(C29="","",IF(C29="Green",F27*(D27-1),IF(C29="Red",-F27,IF(C29="Meio Green",F27*(D27-1)/2,IF(C29="Meio Red",-F27/2,IF(C29="Devolvida",0,"")))))) -> 0
A31: 46242 | C31: 4. Eastern Suburbs × Wynnum Wolves
A32: AUS - NPL Queensland | E32: Data/Hora | G32: A definir
A33: MODELO | B33: λ 3,75 · Over 1,5: 88,8% · Over 1,75: 84,7% · Over 2,0: 80,6% · Over 2,25: 76,4% · Over 2,5: 72,3% | E33: Técnica | F33: Over 2,50 | G33: Orientação | H33: Analisar Over 2,50
A34: ODDS | B34: Over 1,5 @ 1,125 | Over 1,75 @ 1,14 | Over 2,0 @ 1,16 | Over 2,25 @ 1,30 | Over 2,5 @ 1,425
A35: DECISÃO | B35: Over 2,25 @ 1,30 | D35: Motivo | E35: Faixa moderada: 3+ gols = green; exatamente 2 = meio red; preserva parte do ganho de odd
A36: BILHETE | B36: Over 2,25 | C36: Odd | D36: 1.3 | E36: Stake | F36: 0.5 | G36: Status | H36: =IF(C37="","Pendente","Finalizado") -> Finalizado
A37: PLACAR | B37: Mandante | C37: 0 | D37: Visitante | E37: 0 | F37: Total | G37: =IF(OR(C37="",E37=""),"",C37+E37) -> 0
A38: LIQUIDAÇÃO | B38: Resultado | C38: =IF(G37="","",IF(G37>=3,"Green",IF(G37=2,"Meio Red","Red"))) -> Red | D38: P/L | E38: =IF(C38="","",IF(C38="Green",F36*(D36-1),IF(C38="Red",-F36,IF(C38="Meio Green",F36*(D36-1)/2,IF(C38="Meio Red",-F36/2,IF(C38="Devolvida",0,"")))))) -> -0.5
A40: 46242 | C40: 5. Gold Coast Knights × Peninsula Power
A41: AUS - NPL Queensland | E41: Data/Hora | G41: A definir
A42: MODELO | B42: λ 3,33 · Over 1,5: 84,5% · Over 1,75: 79,6% · Over 2,0: 74,6% · Over 2,25: 69,7% | E42: Técnica | F42: Over 1,50 | G42: Orientação | H42: Analisar Over 1,50
A43: ODDS | B43: Over 1,5 @ 1,15 | Over 1,75 @ 1,17 | Over 2,0 @ 1,22 | Over 2,25 @ 1,35
A44: DECISÃO | B44: Over 2,00 @ 1,22 | D44: Motivo | E44: Revisão consistente com técnica Over 1,5: exatamente 2 gols devolvem a stake
A45: BILHETE | B45: Over 2,00 | C45: Odd | D45: 1.22 | E45: Stake | F45: 0.5 | G45: Status | H45: =IF(C46="","Pendente","Finalizado") -> Finalizado
A46: PLACAR | B46: Mandante | C46: 2 | D46: Visitante | E46: 2 | F46: Total | G46: =IF(OR(C46="",E46=""),"",C46+E46) -> 4
A47: LIQUIDAÇÃO | B47: Resultado | C47: =IF(G46="","",IF(G46>2,"Green",IF(G46=2,"Devolvida","Red"))) -> Green | D47: P/L | E47: =IF(C47="","",IF(C47="Green",F45*(D45-1),IF(C47="Red",-F45,IF(C47="Meio Green",F45*(D45-1)/2,IF(C47="Meio Red",-F45/2,IF(C47="Devolvida",0,"")))))) -> 0.11
A49: 46242 | C49: 6. Croydon × Sturt Lions
A50: AUS - NPL South Australia | E50: Data/Hora | G50: A definir
A51: MODELO | B51: λ 3,70 · Over 1,75: 84,1% · Over 2,0: 79,9% · Over 2,25: 75,7% · Over 2,5: 71,5% | E51: Técnica | F51: Over 2,50 | G51: Orientação | H51: Analisar Over 2,50
A52: ODDS | B52: Over 1,75 @ 1,125 | Over 2,0 @ 1,14 | Over 2,25 @ 1,26 | Over 2,5 @ 1,377
A53: DECISÃO | B53: Over 2,25 @ 1,26 | D53: Motivo | E53: Revisão moderada: mantém exposição a 3+ gols e reduz o dano com exatamente 2 gols para meio red
A54: BILHETE | B54: Over 2,25 | C54: Odd | D54: 1.26 | E54: Stake | F54: 0.5 | G54: Status | H54: =IF(C55="","Pendente","Finalizado") -> Finalizado
A55: PLACAR | B55: Mandante | C55: 1 | D55: Visitante | E55: 1 | F55: Total | G55: =IF(OR(C55="",E55=""),"",C55+E55) -> 2
A56: LIQUIDAÇÃO | B56: Resultado | C56: =IF(G55="","",IF(G55>=3,"Green",IF(G55=2,"Meio Red","Red"))) -> Meio Red | D56: P/L | E56: =IF(C56="","",IF(C56="Green",F54*(D54-1),IF(C56="Red",-F54,IF(C56="Meio Green",F54*(D54-1)/2,IF(C56="Meio Red",-F54/2,IF(C56="Devolvida",0,"")))))) -> -0.25
A58: 46242 | C58: 7. Bayswater City × Sorrento FC
A59: AUS - NPL Western Australia | E59: Data/Hora | G59: 0.125
A60: MODELO | B60: λ 3,31 · Over 1,5: 84,3% · Over 1,75: 79,3% · Over 2,0: 74,3% | E60: Técnica | F60: Over 1,50 | G60: Orientação | H60: Analisar Over 1,50
A61: ODDS | B61: Over 1,5 @ 1,115 | Over 1,75 @ 1,125 | Over 2,0 @ 1,15
A62: DECISÃO | B62: Over 2,00 @ 1,15 | D62: Motivo | E62: Proteção por devolução em 2 gols; λ 3,31 e 64,3% de 3+ gols
A63: BILHETE | B63: Over 2,00 | C63: Odd | D63: 1.15 | E63: Stake | F63: 0.5 | G63: Status | H63: =IF(C64="","Pendente","Finalizado") -> Finalizado
A64: PLACAR | B64: Mandante | C64: 7 | D64: Visitante | E64: 1 | F64: Total | G64: =IF(OR(C64="",E64=""),"",C64+E64) -> 8
A65: LIQUIDAÇÃO | B65: Resultado | C65: =IF(G64="","",IF(G64>2,"Green",IF(G64=2,"Devolvida","Red"))) -> Green | D65: P/L | E65: =IF(C65="","",IF(C65="Green",F63*(D63-1),IF(C65="Red",-F63,IF(C65="Meio Green",F63*(D63-1)/2,IF(C65="Meio Red",-F63/2,IF(C65="Devolvida",0,"")))))) -> 0.075
A67: 46242 | C67: 8. MuSa × AIFK
A68: FIN - Kakkonen B | E68: Data/Hora | G68: A definir
A69: MODELO | B69: λ 3,13 · Over 1,5: 81,9% · Over 1,75: 76,5% · Over 2,0: 71,1% · Over 2,25: 65,8% · Over 2,5: 60,4% | E69: Técnica | F69: Over 1,50 | G69: Orientação | H69: Analisar Over 1,50
A70: ODDS | B70: Over 1,75 @ 1,10 | Over 2,0 @ 1,11 | Over 2,25 @ 1,21 | Over 2,5 @ 1,325
A71: DECISÃO | B71: Over 2,00 @ 1,11 | D71: Motivo | E71: Faixa moderada e inteira: exatamente 2 gols devolvem; mantém proximidade da técnica Over 1,5
A72: BILHETE | B72: Over 2,00 | C72: Odd | D72: 1.11 | E72: Stake | F72: 0.5 | G72: Status | H72: =IF(C73="","Pendente","Finalizado") -> Finalizado
A73: PLACAR | B73: Mandante | C73: 1 | D73: Visitante | E73: 2 | F73: Total | G73: =IF(OR(C73="",E73=""),"",C73+E73) -> 3
A74: LIQUIDAÇÃO | B74: Resultado | C74: =IF(G73="","",IF(G73>2,"Green",IF(G73=2,"Devolvida","Red"))) -> Green | D74: P/L | E74: =IF(C74="","",IF(C74="Green",F72*(D72-1),IF(C74="Red",-F72,IF(C74="Meio Green",F72*(D72-1)/2,IF(C74="Meio Red",-F72/2,IF(C74="Devolvida",0,"")))))) -> 0.055
A76: 46242 | C76: 9. HIFK × PuiU
A77: FIN - Kakkonen A | E77: Data/Hora | G77: A definir
A78: MODELO | B78: λ 3,79 · Over 2,0: 81,0% · Over 2,25: 77,0% · Over 2,5: 72,9% · Over 2,75: 67,9% | E78: Técnica | F78: Over 2,50 | G78: Orientação | H78: Analisar Over 2,50
A79: ODDS | B79: Over 2,0 @ 1,10 | Over 2,25 @ 1,19 | Over 2,5 @ 1,30 | Over 2,75 @ 1,325
A80: DECISÃO | B80: Over 2,25 @ 1,19 | D80: Motivo | E80: Faixa moderada abaixo da técnica: 3+ gols = green; exatamente 2 = meio red
A81: BILHETE | B81: Over 2,25 | C81: Odd | D81: 1.19 | E81: Stake | F81: 0.5 | G81: Status | H81: =IF(C82="","Pendente","Finalizado") -> Finalizado
A82: PLACAR | B82: Mandante | C82: 2 | D82: Visitante | E82: 2 | F82: Total | G82: =IF(OR(C82="",E82=""),"",C82+E82) -> 4
A83: LIQUIDAÇÃO | B83: Resultado | C83: =IF(G82="","",IF(G82>=3,"Green",IF(G82=2,"Meio Red","Red"))) -> Green | D83: P/L | E83: =IF(C83="","",IF(C83="Green",F81*(D81-1),IF(C83="Red",-F81,IF(C83="Meio Green",F81*(D81-1)/2,IF(C83="Meio Red",-F81/2,IF(C83="Devolvida",0,"")))))) -> 0.095
A85: 46242 | C85: 10. P-Iirot Rauma × GrIFK
A86: FIN - Kakkonen B | E86: Data/Hora | G86: A definir
A87: MODELO | B87: λ 3,57 · Over 1,5: 87,1% · Over 1,75: 82,6% · Over 2,0: 78,2% · Over 2,25: 73,7% · Over 2,5: 69,2% | E87: Técnica | F87: Over 1,50 | G87: Orientação | H87: Analisar Over 1,50
A88: ODDS | B88: Over 1,5 @ 1,115 | Over 1,75 @ 1,13 | Over 2,0 @ 1,15 | Over 2,25 @ 1,275
A89: DECISÃO | B89: Over 2,00 @ 1,15 | D89: Motivo | E89: Linha inteira moderada; exatamente 2 gols devolvem e 3+ confirmam o cenário central
A90: BILHETE | B90: Over 2,00 | C90: Odd | D90: 1.15 | E90: Stake | F90: 0.5 | G90: Status | H90: =IF(C91="","Pendente","Finalizado") -> Finalizado
A91: PLACAR | B91: Mandante | C91: 2 | D91: Visitante | E91: 0 | F91: Total | G91: =IF(OR(C91="",E91=""),"",C91+E91) -> 2
A92: LIQUIDAÇÃO | B92: Resultado | C92: =IF(G91="","",IF(G91>2,"Green",IF(G91=2,"Devolvida","Red"))) -> Devolvida | D92: P/L | E92: =IF(C92="","",IF(C92="Green",F90*(D90-1),IF(C92="Red",-F90,IF(C92="Meio Green",F90*(D90-1)/2,IF(C92="Meio Red",-F90/2,IF(C92="Devolvida",0,"")))))) -> 0
A94: 46242 | C94: 11. GBK Kokkola × Huima / Urho
A95: FIN - Kakkonen C | E95: Data/Hora | G95: A definir
A96: MODELO | B96: λ 3,75 · Over 2,25: 76,4% · Over 2,5: 72,3% · Over 2,75: 67,1% · Over 3,0: 62,0% | E96: Técnica | F96: Over 2,50 | G96: Orientação | H96: Analisar Over 2,50
A97: ODDS | B97: Over 2,25 @ 1,18 | Over 2,5 @ 1,275 | Over 2,75 @ 1,325 | Over 3,0 @ 1,375
A98: DECISÃO | B98: Over 2,25 @ 1,18 | D98: Motivo | E98: Revisão defensiva: 3+ gols = green; exatamente 2 = meio red; reduz risco de armadilha
A99: BILHETE | B99: Over 2,25 | C99: Odd | D99: 1.18 | E99: Stake | F99: 0.5 | G99: Status | H99: =IF(C100="","Pendente","Finalizado") -> Finalizado
A100: PLACAR | B100: Mandante | C100: 0 | D100: Visitante | E100: 3 | F100: Total | G100: =IF(OR(C100="",E100=""),"",C100+E100) -> 3
A101: LIQUIDAÇÃO | B101: Resultado | C101: =IF(G100="","",IF(G100>=3,"Green",IF(G100=2,"Meio Red","Red"))) -> Green | D101: P/L | E101: =IF(C101="","",IF(C101="Green",F99*(D99-1),IF(C101="Red",-F99,IF(C101="Meio Green",F99*(D99-1)/2,IF(C101="Meio Red",-F99/2,IF(C101="Devolvida",0,"")))))) -> 0.09
A103: 46242 | C103: 12. TP-47 × Närpes Kraft
A104: FIN - Kakkonen C | E104: Data/Hora | G104: A definir
A105: MODELO | B105: λ 5,29 · Over 2,25: 91,5% · Over 2,5: 89,7% · Over 2,75: 86,6% · Over 3,0: 83,5% | E105: Técnica | F105: Over 3,00 | G105: Orientação | H105: Analisar Over 3,00
A106: ODDS | B106: Over 2,25 @ 1,18 | Over 2,5 @ 1,275 | Over 2,75 @ 1,325 | Over 3,0 @ 1,375
A107: DECISÃO | B107: Over 2,50 @ 1,275 | D107: Motivo | E107: Escolha conservadora abaixo da técnica Over 3,0; 3+ gols confirmam o bilhete
A108: BILHETE | B108: Over 2,50 | C108: Odd | D108: 1.275 | E108: Stake | F108: 0.5 | G108: Status | H108: =IF(C109="","Pendente","Finalizado") -> Finalizado
A109: PLACAR | B109: Mandante | C109: 2 | D109: Visitante | E109: 1 | F109: Total | G109: =IF(OR(C109="",E109=""),"",C109+E109) -> 3
A110: LIQUIDAÇÃO | B110: Resultado | C110: =IF(G109="","",IF(G109>2.5,"Green","Red")) -> Green | D110: P/L | E110: =IF(C110="","",IF(C110="Green",F108*(D108-1),IF(C110="Red",-F108,IF(C110="Meio Green",F108*(D108-1)/2,IF(C110="Meio Red",-F108/2,IF(C110="Devolvida",0,"")))))) -> 0.1375
A112: 46242 | C112: 13. SA Bulo Bulo × Nacional Potosí
...

Sheet Backtest
A1: HISTÓRICO — LINHA USADA vs. MELHOR APROVEITAMENTO NOS GREENS
A2: Data | B2: Confronto | C2: Liga | D2: Placar | E2: Odd | F2: P/L (R$) | G2: Gols | H2: Usada | I2: Melhor G | J2: Odd M.G. | K2: P/L M.G. | L2: Fonte odds | M2: Δ linha | N2: O0,50 | O2: O0,75 | P2: O1,00 | Q2: O1,25 | R2: O1,50 | S2: O1,75 | T2: O2,00 | U2: O2,25 | V2: O2,50 | W2: O2,75 | X2: O3,00 | Y2: Análise da Entrada
